Workbook

Sheet Demo
A3: RVNL | B3: 2207
A4: COCHINSHIP | B4: 657
A5: INOXWIND | B5: 4343
A6: TRENT | B6: 123
A7: HUDCO | B7: 4107
A8: GODFRYPHLP | B8: 201
A9: OFSS | B9: 92
A10: GVT&D | B10: 800
A11: IREDA | B11: 5613
A12: NETWEB | B12: 409
A13: JUBLPHARMA | B13: 791
A14: DIXON | B14: 56
... A22: POLICYBZR | B22: 425
C25: Money Allocated | D25: 15002972 | E25: Amol ji | J25: Vishal
A27: Stock | B27: targetWeight | C27: currentPrice | D27: currentQty | E27: targetQty | F27: action | G27: actionQty | H27: buy/sell price | I27: Buy/Sell Qty | J27: Price | K27: Value
A28: RVNL | B28: 0.043461605 | C28: 341.65 | D28: =Iferror(VLOOKUP(A28,$A$3:$B$22,2,0),"") -> 2207 | E28: 1857 | F28: SELL | G28: -350 | H28: 339.3114 | I28: -350 | J28: 339.3114 | K28: =I28*J28 -> -118758.99
A29: COCHINSHIP | B29: 0.044291035 | C29: 1332.1 | D29: =Iferror(VLOOKUP(A29,$A$3:$B$22,2,0),"") -> 657 | E29: 503 | F29: SELL | G29: -154 | H29: 1270.45 | I29: -154 | J29: 1270.45 | K29: =I29*J29 -> -195649.3
A30: INOXWIND | B30: 0 | C30: 170.56 | D30: =Iferror(VLOOKUP(A30,$A$3:$B$22,2,0),"") -> 4343 | E30: 0 | F30: SELL | G30: -4343 | H30: 155.4113 | I30: -4343 | J30: 155.4113 | K30: =I30*J30 -> -674951.28
A31: TRENT | B31: 0 | C31: 4990 | D31: =Iferror(VLOOKUP(A31,$A$3:$B$22,2,0),"") -> 123 | E31: 0 | F31: SELL | G31: -123 | H31: 5031.9476 | I31: -123 | J31: 5031.9476 | K31: =I31*J31 -> -618929.55
A32: HUDCO | B32: 0 | C32: 182 | D32: =Iferror(VLOOKUP(A32,$A$3:$B$22,2,0),"") -> 4107 | E32: 0 | F32: SELL | G32: -4107 | H32: 182.3782 | I32: -4107 | J32: 182.3782 | K32: =I32*J32 -> -749027.27
A33: GODFRYPHLP | B33: 0.056301762 | C33: 5305.05 | D33: =Iferror(VLOOKUP(A33,$A$3:$B$22,2,0),"") -> 201 | E33: 154 | F33: SELL | G33: -47 | H33: 5290 | I33: -47 | J33: 5290 | K33: =I33*J33 -> -248630
A34: OFSS | B34: 0 | C34: 7538 | D34: =Iferror(VLOOKUP(A34,$A$3:$B$22,2,0),"") -> 92 | E34: 0 | F34: SELL | G34: -92 | H34: 7911.05 | I34: -92 | J34: 7911.05 | K34: =I34*J34 -> -727816.6
A35: GVT&D | B35: 0.049489154 | C35: 1427.9 | D35: =Iferror(VLOOKUP(A35,$A$3:$B$22,2,0),"") -> 800 | E35: 585 | F35: SELL | G35: -215 | H35: 1387.1772 | I35: -215 | J35: 1387.1772 | K35: =I35*J35 -> -298243.1
A36: IREDA | B36: 0 | C36: 149.4 | D36: =Iferror(VLOOKUP(A36,$A$3:$B$22,2,0),"") -> 5613 | E36: 0 | F36: SELL | G36: -5613 | H36: 151.9669 | I36: -5613 | J36: 151.9669 | K36: =I36*J36 -> -852990.21
A37: NETWEB | B37: 0 | C37: 1593.5 | D37: =Iferror(VLOOKUP(A37,$A$3:$B$22,2,0),"") -> 409 | E37: 0 | F37: SELL | G37: -409 | H37: 1586.8647 | I37: -409 | J37: 1586.8647 | K37: =I37*J37 -> -649027.66
A38: JUBLPHARMA | B38: 0.041015626 | C38: 910 | D38: =Iferror(VLOOKUP(A38,$A$3:$B$22,2,0),"") -> 791 | E38: 676 | F38: SELL | G38: -115 | H38: 918.2015 | I38: -115 | J38: 918.2015 | K38: =I38*J38 -> -105593.17
A39: DIXON | B39: 0.059074288 | C39: 13888 | D39: =Iferror(VLOOKUP(A39,$A$3:$B$22,2,0),"") -> 56 | E39: 64 | F39: BUY | G39: 8 | H39: 0 | I39: 8 | J39: 13888 | K39: =I39*J39 -> 111104
... A60: VEDL | B60: 0.041242807 | C60: 445 | D60: =Iferror(VLOOKUP(A60,$A$3:$B$22,2,0),"") | E60: 1390 | F60: BUY | G60: 1390 | H60: 0 | I60: 1390 | J60: 445 | K60: =I60*J60 -> 618550
K61: =SUM(K26:K60) -> -2908.2697

Sheet TRADE_INSTRUCTIONS_HPC39_7
A1: Money Allocated | B1: 21940415
C2: Amol Ji | H2: Vishal Ji
A3: Symbol | B3: targetWeight | C3: currentPrice | D3: currentQty | E3: targetQty | F3: action | G3: actionQty | H3: Buy/Sell Qty | I3: Price | J3: Value | K3: NET QTY
A4: ANANDRATHI | B4: 0.027484492 | C4: 2955 | D4: 213 | E4: =ROUND($B$1 * B4 / C4, 0) -> 204 | F4: =IF(G4>0, "BUY", IF(G4<0, "SELL", "FLAT")) -> SELL | G4: =E4-D4 -> -9 | H4: -9 | I4: 2946.7 | J4: =I4 * H4 -> -26520.3 | K4: =D4+H4 -> 204
A5: ASTERDM | B5: 0 | C5: 544.65 | D5: 1041 | E5: =ROUND($B$1 * B5 / C5, 0) -> 0 | F5: =IF(G5>0, "BUY", IF(G5<0, "SELL", "FLAT")) -> SELL | G5: =E5-D5 -> -1041 | H5: -1041 | I5: 530.3 | J5: =I5 * H5 -> -552042.3
A6: BDL | B6: 0 | C6: 1322.3 | D6: 416 | E6: =ROUND($B$1 * B6 / C6, 0) -> 0 | F6: =IF(G6>0, "BUY", IF(G6<0, "SELL", "FLAT")) -> SELL | G6: =E6-D6 -> -416 | H6: -416 | I6: 1251.3 | J6: =I6 * H6 -> -520540.8
A7: BLUEJET | B7: 0 | C7: 422 | D7: 873 | E7: =ROUND($B$1 * B7 / C7, 0) -> 0 | F7: =IF(G7>0, "BUY", IF(G7<0, "SELL", "FLAT")) -> SELL | G7: =E7-D7 -> -873 | H7: -873 | I7: 406.35 | J7: =I7 * H7 -> -354743.55
A8: BSE | B8: 0.025145267 | C8: 2852 | D8: 325 | E8: =ROUND($B$1 * B8 / C8, 0) -> 193 | F8: =IF(G8>0, "BUY", IF(G8<0, "SELL", "FLAT")) -> SELL | G8: =E8-D8 -> -132 | H8: -132 | I8: 2852.4 | J8: =I8 * H8 -> -376516.8 | K8: =D8+H8 -> 193
A9: CEATLTD | B9: 0 | C9: 3883.9 | D9: 143 | E9: =ROUND($B$1 * B9 / C9, 0) -> 0 | F9: =IF(G9>0, "BUY", IF(G9<0, "SELL", "FLAT")) -> SELL | G9: =E9-D9 -> -143 | H9: -143 | I9: 3874.6 | J9: =I9 * H9 -> -554067.8
A10: CHOICEIN | B10: 0 | C10: 782 | D10: 879 | E10: =ROUND($B$1 * B10 / C10, 0) -> 0 | F10: =IF(G10>0, "BUY", IF(G10<0, "SELL", "FLAT")) -> SELL | G10: =E10-D10 -> -879 | H10: -879 | I10: 778.49 | J10: =I10 * H10 -> -684292.71
A11: CREDITACC | B11: 0 | C11: 1318.6 | D11: 550 | E11: =ROUND($B$1 * B11 / C11, 0) -> 0 | F11: =IF(G11>0, "BUY", IF(G11<0, "SELL", "FLAT")) -> SELL | G11: =E11-D11 -> -550 | H11: -550 | I11: 1336.4 | J11: =I11 * H11 -> -735020
A12: ECLERX | B12: 0.026040048 | C12: 4955 | D12: 159 | E12: =ROUND($B$1 * B12 / C12, 0) -> 115 | F12: =IF(G12>0, "BUY", IF(G12<0, "SELL", "FLAT")) -> SELL | G12: =E12-D12 -> -44 | H12: -44 | I12: 4461.92 | J12: =I12 * H12 -> -196324.48 | K12: =D12+H12 -> 115
A13: FORTIS | B13: 0 | C13: 864.9 | D13: 721 | E13: =ROUND($B$1 * B13 / C13, 0) -> 0 | F13: =IF(G13>0, "BUY", IF(G13<0, "SELL", "FLAT")) -> SELL | G13: =E13-D13 -> -721 | H13: -721 | I13: 854.35 | J13: =I13 * H13 -> -615986.35
A14: GPIL | B14: 0 | C14: 253 | D14: 2042 | E14: =ROUND($B$1 * B14 / C14, 0) -> 0 | F14: =IF(G14>0, "BUY", IF(G14<0, "SELL", "FLAT")) -> SELL | G14: =E14-D14 -> -2042 | H14: -2042 | I14: 255.02 | J14: =I14 * H14 -> -520750.84
A15: GRSE | B15: 0.037304193 | C15: 2545 | D15: 362 | E15: =ROUND($B$1 * B15 / C15, 0) -> 322 | F15: =IF(G15>0, "BUY", IF(G15<0, "SELL", "FLAT")) -> SELL | G15: =E15-D15 -> -40 | H15: -40 | I15: 2440.3 | J15: =I15 * H15 -> -97612 | K15: =D15+H15 -> 322
A16: GVT&D | B16: 0.03984902 | C16: 3460 | D16: 281 | E16: =ROUND($B$1 * B16 / C16, 0) -> 253 | F16: =IF(G16>0, "BUY", IF(G16<0, "SELL", "FLAT")) -> SELL | G16: =E16-D16 -> -28 | H16: -28 | I16: 3521.2 | J16: =I16 * H16 -> -98593.6 | K16: =D16+H16 -> 253
A17: INTELLECT | B17: 0 | C17: 814 | D17: 611 | E17: =ROUND($B$1 * B17 / C17, 0) -> 0 | F17: =IF(G17>0, "BUY", IF(G17<0, "SELL", "FLAT")) -> SELL | G17: =E17-D17 -> -611 | H17: -611 | I17: 776.56 | J17: =I17 * H17 -> -474478.16
A18: ITI | B18: 0 | C18: 289.4 | D18: 2475 | E18: =ROUND($B$1 * B18 / C18, 0) -> 0 | F18: =IF(G18>0, "BUY", IF(G18<0, "SELL", "FLAT")) -> SELL | G18: =E18-D18 -> -2475 | H18: -2475 | I18: 292.99 | J18: =I18 * H18 -> -725150.25
A19: JKCEMENT | B19: 0 | C19: 5620 | D19: 92 | E19: =ROUND($B$1 * B19 / C19, 0) -> 0 | F19: =IF(G19>0, "BUY", IF(G19<0, "SELL", "FLAT")) -> SELL | G19: =E19-D19 -> -92 | H19: -92 | I19: 5662.01 | J19: =I19 * H19 -> -520904.92
A20: LAURUSLABS | B20: 0.02592641 | C20: 979.5 | D20: 1025 | E20: =ROUND($B$1 * B20 / C20, 0) -> 581 | F20: =IF(G20>0, "BUY", IF(G20<0, "SELL", "FLAT")) -> SELL | G20: =E20-D20 -> -444 | H20: -444 | I20: 961.95 | J20: =I20 * H20 -> -427105.8 | K20: =D20+H20 -> 581
A21: LTF | B21: 0.031271944 | C21: 284.9 | D21: 2643 | E21: =ROUND($B$1 * B21 / C21, 0) -> 2408 | F21: =IF(G21>0, "BUY", IF(G21<0, "SELL", "FLAT")) -> SELL | G21: =E21-D21 -> -235 | H21: -235 | I21: 279.4 | J21: =I21 * H21 -> -65659 | K21: =D21+H21 -> 2408
A22: MANAPPURAM | B22: 0 | C22: 290.25 | D22: 3149 | E22: =ROUND($B$1 * B22 / C22, 0) -> 0 | F22: =IF(G22>0, "BUY", IF(G22<0, "SELL", "FLAT")) -> SELL | G22: =E22-D22 -> -3149 | H22: -3149 | I22: 286.65 | J22: =I22 * H22 -> -902660.85
A23: MAZDOCK | B23: 0 | C23: 2455 | D23: 223 | E23: =ROUND($B$1 * B23 / C23, 0) -> 0 | F23: =IF(G23>0, "BUY", IF(G23<0, "SELL", "FLAT")) -> SELL | G23: =E23-D23 -> -223 | H23: -223 | I23: 2363.32 | J23: =I23 * H23 -> -527020.36
A24: MUTHOOTFIN | B24: 0.027135146 | C24: 3644.9 | D24: 255 | E24: =ROUND($B$1 * B24 / C24, 0) -> 163 | F24: =IF(G24>0, "BUY", IF(G24<0, "SELL", "FLAT")) -> SELL | G24: =E24-D24 -> -92 | H24: -92 | I24: 3583.61 | J24: =I24 * H24 -> -329692.12 | K24: =D24+H24 -> 163
A25: NAVINFLUOR | B25: 0 | C25: 6300 | D25: 151 | E25: =ROUND($B$1 * B25 / C25, 0) -> 0 | F25: =IF(G25>0, "BUY", IF(G25<0, "SELL", "FLAT")) -> SELL | G25: =E25-D25 -> -151 | H25: -151 | I25: 6321.5 | J25: =I25 * H25 -> -954546.5
A26: PAYTM | B26: 0 | C26: 1191.3 | D26: 715 | E26: =ROUND($B$1 * B26 / C26, 0) -> 0 | F26: =IF(G26>0, "BUY", IF(G26<0, "SELL", "FLAT")) -> SELL | G26: =E26-D26 -> -715 | H26: -715 | I26: 1201.9 | J26: =I26 * H26 -> -859358.5
A27: RBLBANK | B27: 0.032662107 | C27: 304.95 | D27: 3009 | E27: =ROUND($B$1 * B27 / C27, 0) -> 2350 | F27: =IF(G27>0, "BUY", IF(G27<0, "SELL", "FLAT")) -> SELL | G27: =E27-D27 -> -659 | H27: -659 | I27: 304.05 | J27: =I27 * H27 -> -200368.95 | K27: =D27+H27 -> 2350
A28: SYRMA | B28: 0 | C28: 818 | D28: 1033 | E28: =ROUND($B$1 * B28 / C28, 0) -> 0 | F28: =IF(G28>0, "BUY", IF(G28<0, "SELL", "FLAT")) -> SELL | G28: =E28-D28 -> -1033 | H28: -1033 | I28: 830.75 | J28: =I28 * H28 -> -858164.75
A29: FORCEMOT | B29: 0.069775136 | C29: 19950 | D29: 77 | E29: =ROUND($B$1 * B29 / C29, 0) -> 77 | F29: =IF(G29>0, "BUY", IF(G29<0, "SELL", "FLAT")) -> FLAT | G29: =E29-D29 -> 0 | H29: 0 | I29: 0 | J29: =I29 * H29 -> 0 | K29: =D29+H29 -> 77
A30: POWERINDIA | B30: 0.0329124 | C30: 19715 | D30: 37 | E30: =ROUND($B$1 * B30 / C30, 0) -> 37 | F30: =IF(G30>0, "BUY", IF(G30<0, "SELL", "FLAT")) -> FLAT | G30: =E30-D30 -> 0 | H30: 0 | I30: 0 | J30: =I30 * H30 -> 0 | K30: =D30+H30 -> 37
A31: ABCAPITAL | B31: 0.033441414 | C31: 346.9 | D31: 2030 | E31: =ROUND($B$1 * B31 / C31, 0) -> 2115 | F31: =IF(G31>0, "BUY", IF(G31<0, "SELL", "FLAT")) -> BUY | G31: =E31-D31 -> 85 | H31: 85 | I31: 341.35 | J31: =I31 * H31 -> 29014.75 | K31: =D31+H31 -> 2115
A32: ASAHIINDIA | B32: 0.026371026 | C32: 989.9 | D32: 0 | E32: =ROUND($B$1 * B32 / C32, 0) -> 584 | F32: =IF(G32>0, "BUY", IF(G32<0, "SELL", "FLAT")) -> BUY | G32: =E32-D32 -> 584 | H32: 584 | I32: 948.19 | J32: =I32 * H32 -> 553742.96 | K32: =D32+H32 -> 584
A33: ASHOKLEY | B33: 0.036566441 | C33: 200 | D33: 0 | E33: =ROUND($B$1 * B33 / C33, 0) -> 4011 | F33: =IF(G33>0, "BUY", IF(G33<0, "SELL", "FLAT")) -> BUY | G33: =E33-D33 -> 4011 | H33: 4011 | I33: 199.98 | J33: =I33 * H33 -> 802119.78 | K33: =D33+H33 -> 4011
A34: AUBANK | B34: 0.026578631 | C34: 982.5 | D34: 0 | E34: =ROUND($B$1 * B34 / C34, 0) -> 594 | F34: =IF(G34>0, "BUY", IF(G34<0, "SELL", "FLAT")) -> BUY | G34: =E34-D34 -> 594 | H34: 594 | I34: 981.73 | J34: =I34 * H34 -> 583147.62 | K34: =D34+H34 -> 594
A35: BEL | B35: 0.024532372 | C35: 438.4 | D35: 0 | E35: =ROUND($B$1 * B35 / C35, 0) -> 1228 | F35: =IF(G35>0, "BUY", IF(G35<0, "SELL", "FLAT")) -> BUY | G35: =E35-D35 -> 1228 | H35: 1228 | I35: 428.05 | J35: =I35 * H35 -> 525645.4 | K35: =D35+H35 -> 1228
A36: CANBK | B36: 0.025133409 | C36: 147.4 | D36: 0 | E36: =ROUND($B$1 * B36 / C36, 0) -> 3741 | F36: =IF(G36>0, "BUY", IF(G36<0, "SELL", "FLAT")) -> BUY | G36: =E36-D36 -> 3741 | H36: 3741 | I36: 147.23 | J36: =I36 * H36 -> 550787.43 | K36: =D36+H36 -> 3741
A37: CCL | B37: 0.027084339 | C37: 984.05 | D37: 0 | E37: =ROUND($B$1 * B37 / C37, 0) -> 604 | F37: =IF(G37>0, "BUY", IF(G37<0, "SELL", "FLAT")) -> BUY | G37: =E37-D37 -> 604 | H37: 604 | I37: 981.45 | J37: =I37 * H37 -> 592795.8 | K37: =D37+H37 -> 604
A38: CHENNPETRO | B38: 0.033103854 | C38: 841.6 | D38: 0 | E38: =ROUND($B$1 * B38 / C38, 0) -> 863 | F38: =IF(G38>0, "BUY", IF(G38<0, "SELL", "FLAT")) -> BUY | G38: =E38-D38 -> 863 | H38: 863 | I38: 901.9 | J38: =I38 * H38 -> 778339.7 | K38: =D38+H38 -> 863
A39: CRAFTSMAN | B39: 0.033041918 | C39: 7699 | D39: 0 | E39: =ROUND($B$1 * B39 / C39, 0) -> 94 | F39: =IF(G39>0, "BUY", IF(G39<0, "SELL", "FLAT")) -> BUY | G39: =E39-D39 -> 94 | H39: 94 | I39: 7794.5 | J39: =I39 * H39 -> 732683 | K39: =D39+H39 -> 94
A40: CUB | B40: 0.027179632 | C40: 297.1 | D40: 0 | E40: =ROUND($B$1 * B40 / C40, 0) -> 2007 | F40: =IF(G40>0, "BUY", IF(G40<0, "SELL", "FLAT")) -> BUY | G40: =E40-D40 -> 2007 | H40: 2007 | I40: 293.46 | J40: =I40 * H40 -> 588974.22 | K40: =D40+H40 -> 2007
... A44: JKTYRE | B44: 0.029448867 | C44: 534 | D44: 0 | E44: =ROUND($B$1 * B44 / C44, 0) -> 1210 | F44: =IF(G44>0, "BUY", IF(G44<0, "SELL", "FLAT")) -> BUY | G44: =E44-D44 -> 1210 | H44: 1210 | I44: 526.47 | J44: =I44 * H44 -> 637028.7 | K44: =D44+H44 -> 1210
A45: LLOYDSME | B45: 0 | C45: 1167 | D45: -96 | E45: =ROUND($B$1 * B45 / C45, 0) -> 0 | F45: =IF(G45>0, "BUY", IF(G45<0, "SELL", "FLAT")) -> BUY | G45: =E45-D45 -> 96 | H45: 96 | I45: 1235 | J45: =I45 * H45 -> 118560
A46: MCX | B46: 0.041344932 | C46: 2441 | D46: 0 | E46: =ROUND($B$1 * B46 / C46, 0) -> 372 | F46: =IF(G46>0, "BUY", IF(G46<0, "SELL", "FLAT")) -> BUY | G46: =E46-D46 -> 372 | H46: 372 | I46: 2354 | J46: =I46 * H46 -> 875688 | K46: =D46+H46 -> 372
A47: NATIONALUM | B47: 0.036777823 | C47: 371.5 | D47: 0 | E47: =ROUND($B$1 * B47 / C47, 0) -> 2172 | F47: =IF(G47>0, "BUY", IF(G47<0, "SELL", "FLAT")) -> BUY | G47: =E47-D47 -> 2172 | H47: 2172 | I47: 353.6 | J47: =I47 * H47 -> 768019.2 | K47: =D47+H47 -> 2172
A48: NETWEB | B48: 0.042646598 | C48: 3204.9 | D48: 201 | E48: =ROUND($B$1 * B48 / C48, 0) -> 292 | F48: =IF(G48>0, "BUY", IF(G48<0, "SELL", "FLAT")) -> BUY | G48: =E48-D48 -> 91 | H48: 91 | I48: 3057.7 | J48: =I48 * H48 -> 278250.7 | K48: =D48+H48 -> 292
A49: SHRIRAMFIN | B49: 0.030082787 | C49: 1000 | D49: 0 | E49: =ROUND($B$1 * B49 / C49, 0) -> 660 | F49: =IF(G49>0, "BUY", IF(G49<0, "SELL", "FLAT")) -> BUY | G49: =E49-D49 -> 660 | H49: 660 | I49: 990.1 | J49: =I49 * H49 -> 653466 | K49: =D49+H49 -> 660
A50: UNIONBANK | B50: 0.024704397 | C50: 174.6 | D50: 0 | E50: =ROUND($B$1 * B50 / C50, 0) -> 3104 | F50: =IF(G50>0, "BUY", IF(G50<0, "SELL", "FLAT")) -> BUY | G50: =E50-D50 -> 3104 | H50: 3104 | I50: 177.14 | J50: =I50 * H50 -> 549842.56 | K50: =D50+H50 -> 3104

Sheet TRADE_INSTRUCTIONS_HPC39_8_1_JU
A1: Money Allocated | B1: 21729167
C2: Amol Ji | I2: Vishal Ji
A3: Symbol | B3: targetWeight | C3: currentPrice | D3: currentQty | E3: targetQty | F3: action | G3: actionQty | I3: Buy/Sell Qty | J3: Price | K3: Value | L3: NET QTY
A4: ABCAPITAL | B4: 0.027114199 | C4: 391 | D4: 2041 | E4: =ROUND($B$1 * B4 / C4, 0) -> 1507 | F4: =IF(G4>0, "BUY", IF(G4<0, "SELL", "FLAT")) -> SELL | G4: =E4-D4 -> -534 | H4: =C4*G4 -> -208794 | I4: -534 | J4: 390.45 | K4: =J4 * I4 -> -208500.3 | L4: =D4+I4 -> 1507
A5: AMBER | B5: 0 | C5: 7448.5 | D5: 126 | E5: =ROUND($B$1 * B5 / C5, 0) -> 0 | F5: =IF(G5>0, "BUY", IF(G5<0, "SELL", "FLAT")) -> SELL | G5: =E5-D5 -> -126 | H5: =C5*G5 -> -938511 | I5: -126 | J5: 7446.5 | K5: =J5 * I5 -> -938259
A6: ASHOKLEY | B6: 0.028104541 | C6: 164.1 | D6: 3792 | E6: =ROUND($B$1 * B6 / C6, 0) -> 3721 | F6: =IF(G6>0, "BUY", IF(G6<0, "SELL", "FLAT")) -> SELL | G6: =E6-D6 -> -71 | H6: =C6*G6 -> -11651.1 | I6: -71 | J6: 165.2 | K6: =J6 * I6 -> -11729.2 | L6: =D6+I6 -> 3721
A7: AUBANK | B7: 0 | C7: 1065 | D7: 736 | E7: =ROUND($B$1 * B7 / C7, 0) -> 0 | F7: =IF(G7>0, "BUY", IF(G7<0, "SELL", "FLAT")) -> SELL | G7: =E7-D7 -> -736 | H7: =C7*G7 -> -783840 | I7: -736 | J7: 1058.1 | K7: =J7 * I7 -> -778761.6
A8: BEL | B8: 0 | C8: 414.8 | D8: 974 | E8: =ROUND($B$1 * B8 / C8, 0) -> 0 | F8: =IF(G8>0, "BUY", IF(G8<0, "SELL", "FLAT")) -> SELL | G8: =E8-D8 -> -974 | H8: =C8*G8 -> -404015.2 | I8: -974 | J8: 413.25 | K8: =J8 * I8 -> -402505.5
A9: BSE | B9: 0.03198469 | C9: 3937 | D9: 225 | E9: =ROUND($B$1 * B9 / C9, 0) -> 177 | F9: =IF(G9>0, "BUY", IF(G9<0, "SELL", "FLAT")) -> SELL | G9: =E9-D9 -> -48 | H9: =C9*G9 -> -188976 | I9: -48 | J9: 3938.7 | K9: =J9 * I9 -> -189057.6 | L9: =D9+I9 -> 177
A10: CANBK | B10: 0 | C10: 127.55 | D10: 3466 | E10: =ROUND($B$1 * B10 / C10, 0) -> 0 | F10: =IF(G10>0, "BUY", IF(G10<0, "SELL", "FLAT")) -> SELL | G10: =E10-D10 -> -3466 | H10: =C10*G10 -> -442088.3 | I10: -3466 | J10: 127.03 | K10: =J10 * I10 -> -440285.98
A11: DELHIVERY | B11: 0 | C11: 510.3 | D11: 1412 | E11: =ROUND($B$1 * B11 / C11, 0) -> 0 | F11: =IF(G11>0, "BUY", IF(G11<0, "SELL", "FLAT")) -> SELL | G11: =E11-D11 -> -1412 | H11: =C11*G11 -> -720543.6 | I11: -1412 | J11: 507.95 | K11: =J11 * I11 -> -717225.4
A12: FORCEMOT | B12: 0.030901086 | C12: 18795 | D12: 60 | E12: =ROUND($B$1 * B12 / C12, 0) -> 36 | F12: =IF(G12>0, "BUY", IF(G12<0, "SELL", "FLAT")) -> SELL | G12: =E12-D12 -> -24 | H12: =C12*G12 -> -451080 | I12: -24 | J12: 18841 | K12: =J12 * I12 -> -452184 | L12: =D12+I12 -> 36
A13: GLENMARK | B13: 0 | C13: 2207.6 | D13: 219 | E13: =ROUND($B$1 * B13 / C13, 0) -> 0 | F13: =IF(G13>0, "BUY", IF(G13<0, "SELL", "FLAT")) -> SELL | G13: =E13-D13 -> -219 | H13: =C13*G13 -> -483464.4 | I13: -219 | J13: 2193.5 | K13: =J13 * I13 -> -480376.5
A14: HEROMOTOCO | B14: 0 | C14: 4808.9 | D14: 86 | E14: =ROUND($B$1 * B14 / C14, 0) -> 0 | F14: =IF(G14>0, "BUY", IF(G14<0, "SELL", "FLAT")) -> SELL | G14: =E14-D14 -> -86 | H14: =C14*G14 -> -413565.4 | I14: -86 | J14: 4814.3 | K14: =J14 * I14 -> -414029.8
A15: INDIANB | B15: 0 | C15: 815.6 | D15: 693 | E15: =ROUND($B$1 * B15 / C15, 0) -> 0 | F15: =IF(G15>0, "BUY", IF(G15<0, "SELL", "FLAT")) -> SELL | G15: =E15-D15 -> -693 | H15: =C15*G15 -> -565210.8 | I15: -693 | J15: 815.7 | K15: =J15 * I15 -> -565280.1
A16: KEI | B16: 0.026306064 | C16: 5244 | D16: 125 | E16: =ROUND($B$1 * B16 / C16, 0) -> 109 | F16: =IF(G16>0, "BUY", IF(G16<0, "SELL", "FLAT")) -> SELL | G16: =E16-D16 -> -16 | H16: =C16*G16 -> -83904 | I16: -16 | J16: 5273 | K16: =J16 * I16 -> -84368 | L16: =D16+I16 -> 109
A17: LAURUSLABS | B17: 0.044869826 | C17: 1506.1 | D17: 650 | E17: =ROUND($B$1 * B17 / C17, 0) -> 647 | F17: =IF(G17>0, "BUY", IF(G17<0, "SELL", "FLAT")) -> SELL | G17: =E17-D17 -> -3 | H17: =C17*G17 -> -4518.3 | I17: -3 | J17: 1509.9 | K17: =J17 * I17 -> -4529.7 | L17: =D17+I17 -> 647
A18: LTF | B18: 0.031981081 | C18: 314.7 | D18: 2568 | E18: =ROUND($B$1 * B18 / C18, 0) -> 2208 | F18: =IF(G18>0, "BUY", IF(G18<0, "SELL", "FLAT")) -> SELL | G18: =E18-D18 -> -360 | H18: =C18*G18 -> -113292 | I18: -360 | J18: 313.45 | K18: =J18 * I18 -> -112842 | L18: =D18+I18 -> 2208
A19: MCX | B19: 0.038759043 | C19: 3009.5 | D19: 466 | E19: =ROUND($B$1 * B19 / C19, 0) -> 280 | F19: =IF(G19>0, "BUY", IF(G19<0, "SELL", "FLAT")) -> SELL | G19: =E19-D19 -> -186 | H19: =C19*G19 -> -559767 | I19: -186 | J19: 3011 | K19: =J19 * I19 -> -560046 | L19: =D19+I19 -> 280
A20: MUTHOOTFIN | B20: 0 | C20: 2971.8 | D20: 135 | E20: =ROUND($B$1 * B20 / C20, 0) -> 0 | F20: =IF(G20>0, "BUY", IF(G20<0, "SELL", "FLAT")) -> SELL | G20: =E20-D20 -> -135 | H20: =C20*G20 -> -401193 | I20: -135 | J20: 2957.59 | K20: =J20 * I20 -> -399274.65
A21: NAM-INDIA | B21: 0.036387849 | C21: 1212.1 | D21: 701 | E21: =ROUND($B$1 * B21 / C21, 0) -> 652 | F21: =IF(G21>0, "BUY", IF(G21<0, "SELL", "FLAT")) -> SELL | G21: =E21-D21 -> -49 | H21: =C21*G21 -> -59392.9 | I21: -49 | J21: 1220.5 | K21: =J21 * I21 -> -59804.5 | L21: =D21+I21 -> 652
A22: NATIONALUM | B22: 0.037886213 | C22: 336.6 | D22: 2557 | E22: =ROUND($B$1 * B22 / C22, 0) -> 2446 | F22: =IF(G22>0, "BUY", IF(G22<0, "SELL", "FLAT")) -> SELL | G22: =E22-D22 -> -111 | H22: =C22*G22 -> -37362.6 | I22: -111 | J22: 334.95 | K22: =J22 * I22 -> -37179.45 | L22: =D22+I22 -> 2446
A23: POWERINDIA | B23: 0.044771438 | C23: 34240 | D23: 40 | E23: =ROUND($B$1 * B23 / C23, 0) -> 28 | F23: =IF(G23>0, "BUY", IF(G23<0, "SELL", "FLAT")) -> SELL | G23: =E23-D23 -> -12 | H23: =C23*G23 -> -410880 | I23: -12 | J23: 34085 | K23: =J23 * I23 -> -409020 | L23: =D23+I23 -> 28
A24: RBLBANK | B24: 0.025109634 | C24: 359.3 | D24: 2228 | E24: =ROUND($B$1 * B24 / C24, 0) -> 1519 | F24: =IF(G24>0, "BUY", IF(G24<0, "SELL", "FLAT")) -> SELL | G24: =E24-D24 -> -709 | H24: =C24*G24 -> -254743.7 | I24: -709 | J24: 356.55 | K24: =J24 * I24 -> -252793.95 | L24: =D24+I24 -> 1519
A25: SAIL | B25: 0 | C25: 169 | D25: 2653 | E25: =ROUND($B$1 * B25 / C25, 0) -> 0 | F25: =IF(G25>0, "BUY", IF(G25<0, "SELL", "FLAT")) -> SELL | G25: =E25-D25 -> -2653 | H25: =C25*G25 -> -448357 | I25: -2653 | J25: 166.71 | K25: =J25 * I25 -> -442281.63
A26: TVSMOTOR | B26: 0 | C26: 3565 | D26: 132 | E26: =ROUND($B$1 * B26 / C26, 0) -> 0 | F26: =IF(G26>0, "BUY", IF(G26<0, "SELL", "FLAT")) -> SELL | G26: =E26-D26 -> -132 | H26: =C26*G26 -> -470580 | I26: -132 | J26: 3585.6 | K26: =J26 * I26 -> -473299.2
A27: UNIONBANK | B27: 0 | C27: 174.15 | D27: 2580 | E27: =ROUND($B$1 * B27 / C27, 0) -> 0 | F27: =IF(G27>0, "BUY", IF(G27<0, "SELL", "FLAT")) -> SELL | G27: =E27-D27 -> -2580 | H27: =C27*G27 -> -449307 | I27: -2580 | J27: 174.03 | K27: =J27 * I27 -> -448997.4
A28: VEDL | B28: 0 | C28: 277.5 | D28: 821 | E28: =ROUND($B$1 * B28 / C28, 0) -> 0 | F28: =IF(G28>0, "BUY", IF(G28<0, "SELL", "FLAT")) -> SELL | G28: =E28-D28 -> -821 | H28: =C28*G28 -> -227827.5 | I28: -821 | J28: 278.15 | K28: =J28 * I28 -> -228361.15
A29: WAAREEENER | B29: 0 | C29: 2900 | D29: 145 | E29: =ROUND($B$1 * B29 / C29, 0) -> 0 | F29: =IF(G29>0, "BUY", IF(G29<0, "SELL", "FLAT")) -> SELL | G29: =E29-D29 -> -145 | H29: =C29*G29 -> -420500 | I29: -145 | J29: 2904.29 | K29: =J29 * I29 -> -421122.05
A30: ADANIENSOL | B30: 0.043851634 | C30: 1543.2 | D30: 0 | E30: =ROUND($B$1 * B30 / C30, 0) -> 617 | F30: =IF(G30>0, "BUY", IF(G30<0, "SELL", "FLAT")) -> BUY | G30: =E30-D30 -> 617 | H30: =C30*G30 -> 952154.4 | I30: 617 | J30: 1551.9 | K30: =J30 * I30 -> 957522.3 | L30: =D30+I30 -> 617
A31: ADANIENT | B31: 0.022161975 | C31: 3199.9 | D31: 0 | E31: =ROUND($B$1 * B31 / C31, 0) -> 150 | F31: =IF(G31>0, "BUY", IF(G31<0, "SELL", "FLAT")) -> BUY | G31: =E31-D31 -> 150 | H31: =C31*G31 -> 479985 | I31: 150 | J31: 3149.9 | K31: =J31 * I31 -> 472485 | L31: =D31+I31 -> 150
A32: ADANIGREEN | B32: 0.038255106 | C32: 1547.1 | D32: 0 | E32: =ROUND($B$1 * B32 / C32, 0) -> 537 | F32: =IF(G32>0, "BUY", IF(G32<0, "SELL", "FLAT")) -> BUY | G32: =E32-D32 -> 537 | H32: =C32*G32 -> 830792.7 | I32: 537 | J32: 1543.4 | K32: =J32 * I32 -> 828805.8 | L32: =D32+I32 -> 537
A33: ADANIPOWER | B33: 0.047912597 | C33: 227.6 | D33: 3996 | E33: =ROUND($B$1 * B33 / C33, 0) -> 4574 | F33: =IF(G33>0, "BUY", IF(G33<0, "SELL", "FLAT")) -> BUY | G33: =E33-D33 -> 578 | H33: =C33*G33 -> 131552.8 | I33: 578 | J33: 226.61 | K33: =J33 * I33 -> 130980.58 | L33: =D33+I33 -> 4574
A34: BHARATFORG | B34: 0.03548622 | C34: 2127.1 | D34: 318 | E34: =ROUND($B$1 * B34 / C34, 0) -> 363 | F34: =IF(G34>0, "BUY", IF(G34<0, "SELL", "FLAT")) -> BUY | G34: =E34-D34 -> 45 | H34: =C34*G34 -> 95719.5 | I34: 45 | J34: 2129 | K34: =J34 * I34 -> 95805 | L34: =D34+I34 -> 363
A35: BHEL | B35: 0.03306642 | C35: 408.25 | D35: 0 | E35: =ROUND($B$1 * B35 / C35, 0) -> 1760 | F35: =IF(G35>0, "BUY", IF(G35<0, "SELL", "FLAT")) -> BUY | G35: =E35-D35 -> 1760 | H35: =C35*G35 -> 718520 | I35: 1760 | J35: 403.13 | K35: =J35 * I35 -> 709508.8 | L35: =D35+I35 -> 1760
A36: CGPOWER | B36: 0.028147945 | C36: 969.95 | D36: 0 | E36: =ROUND($B$1 * B36 / C36, 0) -> 631 | F36: =IF(G36>0, "BUY", IF(G36<0, "SELL", "FLAT")) -> BUY | G36: =E36-D36 -> 631 | H36: =C36*G36 -> 612038.45 | I36: 631 | J36: 965.23 | K36: =J36 * I36 -> 609060.13 | L36: =D36+I36 -> 631
A37: CUMMINSIND | B37: 0.037132936 | C37: 5652 | D37: 125 | E37: =ROUND($B$1 * B37 / C37, 0) -> 143 | F37: =IF(G37>0, "BUY", IF(G37<0, "SELL", "FLAT")) -> BUY | G37: =E37-D37 -> 18 | H37: =C37*G37 -> 101736 | I37: 18 | J37: 5591 | K37: =J37 * I37 -> 100638 | L37: =D37+I37 -> 143
A38: FEDERALBNK | B38: 0.028890585 | C38: 331.6 | D38: 0 | E38: =ROUND($B$1 * B38 / C38, 0) -> 1893 | F38: =IF(G38>0, "BUY", IF(G38<0, "SELL", "FLAT")) -> BUY | G38: =E38-D38 -> 1893 | H38: =C38*G38 -> 627718.8 | I38: 1893 | J38: 330.05 | K38: =J38 * I38 -> 624784.65 | L38: =D38+I38 -> 1893
A39: GMRAIRPORT | B39: 0.024682253 | C39: 113.22 | D39: 0 | E39: =ROUND($B$1 * B39 / C39, 0) -> 4737 | F39: =IF(G39>0, "BUY", IF(G39<0, "SELL", "FLAT")) -> BUY | G39: =E39-D39 -> 4737 | H39: =C39*G39 -> 536323.14 | I39: 4737 | J39: 111.48 | K39: =J39 * I39 -> 528080.76 | L39: =D39+I39 -> 4737
A40: GVT&D | B40: 0.05096997 | C40: 4869.7 | D40: 0 | E40: =ROUND($B$1 * B40 / C40, 0) -> 227 | F40: =IF(G40>0, "BUY", IF(G40<0, "SELL", "FLAT")) -> BUY | G40: =E40-D40 -> 227 | H40: =C40*G40 -> 1105421.9 | I40: 227 | J40: 4848.98 | K40: =J40 * I40 -> 1100718.5 | L40: =D40+I40 -> 227
A41: MOTHERSON | B41: 0.032946799 | C41: 146.92 | D41: 0 | E41: =ROUND($B$1 * B41 / C41, 0) -> 4873 | F41: =IF(G41>0, "BUY", IF(G41<0, "SELL", "FLAT")) -> BUY | G41: =E41-D41 -> 4873 | H41: =C41*G41 -> 715941.16 | I41: 4873 | J41: 147.09 | K41: =J41 * I41 -> 716769.57 | L41: =D41+I41 -> 4873
... A47: SONACOMS | B47: 0.022602388 | C47: 646 | D47: 0 | E47: =ROUND($B$1 * B47 / C47, 0) -> 760 | F47: =IF(G47>0, "BUY", IF(G47<0, "SELL", "FLAT")) -> BUY | G47: =E47-D47 -> 760 | H47: =C47*G47 -> 490960 | I47: 760 | J47: 652 | K47: =J47 * I47 -> 495520 | L47: =D47+I47 -> 760

Sheet TradingInstruction_Hpc39_10_Jul
A1: Money Allocated | B1: 9632892 | D1: =sum(N4:N24) -> 0
C2: Amol Ji | I2: Vishal Ji
A3: Symbol | B3: targetWeight | C3: currentPrice | D3: currentQty | E3: targetQty | F3: action | G3: actionQty | I3: Buy/Sell Qty | J3: Price | K3: Value | L3: NET Qty
A4: BANDHANBNK | B4: 0.05 | C4: 205.19 | D4: 2416 | E4: =ROUND($B$1 * B4 / C4, 0) -> 2347 | F4: =IF(G4>0, "BUY", IF(G4<0, "SELL", "FLAT")) -> SELL | G4: =E4-D4 -> -69 | H4: =C4*G4 -> -14158.11 | I4: -69 | J4: 201.12 | K4: =J4 * I4 -> -13877.28 | L4: =D4+I4 -> 2347
A5: CREDITACC | B5: 0.05 | C5: 1549.2 | D5: 355 | E5: =ROUND($B$1 * B5 / C5, 0) -> 311 | F5: =IF(G5>0, "BUY", IF(G5<0, "SELL", "FLAT")) -> SELL | G5: =E5-D5 -> -44 | H5: =C5*G5 -> -68164.8 | I5: -44 | J5: 1558.9 | K5: =J5 * I5 -> -68591.6 | L5: =D5+I5 -> 311
A6: DEEPAKFERT | B6: 0.05 | C6: 1617.9 | D6: 314 | E6: =ROUND($B$1 * B6 / C6, 0) -> 298 | F6: =IF(G6>0, "BUY", IF(G6<0, "SELL", "FLAT")) -> SELL | G6: =E6-D6 -> -16 | H6: =C6*G6 -> -25886.4 | I6: -16 | J6: 1639.2 | K6: =J6 * I6 -> -26227.2 | L6: =D6+I6 -> 298
A7: GESHIP | B7: 0.05 | C7: 1433.6 | D7: 339 | E7: =ROUND($B$1 * B7 / C7, 0) -> 336 | F7: =IF(G7>0, "BUY", IF(G7<0, "SELL", "FLAT")) -> SELL | G7: =E7-D7 -> -3 | H7: =C7*G7 -> -4300.8 | I7: -3 | J7: 1431.7 | K7: =J7 * I7 -> -4295.1 | L7: =D7+I7 -> 336
A8: IDFCFIRSTB | B8: 0.05 | C8: 78.75 | D8: 6207 | E8: =ROUND($B$1 * B8 / C8, 0) -> 6116 | F8: =IF(G8>0, "BUY", IF(G8<0, "SELL", "FLAT")) -> SELL | G8: =E8-D8 -> -91 | H8: =C8*G8 -> -7166.25 | I8: -91 | J8: 79.52 | K8: =J8 * I8 -> -7236.32 | L8: =D8+I8 -> 6116
A9: IRB | B9: 0.05 | C9: 21.49 | D9: 23041 | E9: =ROUND($B$1 * B9 / C9, 0) -> 22412 | F9: =IF(G9>0, "BUY", IF(G9<0, "SELL", "FLAT")) -> SELL | G9: =E9-D9 -> -629 | H9: =C9*G9 -> -13517.21 | I9: -629 | J9: 21.36 | K9: =J9 * I9 -> -13435.44 | L9: =D9+I9 -> 22412
A10: LLOYDSME | B10: 0.05 | C10: 1819 | D10: 280 | E10: =ROUND($B$1 * B10 / C10, 0) -> 265 | F10: =IF(G10>0, "BUY", IF(G10<0, "SELL", "FLAT")) -> SELL | G10: =E10-D10 -> -15 | H10: =C10*G10 -> -27285 | I10: -15 | J10: 1787.1 | K10: =J10 * I10 -> -26806.5 | L10: =D10+I10 -> 265
A11: MANAPPURAM | B11: 0.05 | C11: 321.05 | D11: 1523 | E11: =ROUND($B$1 * B11 / C11, 0) -> 1500 | F11: =IF(G11>0, "BUY", IF(G11<0, "SELL", "FLAT")) -> SELL | G11: =E11-D11 -> -23 | H11: =C11*G11 -> -7384.15 | I11: -23 | J11: 329.85 | K11: =J11 * I11 -> -7586.55 | L11: =D11+I11 -> 1500
A12: MOTILALOFS | B12: 0.05 | C12: 967.7 | D12: 527 | E12: =ROUND($B$1 * B12 / C12, 0) -> 498 | F12: =IF(G12>0, "BUY", IF(G12<0, "SELL", "FLAT")) -> SELL | G12: =E12-D12 -> -29 | H12: =C12*G12 -> -28063.3 | I12: -29 | J12: 959.85 | K12: =J12 * I12 -> -27835.65 | L12: =D12+I12 -> 498
A13: OIL | B13: 0.05 | C13: 419.7 | D13: 1183 | E13: =ROUND($B$1 * B13 / C13, 0) -> 1148 | F13: =IF(G13>0, "BUY", IF(G13<0, "SELL", "FLAT")) -> SELL | G13: =E13-D13 -> -35 | H13: =C13*G13 -> -14689.5 | I13: -35 | J13: 420.95 | K13: =J13 * I13 -> -14733.25 | L13: =D13+I13 -> 1148
A14: PNB | B14: 0.05 | C14: 107.03 | D14: 4558 | E14: =ROUND($B$1 * B14 / C14, 0) -> 4500 | F14: =IF(G14>0, "BUY", IF(G14<0, "SELL", "FLAT")) -> SELL | G14: =E14-D14 -> -58 | H14: =C14*G14 -> -6207.74 | I14: -58 | J14: 105.66 | K14: =J14 * I14 -> -6128.28 | L14: =D14+I14 -> 4500
A15: REDINGTON | B15: 0.05 | C15: 277.1 | D15: 1786 | E15: =ROUND($B$1 * B15 / C15, 0) -> 1738 | F15: =IF(G15>0, "BUY", IF(G15<0, "SELL", "FLAT")) -> SELL | G15: =E15-D15 -> -48 | H15: =C15*G15 -> -13300.8 | I15: -48 | J15: 275.95 | K15: =J15 * I15 -> -13245.6 | L15: =D15+I15 -> 1738
A16: UPL | B16: 0.05 | C16: 581.45 | D16: 827 | E16: =ROUND($B$1 * B16 / C16, 0) -> 828 | F16: =IF(G16>0, "BUY", IF(G16<0, "SELL", "FLAT")) -> BUY | G16: =E16-D16 -> 1 | H16: =C16*G16 -> 581.45 | I16: 1 | J16: 611.4 | K16: =J16 * I16 -> 611.4 | L16: =D16+I16 -> 828
A17: ONGC | B17: 0 | C17: 235.07 | D17: 2036 | E17: =ROUND($B$1 * B17 / C17, 0) -> 0 | F17: =IF(G17>0, "BUY", IF(G17<0, "SELL", "FLAT")) -> SELL | G17: =E17-D17 -> -2036 | H17: =C17*G17 -> -478602.52 | I17: -2036 | J17: 238.23 | K17: =J17 * I17 -> -485036.28
A18: GPIL | B18: 0.05 | C18: 256.2 | D18: 1813 | E18: =ROUND($B$1 * B18 / C18, 0) -> 1880 | F18: =IF(G18>0, "BUY", IF(G18<0, "SELL", "FLAT")) -> BUY | G18: =E18-D18 -> 67 | H18: =C18*G18 -> 17165.4 | I18: 67 | J18: 254.95 | K18: =J18 * I18 -> 17081.65 | L18: =D18+I18 -> 1880
A19: HINDALCO | B19: 0.05 | C19: 949.7 | D19: 492 | E19: =ROUND($B$1 * B19 / C19, 0) -> 507 | F19: =IF(G19>0, "BUY", IF(G19<0, "SELL", "FLAT")) -> BUY | G19: =E19-D19 -> 15 | H19: =C19*G19 -> 14245.5 | I19: 15 | J19: 961 | K19: =J19 * I19 -> 14415 | L19: =D19+I19 -> 507
A20: JINDALSTEL | B20: 0.05 | C20: 1036.5 | D20: 441 | E20: =ROUND($B$1 * B20 / C20, 0) -> 465 | F20: =IF(G20>0, "BUY", IF(G20<0, "SELL", "FLAT")) -> BUY | G20: =E20-D20 -> 24 | H20: =C20*G20 -> 24876 | I20: 24 | J20: 1056.2 | K20: =J20 * I20 -> 25348.8 | L20: =D20+I20 -> 465
A21: NATIONALUM | B21: 0.05 | C21: 335.4 | D21: 0 | E21: =ROUND($B$1 * B21 / C21, 0) -> 1436 | F21: =IF(G21>0, "BUY", IF(G21<0, "SELL", "FLAT")) -> BUY | G21: =E21-D21 -> 1436 | H21: =C21*G21 -> 481634.4 | I21: 1436 | J21: 345.75 | K21: =J21 * I21 -> 496497 | L21: =D21+I21 -> 1436
A22: NIACL | B22: 0.05 | C22: 186.5 | D22: 2353 | E22: =ROUND($B$1 * B22 / C22, 0) -> 2583 | F22: =IF(G22>0, "BUY", IF(G22<0, "SELL", "FLAT")) -> BUY | G22: =E22-D22 -> 230 | H22: =C22*G22 -> 42895 | I22: 230 | J22: 184.75 | K22: =J22 * I22 -> 42492.5 | L22: =D22+I22 -> 2583
A23: TATASTEEL | B23: 0.05 | C23: 185.25 | D23: 2515 | E23: =ROUND($B$1 * B23 / C23, 0) -> 2600 | F23: =IF(G23>0, "BUY", IF(G23<0, "SELL", "FLAT")) -> BUY | G23: =E23-D23 -> 85 | H23: =C23*G23 -> 15746.25 | I23: 85 | J23: 190.82 | K23: =J23 * I23 -> 16219.7 | L23: =D23+I23 -> 2600
A24: VEDL | B24: 0.05 | C24: 276.95 | D24: 1636 | E24: =ROUND($B$1 * B24 / C24, 0) -> 1739 | F24: =IF(G24>0, "BUY", IF(G24<0, "SELL", "FLAT")) -> BUY | G24: =E24-D24 -> 103 | H24: =C24*G24 -> 28525.85 | I24: 103 | J24: 279.8 | K24: =J24 * I24 -> 28819.4 | L24: =D24+I24 -> 1739
A28: HPC39_10 | B28: KAPIL SIR | C28: BHAN01 | D28: BANDHANBNK | E28: INE545U01014 | F28: 2347 | G28: 174.13 | H28: 408683.1
A29: HPC39_10 | B29: KAPIL SIR | C29: CRED01 | D29: CREDITACC | E29: INE741K01010 | F29: 311 | G29: 1592.8 | H29: 495360.8
A30: HPC39_10 | B30: KAPIL SIR | C30: DEEP02 | D30: DEEPAKFERT | E30: INE501A01019 | F30: 298 | G30: 1552.8 | H30: 462734.4
A31: HPC39_10 | B31: KAPIL SIR | C31: GESH01 | D31: GESHIP | E31: INE017A01032 | F31: 336 | G31: 1350.4 | H31: 453734.4
A32: HPC39_10 | B32: KAPIL SIR | C32: GPIL01 | D32: GPIL | E32: INE177H01039 | F32: 1880 | G32: 242.4 | H32: 455712
A33: HPC39_10 | B33: KAPIL SIR | C33: HIND01 | D33: HINDALCO | E33: INE038A01020 | F33: 507 | G33: 974.45 | H33: 494046.2
A34: HPC39_10 | B34: KAPIL SIR | C34: IDFC05 | D34: IDFCFIRSTB | E34: INE092T01019 | F34: 6116 | G34: 84.68 | H34: 517902.9
A35: HPC39_10 | B35: KAPIL SIR | C35: IRB001 | D35: IRB | E35: INE821I01022 | F35: 22412 | G35: 20 | H35: 448240
A36: HPC39_10 | B36: KAPIL SIR | C36: JIND01 | D36: JINDALSTEL | E36: INE749A01030 | F36: 465 | G36: 1102.4 | H36: 512616
A37: HPC39_10 | B37: KAPIL SIR | C37: LLOY02 | D37: LLOYDSME | E37: INE281B01032 | F37: 265 | G37: 2047 | H37: 542455
A38: HPC39_10 | B38: KAPIL SIR | C38: MANA02 | D38: MANAPPURAM | E38: INE522D01027 | F38: 1500 | G38: 371.85 | H38: 557775
A39: HPC39_10 | B39: KAPIL SIR | C39: MOTI01 | D39: MOTILALOFS | E39: INE338I01027 | F39: 498 | G39: 851.95 | H39: 424271.1
... A47: HPC39_10 | B47: KAPIL SIR | C47: VEDL01 | D47: VEDL | E47: INE205A01025 | F47: 1739 | G47: 264.25 | H47: 459530.8

Sheet TradingInstruction_Hpc39_10_Sep
A1: Money Allocated | B1: 9907715
C2: Amol Ji | I2: Vishal Ji | M2: net qty
A3: Symbol | B3: targetWeight | C3: currentPrice | D3: currentQty | E3: targetQty | F3: action | G3: actionQty | I3: Buy/Sell Qty | J3: Price | K3: Value
A4: CYIENT | B4: 0.05 | C4: 1159.3 | D4: 569 | E4: =ROUND($B$1 * B4 / C4, 0) -> 427 | F4: =IF(G4>0, "BUY", IF(G4<0, "SELL", "FLAT")) -> SELL | G4: =E4-D4 -> -142 | H4: =C4*G4 -> -164620.6 | I4: -142 | J4: 1138 | K4: =J4 * I4 -> -161596 | M4: =D4+I4 -> 427
A5: JINDALSAW | B5: 0.05 | C5: 314.05 | D5: 1886 | E5: =ROUND($B$1 * B5 / C5, 0) -> 1577 | F5: =IF(G5>0, "BUY", IF(G5<0, "SELL", "FLAT")) -> SELL | G5: =E5-D5 -> -309 | H5: =C5*G5 -> -97041.45 | I5: -309 | J5: 305.5 | K5: =J5 * I5 -> -94399.5 | M5: =D5+I5 -> 1577
A6: JINDALSTEL | B6: 0.05 | C6: 1168.5 | D6: 439 | E6: =ROUND($B$1 * B6 / C6, 0) -> 424 | F6: =IF(G6>0, "BUY", IF(G6<0, "SELL", "FLAT")) -> SELL | G6: =E6-D6 -> -15 | H6: =C6*G6 -> -17527.5 | I6: -15 | J6: 1146 | K6: =J6 * I6 -> -17190 | M6: =D6+I6 -> 424
A7: PVRINOX | B7: 0.05 | C7: 1229 | D7: 432 | E7: =ROUND($B$1 * B7 / C7, 0) -> 403 | F7: =IF(G7>0, "BUY", IF(G7<0, "SELL", "FLAT")) -> SELL | G7: =E7-D7 -> -29 | H7: =C7*G7 -> -35641 | I7: -29 | J7: 1220.7 | K7: =J7 * I7 -> -35400.3 | M7: =D7+I7 -> 403
A8: GESHIP | B8: 0 | C8: 1335.3 | D8: 348 | E8: =ROUND($B$1 * B8 / C8, 0) -> 0 | F8: =IF(G8>0, "BUY", IF(G8<0, "SELL", "FLAT")) -> SELL | G8: =E8-D8 -> -348 | H8: =C8*G8 -> -464684.4 | I8: -348 | J8: 1313 | K8: =J8 * I8 -> -456924
A9: HINDALCO | B9: 0 | C9: 1028.5 | D9: 493 | E9: =ROUND($B$1 * B9 / C9, 0) -> 0 | F9: =IF(G9>0, "BUY", IF(G9<0, "SELL", "FLAT")) -> SELL | G9: =E9-D9 -> -493 | H9: =C9*G9 -> -507050.5 | I9: -493 | J9: 1005.3 | K9: =J9 * I9 -> -495612.9
A10: KEC | B10: 0 | C10: 420.45 | D10: 1020 | E10: =ROUND($B$1 * B10 / C10, 0) -> 0 | F10: =IF(G10>0, "BUY", IF(G10<0, "SELL", "FLAT")) -> SELL | G10: =E10-D10 -> -1020 | H10: =C10*G10 -> -428859 | I10: -1020 | J10: 407.6 | K10: =J10 * I10 -> -415752
A11: NATIONALUM | B11: 0 | C11: 375.8 | D11: 1338 | E11: =ROUND($B$1 * B11 / C11, 0) -> 0 | F11: =IF(G11>0, "BUY", IF(G11<0, "SELL", "FLAT")) -> SELL | G11: =E11-D11 -> -1338 | H11: =C11*G11 -> -502820.4 | I11: -1338 | J11: 369.1 | K11: =J11 * I11 -> -493855.8
A12: OIL | B12: 0 | C12: 489.95 | D12: 1083 | E12: =ROUND($B$1 * B12 / C12, 0) -> 0 | F12: =IF(G12>0, "BUY", IF(G12<0, "SELL", "FLAT")) -> SELL | G12: =E12-D12 -> -1083 | H12: =C12*G12 -> -530615.85 | I12: -1083 | J12: 488.25 | K12: =J12 * I12 -> -528774.75
A13: UPL | B13: 0 | C13: 567.5 | D13: 786 | E13: =ROUND($B$1 * B13 / C13, 0) -> 0 | F13: =IF(G13>0, "BUY", IF(G13<0, "SELL", "FLAT")) -> SELL | G13: =E13-D13 -> -786 | H13: =C13*G13 -> -446055 | I13: -786 | J13: 563.05 | K13: =J13 * I13 -> -442557.3
A14: ZEEL | B14: 0 | C14: 94.17 | D14: 4990 | E14: =ROUND($B$1 * B14 / C14, 0) -> 0 | F14: =IF(G14>0, "BUY", IF(G14<0, "SELL", "FLAT")) -> SELL | G14: =E14-D14 -> -4990 | H14: =C14*G14 -> -469908.3 | I14: -4990 | J14: 91.98 | K14: =J14 * I14 -> -458980.2
A15: IDFCFIRSTB | B15: 0.05 | C15: 85 | D15: 5766 | E15: =ROUND($B$1 * B15 / C15, 0) -> 5828 | F15: =IF(G15>0, "BUY", IF(G15<0, "SELL", "FLAT")) -> BUY | G15: =E15-D15 -> 62 | H15: =C15*G15 -> 5270 | I15: 62 | J15: 84.25 | K15: =J15 * I15 -> 5223.5 | M15: =D15+I15 -> 5828
A16: BANDHANBNK | B16: 0.05 | C16: 164 | D16: 0 | E16: =ROUND($B$1 * B16 / C16, 0) -> 3021 | F16: =IF(G16>0, "BUY", IF(G16<0, "SELL", "FLAT")) -> BUY | G16: =E16-D16 -> 3021 | H16: =C16*G16 -> 495444 | I16: 3021 | J16: 159.94 | K16: =J16 * I16 -> 483178.74 | M16: =D16+I16 -> 3021
A17: CREDITACC | B17: 0.05 | C17: 1371.1 | D17: 313 | E17: =ROUND($B$1 * B17 / C17, 0) -> 361 | F17: =IF(G17>0, "BUY", IF(G17<0, "SELL", "FLAT")) -> BUY | G17: =E17-D17 -> 48 | H17: =C17*G17 -> 65812.8 | I17: 48 | J17: 1386.9 | K17: =J17 * I17 -> 66571.2 | M17: =D17+I17 -> 361
A18: DEEPAKFERT | B18: 0.05 | C18: 1430.5 | D18: 309 | E18: =ROUND($B$1 * B18 / C18, 0) -> 346 | F18: =IF(G18>0, "BUY", IF(G18<0, "SELL", "FLAT")) -> BUY | G18: =E18-D18 -> 37 | H18: =C18*G18 -> 52928.5 | I18: 37 | J18: 1423 | K18: =J18 * I18 -> 52651 | M18: =D18+I18 -> 346
A19: ELECON | B19: 0.05 | C19: 416.9 | D19: 0 | E19: =ROUND($B$1 * B19 / C19, 0) -> 1188 | F19: =IF(G19>0, "BUY", IF(G19<0, "SELL", "FLAT")) -> BUY | G19: =E19-D19 -> 1188 | H19: =C19*G19 -> 495277.2 | I19: 1188 | J19: 410.1 | K19: =J19 * I19 -> 487198.8 | M19: =D19+I19 -> 1188
A20: GODREJPROP | B20: 0.05 | C20: 1979 | D20: 0 | E20: =ROUND($B$1 * B20 / C20, 0) -> 250 | F20: =IF(G20>0, "BUY", IF(G20<0, "SELL", "FLAT")) -> BUY | G20: =E20-D20 -> 250 | H20: =C20*G20 -> 494750 | I20: 250 | J20: 1927.5 | K20: =J20 * I20 -> 481875 | M20: =D20+I20 -> 250
A21: GPIL | B21: 0.05 | C21: 240.9 | D21: 2018 | E21: =ROUND($B$1 * B21 / C21, 0) -> 2056 | F21: =IF(G21>0, "BUY", IF(G21<0, "SELL", "FLAT")) -> BUY | G21: =E21-D21 -> 38 | H21: =C21*G21 -> 9154.2 | I21: 38 | J21: 241.65 | K21: =J21 * I21 -> 9182.7 | M21: =D21+I21 -> 2056
A22: JMFINANCIL | B22: 0.05 | C22: 129.5 | D22: 0 | E22: =ROUND($B$1 * B22 / C22, 0) -> 3825 | F22: =IF(G22>0, "BUY", IF(G22<0, "SELL", "FLAT")) -> BUY | G22: =E22-D22 -> 3825 | H22: =C22*G22 -> 495337.5 | I22: 3825 | J22: 127.08 | K22: =J22 * I22 -> 486081 | M22: =D22+I22 -> 3825
A23: LLOYDSME | B23: 0.05 | C23: 1803.7 | D23: 238 | E23: =ROUND($B$1 * B23 / C23, 0) -> 275 | F23: =IF(G23>0, "BUY", IF(G23<0, "SELL", "FLAT")) -> BUY | G23: =E23-D23 -> 37 | H23: =C23*G23 -> 66736.9 | I23: 37 | J23: 1785.9 | K23: =J23 * I23 -> 66078.3 | M23: =D23+I23 -> 275
A24: LTFOODS | B24: 0.05 | C24: 441.25 | D24: 0 | E24: =ROUND($B$1 * B24 / C24, 0) -> 1123 | F24: =IF(G24>0, "BUY", IF(G24<0, "SELL", "FLAT")) -> BUY | G24: =E24-D24 -> 1123 | H24: =C24*G24 -> 495523.75 | I24: 1123 | J24: 435.6 | K24: =J24 * I24 -> 489178.8 | M24: =D24+I24 -> 1123
A25: MANAPPURAM | B25: 0.05 | C25: 340.9 | D25: 1342 | E25: =ROUND($B$1 * B25 / C25, 0) -> 1453 | F25: =IF(G25>0, "BUY", IF(G25<0, "SELL", "FLAT")) -> BUY | G25: =E25-D25 -> 111 | H25: =C25*G25 -> 37839.9 | I25: 111 | J25: 334.05 | K25: =J25 * I25 -> 37079.55 | M25: =D25+I25 -> 1453
A26: NIACL | B26: 0.05 | C26: 189.25 | D26: 0 | E26: =ROUND($B$1 * B26 / C26, 0) -> 2618 | F26: =IF(G26>0, "BUY", IF(G26<0, "SELL", "FLAT")) -> BUY | G26: =E26-D26 -> 2618 | H26: =C26*G26 -> 495456.5 | I26: 2618 | J26: 186.95 | K26: =J26 * I26 -> 489435.1 | M26: =D26+I26 -> 2618
... A30: YESBANK | B30: 0.05 | C30: 22.2 | D30: 0 | E30: =ROUND($B$1 * B30 / C30, 0) -> 22315 | F30: =IF(G30>0, "BUY", IF(G30<0, "SELL", "FLAT")) -> BUY | G30: =E30-D30 -> 22315 | H30: =C30*G30 -> 495393 | I30: 22315 | J30: 21.9 | K30: =J30 * I30 -> 488698.5 | M30: =D30+I30 -> 22315

Sheet TRADE_INSTRUCTIONS_HPC39_5
A1: Money Allocated | B1: 13344653
C2: Amol Ji | H2: Vishal Ji
A3: Symbol | B3: targetWeight | C3: currentPrice | D3: currentQty | E3: targetQty | F3: action | G3: actionQty | H3: Buy/Sell Qty | I3: Price | J3: Value | N3: net QTy
A4: ABCAPITAL | B4: 0 | C4: 393.3 | D4: 874 | E4: =ROUND($B$1 * B4 / C4, 0) -> 0 | F4: =IF(G4>0, "BUY", IF(G4<0, "SELL", "FLAT")) -> SELL | G4: =E4-D4 -> -874 | H4: -874 | I4: 398.5 | J4: =I4 * H4 -> -348289 | L4: =C4*G4 -> -343744.2
A5: ACUTAAS | B5: 0.036292428 | C5: 3192.3 | D5: 179 | E5: =ROUND($B$1 * B5 / C5, 0) -> 152 | F5: =IF(G5>0, "BUY", IF(G5<0, "SELL", "FLAT")) -> SELL | G5: =E5-D5 -> -27 | H5: -27 | I5: 3192.7 | J5: =I5 * H5 -> -86202.9 | L5: =C5*G5 -> -86192.1 | N5: =D5+H5 -> 152
A6: ADANIPOWER | B6: 0.025580097 | C6: 203.76 | D6: 1909 | E6: =ROUND($B$1 * B6 / C6, 0) -> 1675 | F6: =IF(G6>0, "BUY", IF(G6<0, "SELL", "FLAT")) -> SELL | G6: =E6-D6 -> -234 | H6: -234 | I6: 209.04 | J6: =I6 * H6 -> -48915.36 | L6: =C6*G6 -> -47679.84 | N6: =D6+H6 -> 1675
A7: ANANDRATHI | B7: 0 | C7: 2192 | D7: 89 | E7: =ROUND($B$1 * B7 / C7, 0) -> 0 | F7: =IF(G7>0, "BUY", IF(G7<0, "SELL", "FLAT")) -> SELL | G7: =E7-D7 -> -89 | H7: -89 | I7: 2197.34 | J7: =I7 * H7 -> -195563.26 | L7: =C7*G7 -> -195088
A8: ATHERENERG | B8: 0.04669004 | C8: 1713.2 | D8: 648 | E8: =ROUND($B$1 * B8 / C8, 0) -> 364 | F8: =IF(G8>0, "BUY", IF(G8<0, "SELL", "FLAT")) -> SELL | G8: =E8-D8 -> -284 | H8: -284 | I8: 1646.91 | J8: =I8 * H8 -> -467722.44 | L8: =C8*G8 -> -486548.8 | N8: =D8+H8 -> 364
A9: BELRISE | B9: 0 | C9: 229.64 | D9: 2297 | E9: =ROUND($B$1 * B9 / C9, 0) -> 0 | F9: =IF(G9>0, "BUY", IF(G9<0, "SELL", "FLAT")) -> SELL | G9: =E9-D9 -> -2297 | H9: -2297 | I9: 236.3 | J9: =I9 * H9 -> -542781.1 | L9: =C9*G9 -> -527483.08
A10: BSE | B10: 0 | C10: 3227.8 | D10: 77 | E10: =ROUND($B$1 * B10 / C10, 0) -> 0 | F10: =IF(G10>0, "BUY", IF(G10<0, "SELL", "FLAT")) -> SELL | G10: =E10-D10 -> -77 | H10: -77 | I10: 3211.61 | J10: =I10 * H10 -> -247293.97 | L10: =C10*G10 -> -248540.6
A11: CUMMINSIND | B11: 0 | C11: 5077.5 | D11: 56 | E11: =ROUND($B$1 * B11 / C11, 0) -> 0 | F11: =IF(G11>0, "BUY", IF(G11<0, "SELL", "FLAT")) -> SELL | G11: =E11-D11 -> -56 | H11: -56 | I11: 5048.5 | J11: =I11 * H11 -> -282716 | L11: =C11*G11 -> -284340
A12: FORCEMOT | B12: 0 | C12: 17807 | D12: 21 | E12: =ROUND($B$1 * B12 / C12, 0) -> 0 | F12: =IF(G12>0, "BUY", IF(G12<0, "SELL", "FLAT")) -> SELL | G12: =E12-D12 -> -21 | H12: -21 | I12: 17708.67 | J12: =I12 * H12 -> -371882.07 | L12: =C12*G12 -> -373947
A13: GABRIEL | B13: 0 | C13: 1410.5 | D13: 337 | E13: =ROUND($B$1 * B13 / C13, 0) -> 0 | F13: =IF(G13>0, "BUY", IF(G13<0, "SELL", "FLAT")) -> SELL | G13: =E13-D13 -> -337 | H13: -337 | I13: 1385.02 | J13: =I13 * H13 -> -466751.74 | L13: =C13*G13 -> -475338.5
A14: GMDCLTD | B14: 0 | C14: 560.7 | D14: 646 | E14: =ROUND($B$1 * B14 / C14, 0) -> 0 | F14: =IF(G14>0, "BUY", IF(G14<0, "SELL", "FLAT")) -> SELL | G14: =E14-D14 -> -646 | H14: -646 | I14: 561.9 | J14: =I14 * H14 -> -362987.4 | L14: =C14*G14 -> -362212.2
A15: GVT&D | B15: 0 | C15: 4337.3 | D15: 90 | E15: =ROUND($B$1 * B15 / C15, 0) -> 0 | F15: =IF(G15>0, "BUY", IF(G15<0, "SELL", "FLAT")) -> SELL | G15: =E15-D15 -> -90 | H15: -90 | I15: 4260.12 | J15: =I15 * H15 -> -383410.8 | L15: =C15*G15 -> -390357
A16: HINDALCO | B16: 0 | C16: 1016 | D16: 298 | E16: =ROUND($B$1 * B16 / C16, 0) -> 0 | F16: =IF(G16>0, "BUY", IF(G16<0, "SELL", "FLAT")) -> SELL | G16: =E16-D16 -> -298 | H16: -298 | I16: 1012.6 | J16: =I16 * H16 -> -301754.8 | L16: =C16*G16 -> -302768
A17: KIRLOSENG | B17: 0.036238781 | C17: 2119.4 | D17: 248 | E17: =ROUND($B$1 * B17 / C17, 0) -> 228 | F17: =IF(G17>0, "BUY", IF(G17<0, "SELL", "FLAT")) -> SELL | G17: =E17-D17 -> -20 | H17: -20 | I17: 2158.3 | J17: =I17 * H17 -> -43166 | L17: =C17*G17 -> -42388 | N17: =D17+H17 -> 228
A18: LAURUSLABS | B18: 0.032586788 | C18: 1854.6 | D18: 335 | E18: =ROUND($B$1 * B18 / C18, 0) -> 234 | F18: =IF(G18>0, "BUY", IF(G18<0, "SELL", "FLAT")) -> SELL | G18: =E18-D18 -> -101 | H18: -101 | I18: 1858 | J18: =I18 * H18 -> -187658 | L18: =C18*G18 -> -187314.6 | N18: =D18+H18 -> 234
A19: LTF | B19: 0 | C19: 305.8 | D19: 1149 | E19: =ROUND($B$1 * B19 / C19, 0) -> 0 | F19: =IF(G19>0, "BUY", IF(G19<0, "SELL", "FLAT")) -> SELL | G19: =E19-D19 -> -1149 | H19: -1149 | I19: 312.35 | J19: =I19 * H19 -> -358890.15 | L19: =C19*G19 -> -351364.2
A20: MCX | B20: 0.03123421 | C20: 3279 | D20: 163 | E20: =ROUND($B$1 * B20 / C20, 0) -> 127 | F20: =IF(G20>0, "BUY", IF(G20<0, "SELL", "FLAT")) -> SELL | G20: =E20-D20 -> -36 | H20: -36 | I20: 3213.9 | J20: =I20 * H20 -> -115700.4 | L20: =C20*G20 -> -118044 | N20: =D20+H20 -> 127
A21: NAM-INDIA | B21: 0 | C21: 1173.7 | D21: 281 | E21: =ROUND($B$1 * B21 / C21, 0) -> 0 | F21: =IF(G21>0, "BUY", IF(G21<0, "SELL", "FLAT")) -> SELL | G21: =E21-D21 -> -281 | H21: -281 | I21: 1164.8 | J21: =I21 * H21 -> -327308.8 | L21: =C21*G21 -> -329809.7
A22: NATIONALUM | B22: 0.031519499 | C22: 372.05 | D22: 1181 | E22: =ROUND($B$1 * B22 / C22, 0) -> 1131 | F22: =IF(G22>0, "BUY", IF(G22<0, "SELL", "FLAT")) -> SELL | G22: =E22-D22 -> -50 | H22: -50 | I22: 375.95 | J22: =I22 * H22 -> -18797.5 | L22: =C22*G22 -> -18602.5 | N22: =D22+H22 -> 1131
A23: NETWEB | B23: 0.039707552 | C23: 5139 | D23: 111 | E23: =ROUND($B$1 * B23 / C23, 0) -> 103 | F23: =IF(G23>0, "BUY", IF(G23<0, "SELL", "FLAT")) -> SELL | G23: =E23-D23 -> -8 | H23: -8 | I23: 5117 | J23: =I23 * H23 -> -40936 | L23: =C23*G23 -> -41112 | N23: =D23+H23 -> 103
A24: POWERINDIA | B24: 0.025698313 | C24: 32690 | D24: 11 | E24: =ROUND($B$1 * B24 / C24, 0) -> 10 | F24: =IF(G24>0, "BUY", IF(G24<0, "SELL", "FLAT")) -> SELL | G24: =E24-D24 -> -1 | H24: -1 | I24: 31960 | J24: =I24 * H24 -> -31960 | L24: =C24*G24 -> -32690 | N24: =D24+H24 -> 10
A25: SCHNEIDER | B25: 0 | C25: 1173.7 | D25: 276 | E25: =ROUND($B$1 * B25 / C25, 0) -> 0 | F25: =IF(G25>0, "BUY", IF(G25<0, "SELL", "FLAT")) -> SELL | G25: =E25-D25 -> -276 | H25: -276 | I25: 1159 | J25: =I25 * H25 -> -319884 | L25: =C25*G25 -> -323941.2
A26: SYRMA | B26: 0.030806957 | C26: 1434.7 | D26: 389 | E26: =ROUND($B$1 * B26 / C26, 0) -> 287 | F26: =IF(G26>0, "BUY", IF(G26<0, "SELL", "FLAT")) -> SELL | G26: =E26-D26 -> -102 | H26: -102 | I26: 1413 | J26: =I26 * H26 -> -144126 | L26: =C26*G26 -> -146339.4 | N26: =D26+H26 -> 287
A27: USHAMART | B27: 0 | C27: 503.15 | D27: 608 | E27: =ROUND($B$1 * B27 / C27, 0) -> 0 | F27: =IF(G27>0, "BUY", IF(G27<0, "SELL", "FLAT")) -> SELL | G27: =E27-D27 -> -608 | H27: -608 | I27: 512.53 | J27: =I27 * H27 -> -311618.24 | L27: =C27*G27 -> -305915.2
A28: ADANIENSOL | B28: 0.032781468 | C28: 1385.7 | D28: 237 | E28: =ROUND($B$1 * B28 / C28, 0) -> 316 | F28: =IF(G28>0, "BUY", IF(G28<0, "SELL", "FLAT")) -> BUY | G28: =E28-D28 -> 79 | H28: 79 | I28: 1394.32 | J28: =I28 * H28 -> 110151.28 | L28: =C28*G28 -> 109470.3 | N28: =D28+H28 -> 316
A29: AEGISLOG | B29: 0.029216657 | C29: 1199.4 | D29: 0 | E29: =ROUND($B$1 * B29 / C29, 0) -> 325 | F29: =IF(G29>0, "BUY", IF(G29<0, "SELL", "FLAT")) -> BUY | G29: =E29-D29 -> 325 | H29: 325 | I29: 1257.81 | J29: =I29 * H29 -> 408788.25 | L29: =C29*G29 -> 389805 | N29: =D29+H29 -> 325
A30: APARINDS | B30: 0.036731856 | C30: 17575 | D30: 25 | E30: =ROUND($B$1 * B30 / C30, 0) -> 28 | F30: =IF(G30>0, "BUY", IF(G30<0, "SELL", "FLAT")) -> BUY | G30: =E30-D30 -> 3 | H30: 3 | I30: 17290 | J30: =I30 * H30 -> 51870 | L30: =C30*G30 -> 52725 | N30: =D30+H30 -> 28
A31: BHARATFORG | B31: 0.025617604 | C31: 2053.2 | D31: 0 | E31: =ROUND($B$1 * B31 / C31, 0) -> 167 | F31: =IF(G31>0, "BUY", IF(G31<0, "SELL", "FLAT")) -> BUY | G31: =E31-D31 -> 167 | H31: 167 | I31: 2021.45 | J31: =I31 * H31 -> 337582.15 | L31: =C31*G31 -> 342884.4 | N31: =D31+H31 -> 167
A32: BHEL | B32: 0.030655808 | C32: 425.4 | D32: 0 | E32: =ROUND($B$1 * B32 / C32, 0) -> 962 | F32: =IF(G32>0, "BUY", IF(G32<0, "SELL", "FLAT")) -> BUY | G32: =E32-D32 -> 962 | H32: 962 | I32: 426.75 | J32: =I32 * H32 -> 410533.5 | L32: =C32*G32 -> 409234.8 | N32: =D32+H32 -> 962
A33: CEMPRO | B33: 0.029699095 | C33: 1241.8 | D33: 0 | E33: =ROUND($B$1 * B33 / C33, 0) -> 319 | F33: =IF(G33>0, "BUY", IF(G33<0, "SELL", "FLAT")) -> BUY | G33: =E33-D33 -> 319 | H33: 319 | I33: 1254.5 | J33: =I33 * H33 -> 400185.5 | L33: =C33*G33 -> 396134.2 | N33: =D33+H33 -> 319
A34: CHENNPETRO | B34: 0.031236039 | C34: 1378.7 | D34: 277 | E34: =ROUND($B$1 * B34 / C34, 0) -> 302 | F34: =IF(G34>0, "BUY", IF(G34<0, "SELL", "FLAT")) -> BUY | G34: =E34-D34 -> 25 | H34: 25 | I34: 1469.3 | J34: =I34 * H34 -> 36732.5 | L34: =C34*G34 -> 34467.5 | N34: =D34+H34 -> 302
A35: CPPLUS | B35: 0.043877142 | C35: 3696.9 | D35: 0 | E35: =ROUND($B$1 * B35 / C35, 0) -> 158 | F35: =IF(G35>0, "BUY", IF(G35<0, "SELL", "FLAT")) -> BUY | G35: =E35-D35 -> 158 | H35: 158 | I35: 3678.3 | J35: =I35 * H35 -> 581171.4 | L35: =C35*G35 -> 584110.2 | N35: =D35+H35 -> 158
A36: DATAPATTNS | B36: 0.028878724 | C36: 4435.3 | D36: 0 | E36: =ROUND($B$1 * B36 / C36, 0) -> 87 | F36: =IF(G36>0, "BUY", IF(G36<0, "SELL", "FLAT")) -> BUY | G36: =E36-D36 -> 87 | H36: 87 | I36: 4584.5 | J36: =I36 * H36 -> 398851.5 | L36: =C36*G36 -> 385871.1 | N36: =D36+H36 -> 87
A37: HFCL | B37: 0.053153559 | C37: 236.64 | D37: 2420 | E37: =ROUND($B$1 * B37 / C37, 0) -> 2997 | F37: =IF(G37>0, "BUY", IF(G37<0, "SELL", "FLAT")) -> BUY | G37: =E37-D37 -> 577 | H37: 577 | I37: 226.77 | J37: =I37 * H37 -> 130846.29 | L37: =C37*G37 -> 136541.28 | N37: =D37+H37 -> 2997
A38: HINDCOPPER | B38: 0.039608979 | C38: 518.95 | D38: 958 | E38: =ROUND($B$1 * B38 / C38, 0) -> 1019 | F38: =IF(G38>0, "BUY", IF(G38<0, "SELL", "FLAT")) -> BUY | G38: =E38-D38 -> 61 | H38: 61 | I38: 525.8 | J38: =I38 * H38 -> 32073.8 | L38: =C38*G38 -> 31655.95 | N38: =D38+H38 -> 1019
A39: IDEA | B39: 0.036889353 | C39: 14.11 | D39: 32653 | E39: =ROUND($B$1 * B39 / C39, 0) -> 34888 | F39: =IF(G39>0, "BUY", IF(G39<0, "SELL", "FLAT")) -> BUY | G39: =E39-D39 -> 2235 | H39: 2235 | I39: 14.54 | J39: =I39 * H39 -> 32496.9 | L39: =C39*G39 -> 31535.85 | N39: =D39+H39 -> 34888
... A47: WELSPUNLIV | B47: 0.026246796 | C47: 197.92 | D47: 0 | E47: =ROUND($B$1 * B47 / C47, 0) -> 1770 | F47: =IF(G47>0, "BUY", IF(G47<0, "SELL", "FLAT")) -> BUY | G47: =E47-D47 -> 1770 | H47: 1770 | I47: 199.7 | J47: =I47 * H47 -> 353469 | L47: =C47*G47 -> 350318.4 | N47: =D47+H47 -> 1770

Sheet PC
A1: admin | B1: Date of Entry | C1: Index Price on entry date | D1: Current Index Price | E1: Return Index | F1: Portfolio Invested | G1: Current Value | H1: Performance | I1: Alpha
A2: HPC39_5 | B2: 45538 | C2: 23788 | D2: 22840 | E2: =(D2-C2)/C2% -> -3.9852026 | F2: =-'hpc39_5 cash ledger'!G219 -> 19981206 | G2: =hpc39_5!G153 -> 19358186 | H2: =(G2-F2)/F2% -> -3.1180272 | I2: =H2-E2 -> 0.86717539
A3: HPC39_7 | B3: 45610 | C3: 21963 | D3: 22840 | E3: =(D3-C3)/C3% -> 3.9930793
A4: HPC39_8 | B4: 45659 | C4: 22819 | D4: 22840 | E4: =(D4-C4)/C4% -> 0.092028573

Sheet TRADE_INSTRUCTIONS_HPC39_7_
A1: Money Allocated | B1: 23215067
C2: Amol Ji | I2: Vishal Ji
A3: Symbol | B3: targetWeight | C3: currentPrice | D3: currentQty | E3: targetQty | F3: action | G3: actionQty | I3: Buy/Sell Qty | J3: Price | K3: Value | L3: NET Qty
A4: ABCAPITAL | B4: 0.024730821 | C4: 350.3 | D4: 2115 | E4: =ROUND($B$1 * B4 / C4, 0) -> 1639 | F4: =IF(G4>0, "BUY", IF(G4<0, "SELL", "FLAT")) -> SELL | G4: =E4-D4 -> -476 | H4: =E4*C4 -> 574141.7 | I4: -476 | J4: 357.33 | K4: =J4 * I4 -> -170089.08 | L4: =D4+I4 -> 1639
A5: ANANDRATHI | B5: 0.031384021 | C5: 3596.2 | D5: 204 | E5: =ROUND($B$1 * B5 / C5, 0) -> 203 | F5: =IF(G5>0, "BUY", IF(G5<0, "SELL", "FLAT")) -> SELL | G5: =E5-D5 -> -1 | H5: =C5*G5 -> -3596.2 | I5: -1 | J5: 3615 | K5: =J5 * I5 -> -3615 | L5: =D5+I5 -> 203
A6: ASAHIINDIA | B6: 0 | C6: 825.25 | D6: 584 | E6: =ROUND($B$1 * B6 / C6, 0) -> 0 | F6: =IF(G6>0, "BUY", IF(G6<0, "SELL", "FLAT")) -> SELL | G6: =E6-D6 -> -584 | H6: =C6*G6 -> -481946 | I6: -584 | J6: 844 | K6: =J6 * I6 -> -492896
A7: ASHOKLEY | B7: 0 | C7: 159.2 | D7: 4011 | E7: =ROUND($B$1 * B7 / C7, 0) -> 0 | F7: =IF(G7>0, "BUY", IF(G7<0, "SELL", "FLAT")) -> SELL | G7: =E7-D7 -> -4011 | H7: =C7*G7 -> -638551.2 | I7: -4011 | J7: 159.1 | K7: =J7 * I7 -> -638150.1
A8: AUBANK | B8: 0 | C8: 1019.6 | D8: 594 | E8: =ROUND($B$1 * B8 / C8, 0) -> 0 | F8: =IF(G8>0, "BUY", IF(G8<0, "SELL", "FLAT")) -> SELL | G8: =E8-D8 -> -594 | H8: =C8*G8 -> -605642.4 | I8: -594 | J8: 1009.9 | K8: =J8 * I8 -> -599880.6
A9: BEL | B9: 0 | C9: 434.15 | D9: 1228 | E9: =ROUND($B$1 * B9 / C9, 0) -> 0 | F9: =IF(G9>0, "BUY", IF(G9<0, "SELL", "FLAT")) -> SELL | G9: =E9-D9 -> -1228 | H9: =C9*G9 -> -533136.2 | I9: -1228 | J9: 430.82 | K9: =J9 * I9 -> -529046.96
A10: BSE | B10: 0.027158817 | C10: 3680.6 | D10: 193 | E10: =ROUND($B$1 * B10 / C10, 0) -> 171 | F10: =IF(G10>0, "BUY", IF(G10<0, "SELL", "FLAT")) -> SELL | G10: =E10-D10 -> -22 | H10: =C10*G10 -> -80973.2 | I10: -22 | J10: 3703 | K10: =J10 * I10 -> -81466 | L10: =D10+I10 -> 171
A11: CANBK | B11: 0 | C11: 134.96 | D11: 3741 | E11: =ROUND($B$1 * B11 / C11, 0) -> 0 | F11: =IF(G11>0, "BUY", IF(G11<0, "SELL", "FLAT")) -> SELL | G11: =E11-D11 -> -3741 | H11: =C11*G11 -> -504885.36 | I11: -3741 | J11: 134.2 | K11: =J11 * I11 -> -502042.2
A12: CHENNPETRO | B12: 0.02921823 | C12: 1107 | D12: 863 | E12: =ROUND($B$1 * B12 / C12, 0) -> 613 | F12: =IF(G12>0, "BUY", IF(G12<0, "SELL", "FLAT")) -> SELL | G12: =E12-D12 -> -250 | H12: =C12*G12 -> -276750 | I12: -250 | J12: 1112.2 | K12: =J12 * I12 -> -278050 | L12: =D12+I12 -> 613
A13: CRAFTSMAN | B13: 0 | C13: 7647.5 | D13: 94 | E13: =ROUND($B$1 * B13 / C13, 0) -> 0 | F13: =IF(G13>0, "BUY", IF(G13<0, "SELL", "FLAT")) -> SELL | G13: =E13-D13 -> -94 | H13: =C13*G13 -> -718865 | I13: -94 | J13: 7641.65 | K13: =J13 * I13 -> -718315.1
A14: CUB | B14: 0 | C14: 270.5 | D14: 2007 | E14: =ROUND($B$1 * B14 / C14, 0) -> 0 | F14: =IF(G14>0, "BUY", IF(G14<0, "SELL", "FLAT")) -> SELL | G14: =E14-D14 -> -2007 | H14: =C14*G14 -> -542893.5 | I14: -2007 | J14: 271 | K14: =J14 * I14 -> -543897
A15: ECLERX | B15: 0 | C15: 1391 | D15: 230 | E15: =ROUND($B$1 * B15 / C15, 0) -> 0 | F15: =IF(G15>0, "BUY", IF(G15<0, "SELL", "FLAT")) -> SELL | G15: =E15-D15 -> -230 | H15: =C15*G15 -> -319930 | I15: -230 | J15: 1454.12 | K15: =J15 * I15 -> -334447.6
A16: FORCEMOT | B16: 0.03771921 | C16: 19143 | D16: 77 | E16: =ROUND($B$1 * B16 / C16, 0) -> 46 | F16: =IF(G16>0, "BUY", IF(G16<0, "SELL", "FLAT")) -> SELL | G16: =E16-D16 -> -31 | H16: =C16*G16 -> -593433 | I16: -31 | J16: 19235.19 | K16: =J16 * I16 -> -596290.89 | L16: =D16+I16 -> 46
A17: GMDCLTD | B17: 0.043414202 | C17: 713.4 | D17: 1440 | E17: =ROUND($B$1 * B17 / C17, 0) -> 1413 | F17: =IF(G17>0, "BUY", IF(G17<0, "SELL", "FLAT")) -> SELL | G17: =E17-D17 -> -27 | H17: =C17*G17 -> -19261.8 | I17: -27 | J17: 737.6 | K17: =J17 * I17 -> -19915.2 | L17: =D17+I17 -> 1413
A18: GRSE | B18: 0.025909777 | C18: 2773.7 | D18: 322 | E18: =ROUND($B$1 * B18 / C18, 0) -> 217 | F18: =IF(G18>0, "BUY", IF(G18<0, "SELL", "FLAT")) -> SELL | G18: =E18-D18 -> -105 | H18: =C18*G18 -> -291238.5 | I18: -105 | J18: 2797 | K18: =J18 * I18 -> -293685 | L18: =D18+I18 -> 217
A19: GVT&D | B19: 0.04550268 | C19: 4476.2 | D19: 253 | E19: =ROUND($B$1 * B19 / C19, 0) -> 236 | F19: =IF(G19>0, "BUY", IF(G19<0, "SELL", "FLAT")) -> SELL | G19: =E19-D19 -> -17 | H19: =C19*G19 -> -76095.4 | I19: -17 | J19: 4565 | K19: =J19 * I19 -> -77605 | L19: =D19+I19 -> 236
A20: HINDCOPPER | B20: 0.043811124 | C20: 529.55 | D20: 1979 | E20: =ROUND($B$1 * B20 / C20, 0) -> 1921 | F20: =IF(G20>0, "BUY", IF(G20<0, "SELL", "FLAT")) -> SELL | G20: =E20-D20 -> -58 | H20: =C20*G20 -> -30713.9 | I20: -58 | J20: 533.55 | K20: =J20 * I20 -> -30945.9 | L20: =D20+I20 -> 1921
A21: INDIACEM | B21: 0 | C21: 386 | D21: 1530 | E21: =ROUND($B$1 * B21 / C21, 0) -> 0 | F21: =IF(G21>0, "BUY", IF(G21<0, "SELL", "FLAT")) -> SELL | G21: =E21-D21 -> -1530 | H21: =C21*G21 -> -590580 | I21: -1530 | J21: 393.3 | K21: =J21 * I21 -> -601749
A22: JKTYRE | B22: 0 | C22: 403.1 | D22: 1210 | E22: =ROUND($B$1 * B22 / C22, 0) -> 0 | F22: =IF(G22>0, "BUY", IF(G22<0, "SELL", "FLAT")) -> SELL | G22: =E22-D22 -> -1210 | H22: =C22*G22 -> -487751 | I22: -1210 | J22: 400.85 | K22: =J22 * I22 -> -485028.5
A23: LAURUSLABS | B23: 0.02537362 | C23: 1163.1 | D23: 581 | E23: =ROUND($B$1 * B23 / C23, 0) -> 506 | F23: =IF(G23>0, "BUY", IF(G23<0, "SELL", "FLAT")) -> SELL | G23: =E23-D23 -> -75 | H23: =C23*G23 -> -87232.5 | I23: -75 | J23: 1169.5 | K23: =J23 * I23 -> -87712.5 | L23: =D23+I23 -> 506
A24: LTF | B24: 0 | C24: 284.2 | D24: 2408 | E24: =ROUND($B$1 * B24 / C24, 0) -> 0 | F24: =IF(G24>0, "BUY", IF(G24<0, "SELL", "FLAT")) -> SELL | G24: =E24-D24 -> -2408 | H24: =C24*G24 -> -684353.6 | I24: -2408 | J24: 284.85 | K24: =J24 * I24 -> -685918.8
A25: MCX | B25: 0.040970445 | C25: 2904.9 | D25: 372 | E25: =ROUND($B$1 * B25 / C25, 0) -> 327 | F25: =IF(G25>0, "BUY", IF(G25<0, "SELL", "FLAT")) -> SELL | G25: =E25-D25 -> -45 | H25: =C25*G25 -> -130720.5 | I25: -45 | J25: 2903.52 | K25: =J25 * I25 -> -130658.4 | L25: =D25+I25 -> 327
A26: MUTHOOTFIN | B26: 0 | C26: 3461.2 | D26: 163 | E26: =ROUND($B$1 * B26 / C26, 0) -> 0 | F26: =IF(G26>0, "BUY", IF(G26<0, "SELL", "FLAT")) -> SELL | G26: =E26-D26 -> -163 | H26: =C26*G26 -> -564175.6 | I26: -163 | J26: 3399.47 | K26: =J26 * I26 -> -554113.61
A27: NETWEB | B27: 0.045712877 | C27: 3910 | D27: 292 | E27: =ROUND($B$1 * B27 / C27, 0) -> 271 | F27: =IF(G27>0, "BUY", IF(G27<0, "SELL", "FLAT")) -> SELL | G27: =E27-D27 -> -21 | H27: =C27*G27 -> -82110 | I27: -21 | J27: 4071.3 | K27: =J27 * I27 -> -85497.3 | L27: =D27+I27 -> 271
A28: POWERINDIA | B28: 0.04043882 | C28: 33605 | D28: 37 | E28: =ROUND($B$1 * B28 / C28, 0) -> 28 | F28: =IF(G28>0, "BUY", IF(G28<0, "SELL", "FLAT")) -> SELL | G28: =E28-D28 -> -9 | H28: =C28*G28 -> -302445 | I28: -9 | J28: 34025 | K28: =J28 * I28 -> -306225 | L28: =D28+I28 -> 28
A29: RBLBANK | B29: 0 | C29: 330.15 | D29: 2350 | E29: =ROUND($B$1 * B29 / C29, 0) -> 0 | F29: =IF(G29>0, "BUY", IF(G29<0, "SELL", "FLAT")) -> SELL | G29: =E29-D29 -> -2350 | H29: =C29*G29 -> -775852.5 | I29: -2350 | J29: 327.5 | K29: =J29 * I29 -> -769625
A30: SHRIRAMFIN | B30: 0 | C30: 949.15 | D30: 660 | E30: =ROUND($B$1 * B30 / C30, 0) -> 0 | F30: =IF(G30>0, "BUY", IF(G30<0, "SELL", "FLAT")) -> SELL | G30: =E30-D30 -> -660 | H30: =C30*G30 -> -626439 | I30: -660 | J30: 945.5 | K30: =J30 * I30 -> -624030
A31: UNIONBANK | B31: 0 | C31: 164.43 | D31: 3104 | E31: =ROUND($B$1 * B31 / C31, 0) -> 0 | F31: =IF(G31>0, "BUY", IF(G31<0, "SELL", "FLAT")) -> SELL | G31: =E31-D31 -> -3104 | H31: =C31*G31 -> -510390.72 | I31: -3104 | J31: 162.81 | K31: =J31 * I31 -> -505362.24
A32: ABDL | B32: 0.026826719 | C32: 533.8 | D32: 0 | E32: =ROUND($B$1 * B32 / C32, 0) -> 1167 | F32: =IF(G32>0, "BUY", IF(G32<0, "SELL", "FLAT")) -> BUY | G32: =E32-D32 -> 1167 | H32: =C32*G32 -> 622944.6 | I32: 1167 | J32: 540.23 | K32: =J32 * I32 -> 630448.41 | L32: =D32+I32 -> 1167
A33: ADANIPOWER | B33: 0.032999837 | C33: 227.46 | D33: 0 | E33: =ROUND($B$1 * B33 / C33, 0) -> 3368 | F33: =IF(G33>0, "BUY", IF(G33<0, "SELL", "FLAT")) -> BUY | G33: =E33-D33 -> 3368 | H33: =C33*G33 -> 766085.28 | I33: 3368 | J33: 233 | K33: =J33 * I33 -> 784744 | L33: =D33+I33 -> 3368
A34: APARINDS | B34: 0.038299818 | C34: 12359 | D34: 0 | E34: =ROUND($B$1 * B34 / C34, 0) -> 72 | F34: =IF(G34>0, "BUY", IF(G34<0, "SELL", "FLAT")) -> BUY | G34: =E34-D34 -> 72 | H34: =C34*G34 -> 889848 | I34: 72 | J34: 12685 | K34: =J34 * I34 -> 913320 | L34: =D34+I34 -> 72
A35: CCL | B35: 0.031333595 | C35: 1171 | D35: 604 | E35: =ROUND($B$1 * B35 / C35, 0) -> 621 | F35: =IF(G35>0, "BUY", IF(G35<0, "SELL", "FLAT")) -> BUY | G35: =E35-D35 -> 17 | H35: =C35*G35 -> 19907 | I35: 17 | J35: 1167.4 | K35: =J35 * I35 -> 19845.8 | L35: =D35+I35 -> 621
A36: CUMMINSIND | B36: 0.026590514 | C36: 5283.5 | D36: 0 | E36: =ROUND($B$1 * B36 / C36, 0) -> 117 | F36: =IF(G36>0, "BUY", IF(G36<0, "SELL", "FLAT")) -> BUY | G36: =E36-D36 -> 117 | H36: =C36*G36 -> 618169.5 | I36: 117 | J36: 5252.48 | K36: =J36 * I36 -> 614540.16 | L36: =D36+I36 -> 117
A37: DATAPATTNS | B37: 0.030897347 | C37: 4004.1 | D37: 0 | E37: =ROUND($B$1 * B37 / C37, 0) -> 179 | F37: =IF(G37>0, "BUY", IF(G37<0, "SELL", "FLAT")) -> BUY | G37: =E37-D37 -> 179 | H37: =C37*G37 -> 716733.9 | I37: 179 | J37: 4131.13 | K37: =J37 * I37 -> 739472.27 | L37: =D37+I37 -> 179
A38: GABRIEL | B38: 0.03513398 | C38: 1028.6 | D38: 0 | E38: =ROUND($B$1 * B38 / C38, 0) -> 793 | F38: =IF(G38>0, "BUY", IF(G38<0, "SELL", "FLAT")) -> BUY | G38: =E38-D38 -> 793 | H38: =C38*G38 -> 815679.8 | I38: 793 | J38: 1045.4 | K38: =J38 * I38 -> 829002.2 | L38: =D38+I38 -> 793
A39: GALLANTT | B39: 0.033116715 | C39: 869.5 | D39: 0 | E39: =ROUND($B$1 * B39 / C39, 0) -> 884 | F39: =IF(G39>0, "BUY", IF(G39<0, "SELL", "FLAT")) -> BUY | G39: =E39-D39 -> 884 | H39: =C39*G39 -> 768638 | I39: 884 | J39: 879.54 | K39: =J39 * I39 -> 777513.36 | L39: =D39+I39 -> 884
A40: GESHIP | B40: 0.024550027 | C40: 1531 | D40: 0 | E40: =ROUND($B$1 * B40 / C40, 0) -> 372 | F40: =IF(G40>0, "BUY", IF(G40<0, "SELL", "FLAT")) -> BUY | G40: =E40-D40 -> 372 | H40: =C40*G40 -> 569532 | I40: 372 | J40: 1526.7 | K40: =J40 * I40 -> 567932.4 | L40: =D40+I40 -> 372
A41: GPIL | B41: 0.024832712 | C41: 302.05 | D41: 0 | E41: =ROUND($B$1 * B41 / C41, 0) -> 1909 | F41: =IF(G41>0, "BUY", IF(G41<0, "SELL", "FLAT")) -> BUY | G41: =E41-D41 -> 1909 | H41: =C41*G41 -> 576613.45 | I41: 1909 | J41: 302.55 | K41: =J41 * I41 -> 577567.95 | L41: =D41+I41 -> 1909
A42: HBLENGINE | B42: 0.026681071 | C42: 788 | D42: 0 | E42: =ROUND($B$1 * B42 / C42, 0) -> 786 | F42: =IF(G42>0, "BUY", IF(G42<0, "SELL", "FLAT")) -> BUY | G42: =E42-D42 -> 786 | H42: =C42*G42 -> 619368 | I42: 786 | J42: 798 | K42: =J42 * I42 -> 627228 | L42: =D42+I42 -> 786
A43: KIRLOSENG | B43: 0.038907518 | C43: 1718.8 | D43: 0 | E43: =ROUND($B$1 * B43 / C43, 0) -> 526 | F43: =IF(G43>0, "BUY", IF(G43<0, "SELL", "FLAT")) -> BUY | G43: =E43-D43 -> 526 | H43: =C43*G43 -> 904088.8 | I43: 526 | J43: 1736.57 | K43: =J43 * I43 -> 913435.82 | L43: =D43+I43 -> 526
... A48: WELCORP | B48: 0.024746982 | C48: 1240.7 | D48: 0 | E48: =ROUND($B$1 * B48 / C48, 0) -> 463 | F48: =IF(G48>0, "BUY", IF(G48<0, "SELL", "FLAT")) -> BUY | G48: =E48-D48 -> 463 | H48: =C48*G48 -> 574444.1 | I48: 463 | J48: 1240.4 | K48: =J48 * I48 -> 574305.2 | L48: =D48+I48 -> 463

Sheet Sheet44
A1: Client Code | B1: Name | C1: Scrip Code | D1: Scrip Name | E1: ISIN Code | F1: Stock | G1: Close Rate | H1: Stk.Value Credit | I1: Stk.Value Debit | J1: Variance | K1: Stock Val
A2: HPC39_5 | B2: AMOL | C2: ABCA01 | D2: ABCAPITAL | E2: INE674K01013 | F2: 874 | G2: 405.55 | H2: 354450.7 | I2: 0 | J2: 82.74 | K2: 293272.5
A3: HPC39_5 | B3: AMOL | C3: ACUT01 | D3: ACUTAAS | F3: 179 | G3: 3281.6 | H3: 587406.4 | I3: 0 | J3: 0 | K3: 0
A4: HPC39_5 | B4: AMOL | C4: ADAN06 | D4: ADANIENSOL | E4: INE931S01010 | F4: 237 | G4: 1581.4 | H4: 374791.8 | I4: 0 | J4: 78.46 | K4: 294061.6
A5: HPC39_5 | B5: AMOL | C5: ADAN01 | D5: ADANIPOWER | E5: INE814H01029 | F5: 1909 | G5: 212.63 | H5: 405910.7 | I5: 0 | J5: 79.3 | K5: 321887.2
A6: HPC39_5 | B6: AMOL | C6: ANAN02 | D6: ANANDRATHI | E6: INE463V01026 | F6: 89 | G6: 2213.4 | H6: 196992.6 | I6: 0 | J6: 85.9 | K6: 169216.6
A7: HPC39_5 | B7: AMOL | C7: APAR01 | D7: APARINDS | E7: INE372A01015 | F7: 25 | G7: 17803 | H7: 445075 | I7: 0 | J7: 76.82 | K7: 341906.6
A8: HPC39_5 | B8: AMOL | C8: ATHE01 | D8: ATHERENERG | F8: 648 | G8: 1616.3 | H8: 1047362 | I8: 0 | J8: 0 | K8: 0
A9: HPC39_5 | B9: AMOL | C9: BELR01 | D9: BELRISE | F9: 2297 | G9: 229.87 | H9: 528011.4 | I9: 0 | J9: 0 | K9: 0
A10: HPC39_5 | B10: AMOL | C10: BSE001 | D10: BSE | E10: INE118H01025 | F10: 77 | G10: 3405 | H10: 262185 | I10: 0 | J10: 77.95 | K10: 204373.2
A11: HPC39_5 | B11: AMOL | C11: CHEN01 | D11: CHENNPETRO | E11: INE178A01016 | F11: 277 | G11: 1341.1 | H11: 371484.7 | I11: 0 | J11: 76.24 | K11: 283219.9
A12: HPC39_5 | B12: AMOL | C12: CUMM01 | D12: CUMMINSIND | E12: INE298A01020 | F12: 56 | G12: 5193 | H12: 290808 | I12: 0 | J12: 84.27 | K12: 245063.9
A13: HPC39_5 | B13: AMOL | C13: FORC01 | D13: FORCEMOT | E13: INE451A01017 | F13: 21 | G13: 17370 | H13: 364770 | I13: 0 | J13: 74.89 | K13: 273176.3
A14: HPC39_5 | B14: AMOL | C14: GABR01 | D14: GABRIEL | E14: INE524A01029 | F14: 337 | G14: 1367.6 | H14: 460881.2 | I14: 0 | J14: 76.05 | K14: 350500.2
A15: HPC39_5 | B15: AMOL | C15: GMDC01 | D15: GMDCLTD | E15: INE131A01031 | F15: 646 | G15: 567.65 | H15: 366701.9 | I15: 0 | J15: 75.75 | K15: 277776.7
A16: HPC39_5 | B16: AMOL | C16: GVT&01 | D16: GVT&D | E16: INE200A01026 | F16: 90 | G16: 4339.2 | H16: 390528 | I16: 0 | J16: 77.33 | K16: 301995.3
A17: HPC39_5 | B17: AMOL | C17: HFCL01 | D17: HFCL | E17: INE548A01028 | F17: 2420 | G17: 251.47 | H17: 608557.4 | I17: 0 | J17: 75.5 | K17: 459460.8
A18: HPC39_5 | B18: AMOL | C18: HIND01 | D18: HINDALCO | E18: INE038A01020 | F18: 298 | G18: 1037.4 | H18: 309145.2 | I18: 0 | J18: 84.62 | K18: 261598.7
A19: HPC39_5 | B19: AMOL | C19: HIND06 | D19: HINDCOPPER | E19: INE531E01026 | F19: 958 | G19: 533.55 | H19: 511140.9 | I19: 0 | J19: 75.13 | K19: 384020.2
A20: HPC39_5 | B20: AMOL | C20: IDEA01 | D20: IDEA | E20: INE669E01016 | F20: 32653 | G20: 14.68 | H20: 479346 | I20: 0 | J20: 75.96 | K20: 364111.3
A21: HPC39_5 | B21: AMOL | C21: KIRL01 | D21: KIRLOSENG | E21: INE146L01010 | F21: 248 | G21: 2123.1 | H21: 526528.8 | I21: 0 | J21: 76.86 | K21: 404690
... A31: HPC39_5 | B31: AMOL | C31: USHA01 | D31: USHAMART | E31: INE228A01035 | F31: 608 | G31: 492.45 | H31: 299409.6 | I31: 0 | J31: 81.87 | K31: 245126.6
A36: Client Code | B36: Name | C36: Scrip Code | D36: Scrip Name | E36: ISIN Code | F36: Stock | G36: Close Rate | H36: Stk.Value Credit | I36: Stk.Value Debit | J36: Variance | K36: Stock Val
A37: HPC39_10 | B37: KAPIL SIR | C37: CRED01 | D37: CREDITACC | E37: INE741K01010 | F37: 313 | G37: 1391.7 | H37: 435602.1 | I37: 0 | J37: 79.33 | K37: 345563.1
A38: HPC39_10 | B38: KAPIL SIR | C38: CYIE01 | D38: CYIENT | E38: INE136B01020 | F38: 569 | G38: 1107.45 | H38: 630139.1 | I38: 0 | J38: 82.51 | K38: 519927.7
A39: HPC39_10 | B39: KAPIL SIR | C39: DEEP02 | D39: DEEPAKFERT | E39: INE501A01019 | F39: 309 | G39: 1436.3 | H39: 443816.7 | I39: 0 | J39: 78.38 | K39: 347863.5
A40: HPC39_10 | B40: KAPIL SIR | C40: GESH01 | D40: GESHIP | E40: INE017A01032 | F40: 348 | G40: 1339.6 | H40: 466180.8 | I40: 0 | J40: 81.6 | K40: 380403.5
A41: HPC39_10 | B41: KAPIL SIR | C41: GPIL01 | D41: GPIL | E41: INE177H01039 | F41: 2018 | G41: 239.85 | H41: 484017.3 | I41: 0 | J41: 81.22 | K41: 393118.9
A42: HPC39_10 | B42: KAPIL SIR | C42: HIND01 | D42: HINDALCO | E42: INE038A01020 | F42: 493 | G42: 1037.4 | H42: 511438.2 | I42: 0 | J42: 84.62 | K42: 432779
A43: HPC39_10 | B43: KAPIL SIR | C43: IDFC05 | D43: IDFCFIRSTB | E43: INE092T01019 | F43: 5766 | G43: 83.12 | H43: 479269.9 | I43: 0 | J43: 83.64 | K43: 400861.4
A44: HPC39_10 | B44: KAPIL SIR | C44: JIND03 | D44: JINDALSAW | E44: INE324A01032 | F44: 1886 | G44: 308.6 | H44: 582019.6 | I44: 0 | J44: 76.82 | K44: 447107.5
A45: HPC39_10 | B45: KAPIL SIR | C45: JIND01 | D45: JINDALSTEL | E45: INE749A01030 | F45: 439 | G45: 1179.2 | H45: 517668.8 | I45: 0 | J45: 84.62 | K45: 438051.3
A46: HPC39_10 | B46: KAPIL SIR | C46: KEC001 | D46: KEC | E46: INE389H01022 | F46: 1020 | G46: 425.8 | H46: 434316 | I46: 0 | J46: 80.29 | K46: 348712.3
A47: HPC39_10 | B47: KAPIL SIR | C47: LLOY02 | D47: LLOYDSME | E47: INE281B01032 | F47: 238 | G47: 1810.2 | H47: 430827.6 | I47: 0 | J47: 80.97 | K47: 348841.1
A48: HPC39_10 | B48: KAPIL SIR | C48: MANA02 | D48: MANAPPURAM | E48: INE522D01027 | F48: 1342 | G48: 348.9 | H48: 468223.8 | I48: 0 | J48: 82.04 | K48: 384130.8
... A56: HPC39_10 | B56: KAPIL SIR | C56: ZEEL01 | D56: ZEEL | E56: INE256A01028 | F56: 4990 | G56: 101.51 | H56: 506534.9 | I56: 0 | J56: 77.28 | K56: 391450.2

Sheet Rebalance dates
B1: Rebalance dates
A3: HPC39_5 | B3: 45538 | C3: 45632 | D3: 45722 | E3: 45810 | F3: 45901 | G3: 45992 | H3: 46090 | I3: 46176 | J3: 46266
A4: HPC39_7 | B4: 45610 | C4: 45709 | D4: 45783 | E4: 45870 | F4: 45964 | G4: 46054 | H4: 46146 | I4: 46238
A5: HPC39_8 | C5: 45659 | D5: 45749 | E5: 45839 | F5: 45931 | G5: 46023 | H5: 46118 | I5: 46205
A6: NewInvesting HPC39_10 | B6: 46195 | C6: =hpc39_10!B74 -> 46204 | D6: =hpc39_10!B50 -> 46237 | E6: =hpc39_10!B26 -> 46266

Sheet hpc39_5
A1: Total cash to be allocated | B1: 13344653 | C1: Rebalance Date | D1: 46268
A2: Target rebalance date | B2: 46357
A4: 46268 | B4: Qty | C4: Buying rate | D4: Changed Qty | E4: Amount at entry | F4: Actual Price | G4: Amount by M2M | H4: P&L
A5: ACUTAAS | B5: 152 | C5: 3192.7 | D5: =B5 -> 152 | E5: =B5*C5 -> 485290.4 | F5: =IFERROR(__xludf.DUMMYFUNCTION("GOOGLEFINANCE(CONCAT(""NSE:"",A5))"),3294.2) -> 3294.2 | G5: =D5*F5 -> 500718.4 | H5: =(G5-E5)/E5 -> 0.031791274
A6: ADANIPOWER | B6: 1675 | C6: 209.04 | D6: =B6 -> 1675 | E6: =B6*C6 -> 350142 | F6: =IFERROR(__xludf.DUMMYFUNCTION("GOOGLEFINANCE(CONCAT(""NSE:"",A6))"),203.99) -> 203.99 | G6: =D6*F6 -> 341683.25 | H6: =(G6-E6)/E6 -> -0.024158056
A7: ATHERENERG | B7: 364 | C7: 1646.91 | D7: =B7 -> 364 | E7: =B7*C7 -> 599475.24 | F7: =IFERROR(__xludf.DUMMYFUNCTION("GOOGLEFINANCE(CONCAT(""NSE:"",A7))"),1542.5) -> 1542.5 | G7: =D7*F7 -> 561470 | H7: =(G7-E7)/E7 -> -0.063397514
A8: KIRLOSENG | B8: 228 | C8: 2158.3 | D8: =B8 -> 228 | E8: =B8*C8 -> 492092.4 | F8: =IFERROR(__xludf.DUMMYFUNCTION("GOOGLEFINANCE(CONCAT(""NSE:"",A8))"),2125.3) -> 2125.3 | G8: =D8*F8 -> 484568.4 | H8: =(G8-E8)/E8 -> -0.015289811
A9: LAURUSLABS | B9: 234 | C9: 1858 | D9: =B9 -> 234 | E9: =B9*C9 -> 434772 | F9: =IFERROR(__xludf.DUMMYFUNCTION("GOOGLEFINANCE(CONCAT(""NSE:"",A9))"),1944.7) -> 1944.7 | G9: =D9*F9 -> 455059.8 | H9: =(G9-E9)/E9 -> 0.046663079
A10: MCX | B10: 127 | C10: 3213.9 | D10: =B10 -> 127 | E10: =B10*C10 -> 408165.3 | F10: =IFERROR(__xludf.DUMMYFUNCTION("GOOGLEFINANCE(CONCAT(""NSE:"",A10))"),3290.8) -> 3290.8 | G10: =D10*F10 -> 417931.6 | H10: =(G10-E10)/E10 -> 0.023927316
A11: NATIONALUM | B11: 1131 | C11: 375.95 | D11: =B11 -> 1131 | E11: =B11*C11 -> 425199.45 | F11: =IFERROR(__xludf.DUMMYFUNCTION("GOOGLEFINANCE(CONCAT(""NSE:"",A11))"),356.3) -> 356.3 | G11: =D11*F11 -> 402975.3 | H11: =(G11-E11)/E11 -> -0.052267589
A12: NETWEB | B12: 103 | C12: 5117 | D12: =B12 -> 103 | E12: =B12*C12 -> 527051 | F12: =IFERROR(__xludf.DUMMYFUNCTION("GOOGLEFINANCE(CONCAT(""NSE:"",A12))"),4576.0) -> 4576 | G12: =D12*F12 -> 471328 | H12: =(G12-E12)/E12 -> -0.10572601
A13: POWERINDIA | B13: 10 | C13: 31960 | D13: =B13 -> 10 | E13: =B13*C13 -> 319600 | F13: =IFERROR(__xludf.DUMMYFUNCTION("GOOGLEFINANCE(CONCAT(""NSE:"",A13))"),30810.0) -> 30810 | G13: =D13*F13 -> 308100 | H13: =(G13-E13)/E13 -> -0.035982478
A14: SYRMA | B14: 287 | C14: 1413 | D14: =B14 -> 287 | E14: =B14*C14 -> 405531 | F14: =IFERROR(__xludf.DUMMYFUNCTION("GOOGLEFINANCE(CONCAT(""NSE:"",A14))"),1642.0) -> 1642 | G14: =D14*F14 -> 471254 | H14: =(G14-E14)/E14 -> 0.16206653
A15: ADANIENSOL | B15: 316 | C15: 1394.32 | D15: =B15 -> 316 | E15: =B15*C15 -> 440605.12 | F15: =IFERROR(__xludf.DUMMYFUNCTION("GOOGLEFINANCE(CONCAT(""NSE:"",A15))"),1356.1) -> 1356.1 | G15: =D15*F15 -> 428527.6 | H15: =(G15-E15)/E15 -> -0.027411211
A16: AEGISLOG | B16: 325 | C16: 1257.81 | D16: =B16 -> 325 | E16: =B16*C16 -> 408788.25 | F16: =IFERROR(__xludf.DUMMYFUNCTION("GOOGLEFINANCE(CONCAT(""NSE:"",A16))"),1365.5) -> 1365.5 | G16: =D16*F16 -> 443787.5 | H16: =(G16-E16)/E16 -> 0.085617065
A17: APARINDS | B17: 28 | C17: 17290 | D17: =B17 -> 28 | E17: =B17*C17 -> 484120 | F17: =IFERROR(__xludf.DUMMYFUNCTION("GOOGLEFINANCE(CONCAT(""NSE:"",A17))"),17308.0) -> 17308 | G17: =D17*F17 -> 484624 | H17: =(G17-E17)/E17 -> 0.0010410642
A18: BHARATFORG | B18: 167 | C18: 2021.45 | D18: =B18 -> 167 | E18: =B18*C18 -> 337582.15 | F18: =IFERROR(__xludf.DUMMYFUNCTION("GOOGLEFINANCE(CONCAT(""NSE:"",A18))"),1915.6) -> 1915.6 | G18: =D18*F18 -> 319905.2 | H18: =(G18-E18)/E18 -> -0.052363403
A19: BHEL | B19: 962 | C19: 426.75 | D19: =B19 -> 962 | E19: =B19*C19 -> 410533.5 | F19: =IFERROR(__xludf.DUMMYFUNCTION("GOOGLEFINANCE(CONCAT(""NSE:"",A19))"),420.35) -> 420.35 | G19: =D19*F19 -> 404376.7 | H19: =(G19-E19)/E19 -> -0.014997071
A20: CEMPRO | B20: 319 | C20: 1254.5 | D20: =B20 -> 319 | E20: =B20*C20 -> 400185.5 | F20: =IFERROR(__xludf.DUMMYFUNCTION("GOOGLEFINANCE(CONCAT(""NSE:"",A20))"),1254.1) -> 1254.1 | G20: =D20*F20 -> 400057.9 | H20: =(G20-E20)/E20 -> -0.00031885213
A21: CHENNPETRO | B21: 302 | C21: 1469.3 | D21: =B21 -> 302 | E21: =B21*C21 -> 443728.6 | F21: =IFERROR(__xludf.DUMMYFUNCTION("GOOGLEFINANCE(CONCAT(""NSE:"",A21))"),1417.5) -> 1417.5 | G21: =D21*F21 -> 428085 | H21: =(G21-E21)/E21 -> -0.035254883
A22: CPPLUS | B22: 158 | C22: 3678.3 | D22: =B22 -> 158 | E22: =B22*C22 -> 581171.4 | F22: =IFERROR(__xludf.DUMMYFUNCTION("GOOGLEFINANCE(CONCAT(""NSE:"",A22))"),3463.7) -> 3463.7 | G22: =D22*F22 -> 547264.6 | H22: =(G22-E22)/E22 -> -0.058342169
A23: DATAPATTNS | B23: 87 | C23: 4584.5 | D23: =B23 -> 87 | E23: =B23*C23 -> 398851.5 | F23: =IFERROR(__xludf.DUMMYFUNCTION("GOOGLEFINANCE(CONCAT(""NSE:"",A23))"),4397.0) -> 4397 | G23: =D23*F23 -> 382539 | H23: =(G23-E23)/E23 -> -0.04089868
A24: HFCL | B24: 2997 | C24: 226.77 | D24: =B24 -> 2997 | E24: =B24*C24 -> 679629.69 | F24: =IFERROR(__xludf.DUMMYFUNCTION("GOOGLEFINANCE(CONCAT(""NSE:"",A24))"),213.3) -> 213.3 | G24: =D24*F24 -> 639260.1 | H24: =(G24-E24)/E24 -> -0.059399391
A25: HINDCOPPER | B25: 1019 | C25: 525.8 | D25: =B25 -> 1019 | E25: =B25*C25 -> 535790.2 | F25: =IFERROR(__xludf.DUMMYFUNCTION("GOOGLEFINANCE(CONCAT(""NSE:"",A25))"),484.55) -> 484.55 | G25: =D25*F25 -> 493756.45 | H25: =(G25-E25)/E25 -> -0.078451883
A26: IDEA | B26: 34888 | C26: 14.54 | D26: =B26 -> 34888 | E26: =B26*C26 -> 507271.52 | F26: =IFERROR(__xludf.DUMMYFUNCTION("GOOGLEFINANCE(CONCAT(""NSE:"",A26))"),14.27) -> 14.27 | G26: =D26*F26 -> 497851.76 | H26: =(G26-E26)/E26 -> -0.018569464
A27: MOTHERSON | B27: 2011 | C27: 162.1 | D27: =B27 -> 2011 | E27: =B27*C27 -> 325983.1 | F27: =IFERROR(__xludf.DUMMYFUNCTION("GOOGLEFINANCE(CONCAT(""NSE:"",A27))"),161.34) -> 161.34 | G27: =D27*F27 -> 324454.74 | H27: =(G27-E27)/E27 -> -0.0046884639
A28: NAVINFLUOR | B28: 40 | C28: 8544.77 | D28: =B28 -> 40 | E28: =B28*C28 -> 341790.8 | F28: =IFERROR(__xludf.DUMMYFUNCTION("GOOGLEFINANCE(CONCAT(""NSE:"",A28))"),8211.0) -> 8211 | G28: =D28*F28 -> 328440 | H28: =(G28-E28)/E28 -> -0.039061321
A29: PFOCUS | B29: 1556 | C29: 282.2 | D29: =B29 -> 1556 | E29: =B29*C29 -> 439103.2 | F29: =IFERROR(__xludf.DUMMYFUNCTION("GOOGLEFINANCE(CONCAT(""NSE:"",A29))"),338.9) -> 338.9 | G29: =D29*F29 -> 527328.4 | H29: =(G29-E29)/E29 -> 0.20092133
A30: RRKABEL | B30: 169 | C30: 2616.36 | D30: =B30 -> 169 | E30: =B30*C30 -> 442164.84 | F30: =IFERROR(__xludf.DUMMYFUNCTION("GOOGLEFINANCE(CONCAT(""NSE:"",A30))"),2422.4) -> 2422.4 | G30: =D30*F30 -> 409385.6 | H30: =(G30-E30)/E30 -> -0.074133529
A31: SHRIRAMFIN | B31: 373 | C31: 1046.3 | D31: =B31 -> 373 | E31: =B31*C31 -> 390269.9 | F31: =IFERROR(__xludf.DUMMYFUNCTION("GOOGLEFINANCE(CONCAT(""NSE:"",A31))"),989.1) -> 989.1 | G31: =D31*F31 -> 368934.3 | H31: =(G31-E31)/E31 -> -0.054668833
A32: SONACOMS | B32: 430 | C32: 790.15 | D32: =B32 -> 430 | E32: =B32*C32 -> 339764.5 | F32: =IFERROR(__xludf.DUMMYFUNCTION("GOOGLEFINANCE(CONCAT(""NSE:"",A32))"),786.05) -> 786.05 | G32: =D32*F32 -> 338001.5 | H32: =(G32-E32)/E32 -> -0.0051888882
A33: WELCORP | B33: 229 | C33: 2607.88 | D33: =B33 -> 229 | E33: =B33*C33 -> 597204.52 | F33: =IFERROR(__xludf.DUMMYFUNCTION("GOOGLEFINANCE(CONCAT(""NSE:"",A33))"),2491.5) -> 2491.5 | G33: =D33*F33 -> 570553.5 | H33: =(G33-E33)/E33 -> -0.044626286
A34: WELSPUNLIV | B34: 1770 | C34: 199.7 | D34: =B34 -> 1770 | E34: =B34*C34 -> 353469 | F34: =IFERROR(__xludf.DUMMYFUNCTION("GOOGLEFINANCE(CONCAT(""NSE:"",A34))"),208.89) -> 208.89 | G34: =D34*F34 -> 369735.3 | H34: =(G34-E34)/E34 -> 0.046019029
A36: 46176 | B36: Qty | C36: Buying rate | D36: Changed Qty | E36: Amount at entry | F36: Actual Price | G36: Amount by M2M | H36: P&L | L36: Client Code | M36: Name | N36: Scrip Code | O36: Scrip Name | P36: ISIN Code | Q36: Stock | R36: Close Rate | S36: Stk.Value Credit | T36: Stk.Value Debit | U36: Variance | V36: Stock Val
A37: ABCAPITAL | B37: 874 | C37: 343.3 | D37: =B37 -> 874 | E37: =B37*C37 -> 300044.2 | F37: =IFERROR(__xludf.DUMMYFUNCTION("GOOGLEFINANCE(CONCAT(""NSE:"",A37))"),386.35) -> 386.35 | G37: =B37*F37 -> 337669.9 | H37: =(G37-E37)/E37 -> 0.12540052 | J37: =G37-C37*B37 -> 37625.7 | L37: HPC39_5 | M37: AMOL | N37: ABCA01 | O37: ABCAPITAL | P37: INE674K01013 | Q37: 874 | R37: 405.55 | S37: 354450.7 | T37: 0 | U37: 82.74 | V37: 293272.5
A38: APARINDS | B38: 25 | C38: 13574 | D38: =B38 -> 25 | E38: =B38*C38 -> 339350 | F38: =IFERROR(__xludf.DUMMYFUNCTION("GOOGLEFINANCE(CONCAT(""NSE:"",A38))"),17308.0) -> 17308 | G38: =B38*F38 -> 432700 | H38: =(G38-E38)/E38 -> 0.27508472 | J38: =G38-C38*B38 -> 93350 | L38: HPC39_5 | M38: AMOL | N38: ACUT01 | O38: ACUTAAS | Q38: 179 | R38: 3281.6 | S38: 587406.4 | T38: 0 | U38: 0 | V38: 0
A39: BSE | B39: 77 | C39: 3902.1 | D39: =B39 -> 77 | E39: =B39*C39 -> 300461.7 | F39: =IFERROR(__xludf.DUMMYFUNCTION("GOOGLEFINANCE(CONCAT(""NSE:"",A39))"),3271.6) -> 3271.6 | G39: =B39*F39 -> 251913.2 | H39: =(G39-E39)/E39 -> -0.16157966 | J39: =G39-C39*B39 -> -48548.5 | L39: HPC39_5 | M39: AMOL | N39: ADAN06 | O39: ADANIENSOL | P39: INE931S01010 | Q39: 237 | R39: 1581.4 | S39: 374791.8 | T39: 0 | U39: 78.46 | V39: 294061.6
A40: CHENNPETRO | B40: 277 | C40: 1185.2 | D40: =B40 -> 277 | E40: =B40*C40 -> 328300.4 | F40: =IFERROR(__xludf.DUMMYFUNCTION("GOOGLEFINANCE(CONCAT(""NSE:"",A40))"),1417.5) -> 1417.5 | G40: =B40*F40 -> 392647.5 | H40: =(G40-E40)/E40 -> 0.19600068 | J40: =G40-C40*B40 -> 64347.1 | L40: HPC39_5 | M40: AMOL | N40: ADAN01 | O40: ADANIPOWER | P40: INE814H01029 | Q40: 1909 | R40: 212.63 | S40: 405910.7 | T40: 0 | U40: 79.3 | V40: 321887.2
A41: FORCEMOT | B41: 21 | C41: 17900 | D41: =B41 -> 21 | E41: =B41*C41 -> 375900 | F41: =IFERROR(__xludf.DUMMYFUNCTION("GOOGLEFINANCE(CONCAT(""NSE:"",A41))"),17516.0) -> 17516 | G41: =B41*F41 -> 367836 | H41: =(G41-E41)/E41 -> -0.021452514 | J41: =G41-C41*B41 -> -8064 | L41: HPC39_5 | M41: AMOL | N41: ANAN02 | O41: ANANDRATHI | P41: INE463V01026 | Q41: 89 | R41: 2213.4 | S41: 196992.6 | T41: 0 | U41: 85.9 | V41: 169216.6
A42: GMDCLTD | B42: 646 | C42: 663.05 | D42: =B42 -> 646 | E42: =B42*C42 -> 428330.3 | F42: =IFERROR(__xludf.DUMMYFUNCTION("GOOGLEFINANCE(CONCAT(""NSE:"",A42))"),549.9) -> 549.9 | G42: =B42*F42 -> 355235.4 | H42: =(G42-E42)/E42 -> -0.17065078 | J42: =G42-C42*B42 -> -73094.9 | L42: HPC39_5 | M42: AMOL | N42: APAR01 | O42: APARINDS | P42: INE372A01015 | Q42: 25 | R42: 17803 | S42: 445075 | T42: 0 | U42: 76.82 | V42: 341906.6
A43: GVT&D | B43: 90 | C43: 4963 | D43: =B43 -> 90 | E43: =B43*C43 -> 446670 | F43: =IFERROR(__xludf.DUMMYFUNCTION("GOOGLEFINANCE(CONCAT(""NSE:"",A43))"),4297.0) -> 4297 | G43: =B43*F43 -> 386730 | H43: =(G43-E43)/E43 -> -0.13419303 | J43: =G43-C43*B43 -> -59940 | L43: HPC39_5 | M43: AMOL | N43: ATHE01 | O43: ATHERENERG | Q43: 648 | R43: 1616.3 | S43: 1047362 | T43: 0 | U43: 0 | V43: 0
A44: KIRLOSENG | B44: 248 | C44: 1870.36 | D44: =B44 -> 248 | E44: =B44*C44 -> 463849.28 | F44: =IFERROR(__xludf.DUMMYFUNCTION("GOOGLEFINANCE(CONCAT(""NSE:"",A44))"),2125.3) -> 2125.3 | G44: =B44*F44 -> 527074.4 | H44: =(G44-E44)/E44 -> 0.13630531 | J44: =G44-C44*B44 -> 63225.12 | L44: HPC39_5 | M44: AMOL | N44: BELR01 | O44: BELRISE | Q44: 2297 | R44: 229.87 | S44: 528011.4 | T44: 0 | U44: 0 | V44: 0
A45: LTF | B45: 1149 | C45: 265.75 | D45: =B45 -> 1149 | E45: =B45*C45 -> 305346.75 | F45: =IFERROR(__xludf.DUMMYFUNCTION("GOOGLEFINANCE(CONCAT(""NSE:"",A45))"),298.85) -> 298.85 | G45: =B45*F45 -> 343378.65 | H45: =(G45-E45)/E45 -> 0.12455315 | J45: =G45-C45*B45 -> 38031.9 | L45: HPC39_5 | M45: AMOL | N45: BSE001 | O45: BSE | P45: INE118H01025 | Q45: 77 | R45: 3405 | S45: 262185 | T45: 0 | U45: 77.95 | V45: 204373.2
A46: MCX | B46: 163 | C46: 2839.2 | D46: =B46 -> 163 | E46: =B46*C46 -> 462789.6 | F46: =IFERROR(__xludf.DUMMYFUNCTION("GOOGLEFINANCE(CONCAT(""NSE:"",A46))"),3290.8) -> 3290.8 | G46: =B46*F46 -> 536400.4 | H46: =(G46-E46)/E46 -> 0.15905889 | J46: =G46-C46*B46 -> 73610.8 | L46: HPC39_5 | M46: AMOL | N46: CHEN01 | O46: CHENNPETRO | P46: INE178A01016 | Q46: 277 | R46: 1341.1 | S46: 371484.7 | T46: 0 | U46: 76.24 | V46: 283219.9
A47: NETWEB | B47: 111 | C47: 4739.1 | D47: =B47 -> 111 | E47: =B47*C47 -> 526040.1 | F47: =IFERROR(__xludf.DUMMYFUNCTION("GOOGLEFINANCE(CONCAT(""NSE:"",A47))"),4576.0) -> 4576 | G47: =B47*F47 -> 507936 | H47: =(G47-E47)/E47 -> -0.034415817 | J47: =G47-C47*B47 -> -18104.1 | L47: HPC39_5 | M47: AMOL | N47: CUMM01 | O47: CUMMINSIND | P47: INE298A01020 | Q47: 56 | R47: 5193 | S47: 290808 | T47: 0 | U47: 84.27 | V47: 245063.9
A48: POWERINDIA | B48: 11 | C48: 35545 | D48: =B48 -> 11 | E48: =B48*C48 -> 390995 | F48: =IFERROR(__xludf.DUMMYFUNCTION("GOOGLEFINANCE(CONCAT(""NSE:"",A48))"),30810.0) -> 30810 | G48: =B48*F48 -> 338910 | H48: =(G48-E48)/E48 -> -0.13321142 | J48: =G48-C48*B48 -> -52085 | L48: HPC39_5 | M48: AMOL | N48: FORC01 | O48: FORCEMOT | P48: INE451A01017 | Q48: 21 | R48: 17370 | S48: 364770 | T48: 0 | U48: 74.89 | V48: 273176.3
A49: ACUTAAS | B49: 179 | C49: 3118.4 | D49: =B49 -> 179 | E49: =B49*C49 -> 558193.6 | F49: =IFERROR(__xludf.DUMMYFUNCTION("GOOGLEFINANCE(CONCAT(""NSE:"",A49))"),3294.2) -> 3294.2 | G49: =B49*F49 -> 589661.8 | H49: =(G49-E49)/E49 -> 0.056375064 | J49: =G49-C49*B49 -> 31468.2 | L49: HPC39_5 | M49: AMOL | N49: GABR01 | O49: GABRIEL | P49: INE524A01029 | Q49: 337 | R49: 1367.6 | S49: 460881.2 | T49: 0 | U49: 76.05 | V49: 350500.2
A50: ADANIENSOL | B50: 237 | C50: 1458 | D50: =B50 -> 237 | E50: =B50*C50 -> 345546 | F50: =IFERROR(__xludf.DUMMYFUNCTION("GOOGLEFINANCE(CONCAT(""NSE:"",A50))"),1356.1) -> 1356.1 | G50: =B50*F50 -> 321395.7 | H50: =(G50-E50)/E50 -> -0.069890261 | J50: =G50-C50*B50 -> -24150.3 | L50: HPC39_5 | M50: AMOL | N50: GMDC01 | O50: GMDCLTD | P50: INE131A01031 | Q50: 646 | R50: 567.65 | S50: 366701.9 | T50: 0 | U50: 75.75 | V50: 277776.7
A51: ADANIPOWER | B51: 1909 | C51: 231.85 | D51: =B51 -> 1909 | E51: =B51*C51 -> 442601.65 | F51: =IFERROR(__xludf.DUMMYFUNCTION("GOOGLEFINANCE(CONCAT(""NSE:"",A51))"),203.99) -> 203.99 | G51: =B51*F51 -> 389416.91 | H51: =(G51-E51)/E51 -> -0.1201639 | J51: =G51-C51*B51 -> -53184.74 | L51: HPC39_5 | M51: AMOL | N51: GVT&01 | O51: GVT&D | P51: INE200A01026 | Q51: 90 | R51: 4339.2 | S51: 390528 | T51: 0 | U51: 77.33 | V51: 301995.3
A52: ANANDRATHI | B52: 89 | C52: 1749.3 | D52: =B52 -> 89 | E52: =B52*C52 -> 155687.7 | F52: =IFERROR(__xludf.DUMMYFUNCTION("GOOGLEFINANCE(CONCAT(""NSE:"",A52))"),2211.9) -> 2211.9 | G52: =B52*F52 -> 196859.1 | H52: =(G52-E52)/E52 -> 0.26444864 | J52: =G52-C52*B52 -> 41171.4 | L52: HPC39_5 | M52: AMOL | N52: HFCL01 | O52: HFCL | P52: INE548A01028 | Q52: 2420 | R52: 251.47 | S52: 608557.4 | T52: 0 | U52: 75.5 | V52: 459460.8
A53: ATHERENERG | B53: 648 | C53: 978.5 | D53: =B53 -> 648 | E53: =B53*C53 -> 634068 | F53: =IFERROR(__xludf.DUMMYFUNCTION("GOOGLEFINANCE(CONCAT(""NSE:"",A53))"),1542.5) -> 1542.5 | G53: =B53*F53 -> 999540 | H53: =(G53-E53)/E53 -> 0.57639244 | J53: =G53-C53*B53 -> 365472 | L53: HPC39_5 | M53: AMOL | N53: HIND01 | O53: HINDALCO | P53: INE038A01020 | Q53: 298 | R53: 1037.4 | S53: 309145.2 | T53: 0 | U53: 84.62 | V53: 261598.7
A54: BELRISE | B54: 2297 | C54: 219.18 | D54: =B54 -> 2297 | E54: =B54*C54 -> 503456.46 | F54: =IFERROR(__xludf.DUMMYFUNCTION("GOOGLEFINANCE(CONCAT(""NSE:"",A54))"),231.03) -> 231.03 | G54: =B54*F54 -> 530675.91 | H54: =(G54-E54)/E54 -> 0.054065152 | J54: =G54-C54*B54 -> 27219.45 | L54: HPC39_5 | M54: AMOL | N54: HIND06 | O54: HINDCOPPER | P54: INE531E01026 | Q54: 958 | R54: 533.55 | S54: 511140.9 | T54: 0 | U54: 75.13 | V54: 384020.2
A55: CUMMINSIND | B55: 56 | C55: 5685 | D55: =B55 -> 56 | E55: =B55*C55 -> 318360 | F55: =IFERROR(__xludf.DUMMYFUNCTION("GOOGLEFINANCE(CONCAT(""NSE:"",A55))"),5003.0) -> 5003 | G55: =B55*F55 -> 280168 | H55: =(G55-E55)/E55 -> -0.11996482 | J55: =G55-C55*B55 -> -38192 | L55: HPC39_5 | M55: AMOL | N55: IDEA01 | O55: IDEA | P55: INE669E01016 | Q55: 32653 | R55: 14.68 | S55: 479346 | T55: 0 | U55: 75.96 | V55: 364111.3
A56: GABRIEL | B56: 337 | C56: 1063.4 | D56: =B56 -> 337 | E56: =B56*C56 -> 358365.8 | F56: =IFERROR(__xludf.DUMMYFUNCTION("GOOGLEFINANCE(CONCAT(""NSE:"",A56))"),1287.7) -> 1287.7 | G56: =B56*F56 -> 433954.9 | H56: =(G56-E56)/E56 -> 0.21092721 | J56: =G56-C56*B56 -> 75589.1 | L56: HPC39_5 | M56: AMOL | N56: KIRL01 | O56: KIRLOSENG | P56: INE146L01010 | Q56: 248 | R56: 2123.1 | S56: 526528.8 | T56: 0 | U56: 76.86 | V56: 404690
A57: HFCL | B57: 2420 | C57: 195.57 | D57: =B57 -> 2420 | E57: =B57*C57 -> 473279.4 | F57: =IFERROR(__xludf.DUMMYFUNCTION("GOOGLEFINANCE(CONCAT(""NSE:"",A57))"),213.3) -> 213.3 | G57: =B57*F57 -> 516186 | H57: =(G57-E57)/E57 -> 0.090658076 | J57: =G57-C57*B57 -> 42906.6 | L57: HPC39_5 | M57: AMOL | N57: LAUR01 | O57: LAURUSLABS | P57: INE947Q01028 | Q57: 335 | R57: 1938.5 | S57: 649397.5 | T57: 0 | U57: 83.74 | V57: 543805.5
A58: HINDALCO | B58: 298 | C58: 1134.9 | D58: =B58 -> 298 | E58: =B58*C58 -> 338200.2 | F58: =IFERROR(__xludf.DUMMYFUNCTION("GOOGLEFINANCE(CONCAT(""NSE:"",A58))"),983.7) -> 983.7 | G58: =B58*F58 -> 293142.6 | H58: =(G58-E58)/E58 -> -0.1332276 | J58: =G58-C58*B58 -> -45057.6 | L58: HPC39_5 | M58: AMOL | N58: LTF001 | O58: LTF | P58: INE498L01015 | Q58: 1149 | R58: 314.3 | S58: 361130.7 | T58: 0 | U58: 82.28 | V58: 297138.3
A59: HINDCOPPER | B59: 958 | C59: 541.3 | D59: =B59 -> 958 | E59: =B59*C59 -> 518565.4 | F59: =IFERROR(__xludf.DUMMYFUNCTION("GOOGLEFINANCE(CONCAT(""NSE:"",A59))"),484.55) -> 484.55 | G59: =B59*F59 -> 464198.9 | H59: =(G59-E59)/E59 -> -0.1048402 | J59: =G59-C59*B59 -> -54366.5 | L59: HPC39_5 | M59: AMOL | N59: MCX001 | O59: MCX | P59: INE745G01043 | Q59: 163 | R59: 3332 | S59: 543116 | T59: 0 | U59: 80.05 | V59: 434764.4
A60: IDEA | B60: 32653 | C60: 14.17 | D60: =B60 -> 32653 | E60: =B60*C60 -> 462693.01 | F60: =IFERROR(__xludf.DUMMYFUNCTION("GOOGLEFINANCE(CONCAT(""NSE:"",A60))"),14.27) -> 14.27 | G60: =B60*F60 -> 465958.31 | H60: =(G60-E60)/E60 -> 0.007057163 | J60: =G60-C60*B60 -> 3265.3 | L60: HPC39_5 | M60: AMOL | N60: NAM01 | O60: NAM-INDIA | P60: INE298J01013 | Q60: 281 | R60: 1194.4 | S60: 335626.4 | T60: 0 | U60: 80.01 | V60: 268534.7
A61: LAURUSLABS | B61: 335 | C61: 1386.5 | D61: =B61 -> 335 | E61: =B61*C61 -> 464477.5 | F61: =IFERROR(__xludf.DUMMYFUNCTION("GOOGLEFINANCE(CONCAT(""NSE:"",A61))"),1944.7) -> 1944.7 | G61: =B61*F61 -> 651474.5 | H61: =(G61-E61)/E61 -> 0.40259647 | J61: =G61-C61*B61 -> 186997 | L61: HPC39_5 | M61: AMOL | N61: NATI01 | O61: NATIONALUM | P61: INE139A01034 | Q61: 1181 | R61: 394.95 | S61: 466436 | T61: 0 | U61: 78.97 | V61: 368344.5
A62: NAM-INDIA | B62: 281 | C62: 1071.3 | D62: =B62 -> 281 | E62: =B62*C62 -> 301035.3 | F62: =IFERROR(__xludf.DUMMYFUNCTION("GOOGLEFINANCE(CONCAT(""NSE:"",A62))"),1113.3) -> 1113.3 | G62: =B62*F62 -> 312837.3 | H62: =(G62-E62)/E62 -> 0.039204705 | J62: =G62-C62*B62 -> 11802 | L62: HPC39_5 | M62: AMOL | N62: NETW02 | O62: NETWEB | P62: INE0NT901020 | Q62: 111 | R62: 5322.9 | S62: 590841.9 | T62: 0 | U62: 73.07 | V62: 431728.2
A63: NATIONALUM | B63: 1181 | C63: 433.05 | D63: =B63 -> 1181 | E63: =B63*C63 -> 511432.05 | F63: =IFERROR(__xludf.DUMMYFUNCTION("GOOGLEFINANCE(CONCAT(""NSE:"",A63))"),356.3) -> 356.3 | G63: =B63*F63 -> 420790.3 | H63: =(G63-E63)/E63 -> -0.17723127 | J63: =G63-C63*B63 -> -90641.75 | L63: HPC39_5 | M63: AMOL | N63: POWE03 | O63: POWERINDIA | P63: INE07Y701011 | Q63: 11 | R63: 33330 | S63: 366630 | T63: 0 | U63: 76.95 | V63: 282121.8
A64: SCHNEIDER | B64: 276 | C64: 1122.3 | D64: =B64 -> 276 | E64: =B64*C64 -> 309754.8 | F64: =IFERROR(__xludf.DUMMYFUNCTION("GOOGLEFINANCE(CONCAT(""NSE:"",A64))"),1193.0) -> 1193 | G64: =B64*F64 -> 329268 | H64: =(G64-E64)/E64 -> 0.062995634 | J64: =G64-C64*B64 -> 19513.2 | L64: HPC39_5 | M64: AMOL | N64: SCHN01 | O64: SCHNEIDER | P64: INE839M01018 | Q64: 276 | R64: 1201.9 | S64: 331724.4 | T64: 0 | U64: 76 | V64: 252110.5
A65: SYRMA | B65: 389 | C65: 1188 | D65: =B65 -> 389 | E65: =B65*C65 -> 462132 | F65: =IFERROR(__xludf.DUMMYFUNCTION("GOOGLEFINANCE(CONCAT(""NSE:"",A65))"),1642.0) -> 1642 | G65: =B65*F65 -> 638738 | H65: =(G65-E65)/E65 -> 0.38215488 | J65: =G65-C65*B65 -> 176606 | L65: HPC39_5 | M65: AMOL | N65: SYRM01 | O65: SYRMA | P65: INE0DYJ01015 | Q65: 389 | R65: 1474.3 | S65: 573502.7 | T65: 0 | U65: 77.99 | V65: 447274.8
A66: USHAMART | B66: 608 | C66: 489.85 | D66: =B66 -> 608 | E66: =B66*C66 -> 297828.8 | F66: =IFERROR(__xludf.DUMMYFUNCTION("GOOGLEFINANCE(CONCAT(""NSE:"",A66))"),492.45) -> 492.45 | G66: =B66*F66 -> 299409.6 | H66: =(G66-E66)/E66 -> 0.0053077473 | J66: =G66-C66*B66 -> 1580.8 | L66: HPC39_5 | M66: AMOL | N66: USHA01 | O66: USHAMART | P66: INE228A01035 | Q66: 608 | R66: 492.45 | S66: 299409.6 | T66: 0 | U66: 81.87 | V66: 245126.6
A68: 46090 | B68: Qty | C68: Buying rate | D68: Changed Qty | E68: Amount at entry | F68: Actual Price | G68: Amount by M2M | H68: P&L
A69: BSE | B69: 116 | C69: 2723.4 | D69: =B69 -> 116 | E69: =B69*C69 -> 315914.4 | F69: =IFERROR(__xludf.DUMMYFUNCTION("GOOGLEFINANCE(CONCAT(""NSE:"",A69))"),3271.6) -> 3271.6 | G69: =D69*F69 -> 379505.6 | H69: =(G69-E69)/E69 -> 0.2012925
A70: GRSE | B70: 126 | C70: 2475.5 | D70: =B70 -> 126 | E70: =B70*C70 -> 311913 | F70: =IFERROR(__xludf.DUMMYFUNCTION("GOOGLEFINANCE(CONCAT(""NSE:"",A70))"),2337.0) -> 2337 | G70: =D70*F70 -> 294462 | H70: =(G70-E70)/E70 -> -0.055948293
A71: MCX | B71: 187 | C71: 2562.88 | D71: =B71 -> 187 | E71: =B71*C71 -> 479258.56 | F71: =IFERROR(__xludf.DUMMYFUNCTION("GOOGLEFINANCE(CONCAT(""NSE:"",A71))"),3290.8) -> 3290.8 | G71: =D71*F71 -> 615379.6 | H71: =(G71-E71)/E71 -> 0.28402422
A72: POWERINDIA | B72: 14 | C72: 24570.94 | D72: =B72 -> 14 | E72: =B72*C72 -> 343993.16 | F72: =IFERROR(__xludf.DUMMYFUNCTION("GOOGLEFINANCE(CONCAT(""NSE:"",A72))"),30810.0) -> 30810 | G72: =D72*F72 -> 431340 | H72: =(G72-E72)/E72 -> 0.25392028
A73: ABCAPITAL | B73: 1081 | C73: 316.5 | D73: =B73 -> 1081 | E73: =B73*C73 -> 342136.5 | F73: =IFERROR(__xludf.DUMMYFUNCTION("GOOGLEFINANCE(CONCAT(""NSE:"",A73))"),386.35) -> 386.35 | G73: =D73*F73 -> 417644.35 | H73: =(G73-E73)/E73 -> 0.2206951
A74: APARINDS | B74: 29 | C74: 9964 | D74: =B74 -> 29 | E74: =B74*C74 -> 288956 | F74: =IFERROR(__xludf.DUMMYFUNCTION("GOOGLEFINANCE(CONCAT(""NSE:"",A74))"),17308.0) -> 17308 | G74: =D74*F74 -> 501932 | H74: =(G74-E74)/E74 -> 0.73705339
A75: ASHOKLEY | B75: 1690 | C75: 185.49 | D75: =B75 -> 1690 | E75: =B75*C75 -> 313478.1 | F75: =IFERROR(__xludf.DUMMYFUNCTION("GOOGLEFINANCE(CONCAT(""NSE:"",A75))"),157.53) -> 157.53 | G75: =D75*F75 -> 266225.7 | H75: =(G75-E75)/E75 -> -0.15073589
A76: AUBANK | B76: 296 | C76: 924.2 | D76: =B76 -> 296 | E76: =B76*C76 -> 273563.2 | F76: =IFERROR(__xludf.DUMMYFUNCTION("GOOGLEFINANCE(CONCAT(""NSE:"",A76))"),1036.2) -> 1036.2 | G76: =D76*F76 -> 306715.2 | H76: =(G76-E76)/E76 -> 0.12118589
A77: BANKINDIA | B77: 1605 | C77: 151.07 | D77: =B77 -> 1605 | E77: =B77*C77 -> 242467.35 | F77: =IFERROR(__xludf.DUMMYFUNCTION("GOOGLEFINANCE(CONCAT(""NSE:"",A77))"),138.55) -> 138.55 | G77: =D77*F77 -> 222372.75 | H77: =(G77-E77)/E77 -> -0.082875488
A78: BHARATFORG | B78: 139 | C78: 1828.7 | D78: =B78 -> 139 | E78: =B78*C78 -> 254189.3 | F78: =IFERROR(__xludf.DUMMYFUNCTION("GOOGLEFINANCE(CONCAT(""NSE:"",A78))"),1915.6) -> 1915.6 | G78: =D78*F78 -> 266268.4 | H78: =(G78-E78)/E78 -> 0.047520096
A79: CANBK | B79: 1919 | C79: 138.91 | D79: =B79 -> 1919 | E79: =B79*C79 -> 266568.29 | F79: =IFERROR(__xludf.DUMMYFUNCTION("GOOGLEFINANCE(CONCAT(""NSE:"",A79))"),122.6) -> 122.6 | G79: =D79*F79 -> 235269.4 | H79: =(G79-E79)/E79 -> -0.11741415
A80: CCL | B80: 293 | C80: 1008.2 | D80: =B80 -> 293 | E80: =B80*C80 -> 295402.6 | F80: =IFERROR(__xludf.DUMMYFUNCTION("GOOGLEFINANCE(CONCAT(""NSE:"",A80))"),1065.3) -> 1065.3 | G80: =D80*F80 -> 312132.9 | H80: =(G80-E80)/E80 -> 0.056635588
A81: CHENNPETRO | B81: 389 | C81: 944.6 | D81: =B81 -> 389 | E81: =B81*C81 -> 367449.4 | F81: =IFERROR(__xludf.DUMMYFUNCTION("GOOGLEFINANCE(CONCAT(""NSE:"",A81))"),1417.5) -> 1417.5 | G81: =D81*F81 -> 551407.5 | H81: =(G81-E81)/E81 -> 0.50063519
A82: CUB | B82: 1095 | C82: 248.3 | D82: =B82 -> 1095 | E82: =B82*C82 -> 271888.5 | F82: =IFERROR(__xludf.DUMMYFUNCTION("GOOGLEFINANCE(CONCAT(""NSE:"",A82))"),232.4) -> 232.4 | G82: =D82*F82 -> 254478 | H82: =(G82-E82)/E82 -> -0.064035441
A83: DATAPATTNS | B83: 126 | C83: 3488.72 | D83: =B83 -> 126 | E83: =B83*C83 -> 439578.72 | F83: =IFERROR(__xludf.DUMMYFUNCTION("GOOGLEFINANCE(CONCAT(""NSE:"",A83))"),4397.0) -> 4397 | G83: =D83*F83 -> 554022 | H83: =(G83-E83)/E83 -> 0.26034763
A84: FORCEMOT | B84: 28 | C84: 20210 | D84: =B84 -> 28 | E84: =B84*C84 -> 565880 | F84: =IFERROR(__xludf.DUMMYFUNCTION("GOOGLEFINANCE(CONCAT(""NSE:"",A84))"),17516.0) -> 17516 | G84: =D84*F84 -> 490448 | H84: =(G84-E84)/E84 -> -0.13330035
A85: GMDCLTD | B85: 717 | C85: 530.8 | D85: =B85 -> 717 | E85: =B85*C85 -> 380583.6 | F85: =IFERROR(__xludf.DUMMYFUNCTION("GOOGLEFINANCE(CONCAT(""NSE:"",A85))"),549.9) -> 549.9 | G85: =D85*F85 -> 394278.3 | H85: =(G85-E85)/E85 -> 0.035983421
A86: GRAPHITE | B86: 422 | C86: 638.5 | D86: =B86 -> 422 | E86: =B86*C86 -> 269447 | F86: =IFERROR(__xludf.DUMMYFUNCTION("GOOGLEFINANCE(CONCAT(""NSE:"",A86))"),812.7) -> 812.7 | G86: =D86*F86 -> 342959.4 | H86: =(G86-E86)/E86 -> 0.27282694
A87: GVT&D | B87: 136 | C87: 3710.4 | D87: =B87 -> 136 | E87: =B87*C87 -> 504614.4 | F87: =IFERROR(__xludf.DUMMYFUNCTION("GOOGLEFINANCE(CONCAT(""NSE:"",A87))"),4297.0) -> 4297 | G87: =D87*F87 -> 584392 | H87: =(G87-E87)/E87 -> 0.15809616
A88: HINDCOPPER | B88: 896 | C88: 539.95 | D88: =B88 -> 896 | E88: =B88*C88 -> 483795.2 | F88: =IFERROR(__xludf.DUMMYFUNCTION("GOOGLEFINANCE(CONCAT(""NSE:"",A88))"),484.55) -> 484.55 | G88: =D88*F88 -> 434156.8 | H88: =(G88-E88)/E88 -> -0.10260209
A89: INDIANB | B89: 310 | C89: 895 | D89: =B89 -> 310 | E89: =B89*C89 -> 277450 | F89: =IFERROR(__xludf.DUMMYFUNCTION("GOOGLEFINANCE(CONCAT(""NSE:"",A89))"),842.9) -> 842.9 | G89: =D89*F89 -> 261299 | H89: =(G89-E89)/E89 -> -0.05821229
A90: KARURVYSYA | B90: 1068 | C90: 293.76 | D90: =B90 -> 1068 | E90: =B90*C90 -> 313735.68 | F90: =IFERROR(__xludf.DUMMYFUNCTION("GOOGLEFINANCE(CONCAT(""NSE:"",A90))"),333.2) -> 333.2 | G90: =D90*F90 -> 355857.6 | H90: =(G90-E90)/E90 -> 0.13425926
A91: KIRLOSENG | B91: 303 | C91: 1468.26 | D91: =B91 -> 303 | E91: =B91*C91 -> 444882.78 | F91: =IFERROR(__xludf.DUMMYFUNCTION("GOOGLEFINANCE(CONCAT(""NSE:"",A91))"),2125.3) -> 2125.3 | G91: =D91*F91 -> 643965.9 | H91: =(G91-E91)/E91 -> 0.44749568
A92: LAURUSLABS | B92: 288 | C92: 998.3 | D92: =B92 -> 288 | E92: =B92*C92 -> 287510.4 | F92: =IFERROR(__xludf.DUMMYFUNCTION("GOOGLEFINANCE(CONCAT(""NSE:"",A92))"),1944.7) -> 1944.7 | G92: =D92*F92 -> 560073.6 | H92: =(G92-E92)/E92 -> 0.94801162
A93: LTF | B93: 1171 | C93: 265.25 | D93: =B93 -> 1171 | E93: =B93*C93 -> 310607.75 | F93: =IFERROR(__xludf.DUMMYFUNCTION("GOOGLEFINANCE(CONCAT(""NSE:"",A93))"),298.85) -> 298.85 | G93: =D93*F93 -> 349953.35 | H93: =(G93-E93)/E93 -> 0.12667295
A94: MRPL | B94: 1492 | C94: 192.08 | D94: =B94 -> 1492 | E94: =B94*C94 -> 286583.36 | F94: =IFERROR(__xludf.DUMMYFUNCTION("GOOGLEFINANCE(CONCAT(""NSE:"",A94))"),162.81) -> 162.81 | G94: =D94*F94 -> 242912.52 | H94: =(G94-E94)/E94 -> -0.15238442
A95: NATIONALUM | B95: 942 | C95: 392.6 | D95: =B95 -> 942 | E95: =B95*C95 -> 369829.2 | F95: =IFERROR(__xludf.DUMMYFUNCTION("GOOGLEFINANCE(CONCAT(""NSE:"",A95))"),356.3) -> 356.3 | G95: =D95*F95 -> 335634.6 | H95: =(G95-E95)/E95 -> -0.09246052
A96: NETWEB | B96: 132 | C96: 3156.68 | D96: =B96 -> 132 | E96: =B96*C96 -> 416681.76 | F96: =IFERROR(__xludf.DUMMYFUNCTION("GOOGLEFINANCE(CONCAT(""NSE:"",A96))"),4576.0) -> 4576 | G96: =D96*F96 -> 604032 | H96: =(G96-E96)/E96 -> 0.44962429
A97: RBLBANK | B97: 1099 | C97: 294.75 | D97: =B97 -> 1099 | E97: =B97*C97 -> 323930.25 | F97: =IFERROR(__xludf.DUMMYFUNCTION("GOOGLEFINANCE(CONCAT(""NSE:"",A97))"),406.85) -> 406.85 | G97: =D97*F97 -> 447128.15 | H97: =(G97-E97)/E97 -> 0.38032231
A98: SYRMA | B98: 380 | C98: 709.65 | D98: =B98 -> 380 | E98: =B98*C98 -> 269667 | F98: =IFERROR(__xludf.DUMMYFUNCTION("GOOGLEFINANCE(CONCAT(""NSE:"",A98))"),1642.0) -> 1642 | G98: =D98*F98 -> 623960 | H98: =(G98-E98)/E98 -> 1.3138167
A100: 45901 | B100: Qty | C100: Buying rate | D100: Changed Qty | E100: Amount at entry | F100: Actual Price | G100: Amount by M2M | H100: P&L
A101: AMBER | B101: 79 | C101: 7619 | D101: 79 | E101: =B101*C101 -> 601901 | F101: =IFERROR(__xludf.DUMMYFUNCTION("GOOGLEFINANCE(CONCAT(""NSE:"",A101))"),7028.5) -> 7028.5 | G101: =F101*D101 -> 555251.5 | H101: =(G101-E101)/E101 -> -0.077503609
A102: BHARTIHEXA | B102: 259 | C102: 1780.2 | D102: 259 | E102: =B102*C102 -> 461071.8 | F102: =IFERROR(__xludf.DUMMYFUNCTION("GOOGLEFINANCE(CONCAT(""NSE:"",A102))"),1473.0) -> 1473 | G102: =F102*D102 -> 381507 | H102: =(G102-E102)/E102 -> -0.17256488
A103: BSE | B103: 381 | C103: 2229.4 | D103: 381 | E103: =B103*C103 -> 849401.4 | F103: =IFERROR(__xludf.DUMMYFUNCTION("GOOGLEFINANCE(CONCAT(""NSE:"",A103))"),3271.6) -> 3271.6 | G103: =F103*D103 -> 1246479.6 | H103: =(G103-E103)/E103 -> 0.46748004
A104: COFORGE | B104: 262 | C104: 1765 | D104: 262 | E104: =B104*C104 -> 462430 | F104: =IFERROR(__xludf.DUMMYFUNCTION("GOOGLEFINANCE(CONCAT(""NSE:"",A104))"),1773.7) -> 1773.7 | G104: =F104*D104 -> 464709.4 | H104: =(G104-E104)/E104 -> 0.0049291785
...

Sheet hpc39_7
A1: Total cash to be allocated | B1: 20000000 | C1: Rebalance Date | D1: 46238
A2: Target rebalance date | B2: 46327
A3: 46238 | B3: qty | C3: Buying Rate | D3: Changed Qty | E3: Amount at entry | F3: Actual Price | G3: Amount by M2M | H3: P&L
A4: APARINDS | B4: 41 | C4: 15857.52 | D4: 41 | E4: =B4*C4 -> 650158.32 | F4: =IFERROR(__xludf.DUMMYFUNCTION("GOOGLEFINANCE(CONCAT(""NSE:"",A4))"),17308.0) -> 17308 | G4: =D4*F4 -> 709628 | H4: =(G4-E4)/E4 -> 0.091469536
A5: DATAPATTNS | B5: 139 | C5: 4532 | D5: 139 | E5: =B5*C5 -> 629948 | F5: =IFERROR(__xludf.DUMMYFUNCTION("GOOGLEFINANCE(CONCAT(""NSE:"",A5))"),4397.0) -> 4397 | G5: =D5*F5 -> 611183 | H5: =(G5-E5)/E5 -> -0.029788173
A6: KIRLOSENG | B6: 495 | C6: 2260.6 | D6: 495 | E6: =B6*C6 -> 1118997 | F6: =IFERROR(__xludf.DUMMYFUNCTION("GOOGLEFINANCE(CONCAT(""NSE:"",A6))"),2125.3) -> 2125.3 | G6: =D6*F6 -> 1052023.5 | H6: =(G6-E6)/E6 -> -0.059851367
A7: LAURUSLABS | B7: 466 | C7: 1835.2 | D7: 466 | E7: =B7*C7 -> 855203.2 | F7: =IFERROR(__xludf.DUMMYFUNCTION("GOOGLEFINANCE(CONCAT(""NSE:"",A7))"),1944.7) -> 1944.7 | G7: =D7*F7 -> 906230.2 | H7: =(G7-E7)/E7 -> 0.059666521
A8: MCX | B8: 244 | C8: 2587.32 | D8: 244 | E8: =B8*C8 -> 631306.08 | F8: =IFERROR(__xludf.DUMMYFUNCTION("GOOGLEFINANCE(CONCAT(""NSE:"",A8))"),3290.8) -> 3290.8 | G8: =D8*F8 -> 802955.2 | H8: =(G8-E8)/E8 -> 0.27189524
A9: NATIONALUM | B9: 2114 | C9: 381 | D9: 2114 | E9: =B9*C9 -> 805434 | F9: =IFERROR(__xludf.DUMMYFUNCTION("GOOGLEFINANCE(CONCAT(""NSE:"",A9))"),356.3) -> 356.3 | G9: =D9*F9 -> 753218.2 | H9: =(G9-E9)/E9 -> -0.064829396
A10: NETWEB | B10: 194 | C10: 4804.1 | D10: 194 | E10: =B10*C10 -> 931995.4 | F10: =IFERROR(__xludf.DUMMYFUNCTION("GOOGLEFINANCE(CONCAT(""NSE:"",A10))"),4576.0) -> 4576 | G10: =D10*F10 -> 887744 | H10: =(G10-E10)/E10 -> -0.047480277
A11: SYRMA | B11: 573 | C11: 1438.23 | D11: 573 | E11: =B11*C11 -> 824105.79 | F11: =IFERROR(__xludf.DUMMYFUNCTION("GOOGLEFINANCE(CONCAT(""NSE:"",A11))"),1642.0) -> 1642 | G11: =D11*F11 -> 940866 | H11: =(G11-E11)/E11 -> 0.14168109
A12: WELCORP | B12: 429 | C12: 1769.2 | D12: 429 | E12: =B12*C12 -> 758986.8 | F12: =IFERROR(__xludf.DUMMYFUNCTION("GOOGLEFINANCE(CONCAT(""NSE:"",A12))"),2491.5) -> 2491.5 | G12: =D12*F12 -> 1068853.5 | H12: =(G12-E12)/E12 -> 0.40826362
A13: ACUTAAS | B13: 317 | C13: 3263.1 | D13: 317 | E13: =B13*C13 -> 1034402.7 | F13: =IFERROR(__xludf.DUMMYFUNCTION("GOOGLEFINANCE(CONCAT(""NSE:"",A13))"),3294.2) -> 3294.2 | G13: =D13*F13 -> 1044261.4 | H13: =(G13-E13)/E13 -> 0.0095308143
A14: ADANIENSOL | B14: 541 | C14: 1650.7 | D14: 541 | E14: =B14*C14 -> 893028.7 | F14: =IFERROR(__xludf.DUMMYFUNCTION("GOOGLEFINANCE(CONCAT(""NSE:"",A14))"),1356.1) -> 1356.1 | G14: =D14*F14 -> 733650.1 | H14: =(G14-E14)/E14 -> -0.17846974
A15: ADANIPOWER | B15: 3530 | C15: 210.66 | D15: 3530 | E15: =B15*C15 -> 743629.8 | F15: =IFERROR(__xludf.DUMMYFUNCTION("GOOGLEFINANCE(CONCAT(""NSE:"",A15))"),203.99) -> 203.99 | G15: =D15*F15 -> 720084.7 | H15: =(G15-E15)/E15 -> -0.031662394
A16: AEGISLOG | B16: 541 | C16: 1400.7 | D16: 541 | E16: =B16*C16 -> 757778.7 | F16: =IFERROR(__xludf.DUMMYFUNCTION("GOOGLEFINANCE(CONCAT(""NSE:"",A16))"),1365.5) -> 1365.5 | G16: =D16*F16 -> 738735.5 | H16: =(G16-E16)/E16 -> -0.025130292
A17: ATHERENERG | B17: 933 | C17: 1438.5 | D17: 933 | E17: =B17*C17 -> 1342120.5 | F17: =IFERROR(__xludf.DUMMYFUNCTION("GOOGLEFINANCE(CONCAT(""NSE:"",A17))"),1542.5) -> 1542.5 | G17: =D17*F17 -> 1439152.5 | H17: =(G17-E17)/E17 -> 0.072297532
A18: BELRISE | B18: 2638 | C18: 243.66 | D18: 2638 | E18: =B18*C18 -> 642775.08 | F18: =IFERROR(__xludf.DUMMYFUNCTION("GOOGLEFINANCE(CONCAT(""NSE:"",A18))"),231.03) -> 231.03 | G18: =D18*F18 -> 609457.14 | H18: =(G18-E18)/E18 -> -0.051834524
A19: BHARATFORG | B19: 341 | C19: 2220.64 | D19: 341 | E19: =B19*C19 -> 757238.24 | F19: =IFERROR(__xludf.DUMMYFUNCTION("GOOGLEFINANCE(CONCAT(""NSE:"",A19))"),1915.6) -> 1915.6 | G19: =D19*F19 -> 653219.6 | H19: =(G19-E19)/E19 -> -0.1373658
A20: BHEL | B20: 1597 | C20: 413 | D20: 1597 | E20: =B20*C20 -> 659561 | F20: =IFERROR(__xludf.DUMMYFUNCTION("GOOGLEFINANCE(CONCAT(""NSE:"",A20))"),420.35) -> 420.35 | G20: =D20*F20 -> 671298.95 | H20: =(G20-E20)/E20 -> 0.01779661
A21: CEMPRO | B21: 615 | C21: 1308.2 | D21: 615 | E21: =B21*C21 -> 804543 | F21: =IFERROR(__xludf.DUMMYFUNCTION("GOOGLEFINANCE(CONCAT(""NSE:"",A21))"),1254.1) -> 1254.1 | G21: =D21*F21 -> 771271.5 | H21: =(G21-E21)/E21 -> -0.041354533
A22: CHENNPETRO | B22: 619 | C22: 1311.3 | D22: 619 | E22: =B22*C22 -> 811694.7 | F22: =IFERROR(__xludf.DUMMYFUNCTION("GOOGLEFINANCE(CONCAT(""NSE:"",A22))"),1417.5) -> 1417.5 | G22: =D22*F22 -> 877432.5 | H22: =(G22-E22)/E22 -> 0.080988332
A23: FEDERALBNK | B23: 1929 | C23: 358.75 | D23: 1929 | E23: =B23*C23 -> 692028.75 | F23: =IFERROR(__xludf.DUMMYFUNCTION("GOOGLEFINANCE(CONCAT(""NSE:"",A23))"),339.5) -> 339.5 | G23: =D23*F23 -> 654895.5 | H23: =(G23-E23)/E23 -> -0.053658537
A24: GRANULES | B24: 828 | C24: 835.82 | D24: 828 | E24: =B24*C24 -> 692058.96 | F24: =IFERROR(__xludf.DUMMYFUNCTION("GOOGLEFINANCE(CONCAT(""NSE:"",A24))"),860.3) -> 860.3 | G24: =D24*F24 -> 712328.4 | H24: =(G24-E24)/E24 -> 0.029288603
A25: HFCL | B25: 5754 | C25: 209.34 | D25: 5754 | E25: =B25*C25 -> 1204542.4 | F25: =IFERROR(__xludf.DUMMYFUNCTION("GOOGLEFINANCE(CONCAT(""NSE:"",A25))"),213.3) -> 213.3 | G25: =D25*F25 -> 1227328.2 | H25: =(G25-E25)/E25 -> 0.018916595
A26: HINDCOPPER | B26: 1932 | C26: 505.1 | D26: 1932 | E26: =B26*C26 -> 975853.2 | F26: =IFERROR(__xludf.DUMMYFUNCTION("GOOGLEFINANCE(CONCAT(""NSE:"",A26))"),484.55) -> 484.55 | G26: =D26*F26 -> 936150.6 | H26: =(G26-E26)/E26 -> -0.040685013
A27: HONASA | B27: 1325 | C27: 462.9 | D27: 1325 | E27: =B27*C27 -> 613342.5 | F27: =IFERROR(__xludf.DUMMYFUNCTION("GOOGLEFINANCE(CONCAT(""NSE:"",A27))"),465.25) -> 465.25 | G27: =D27*F27 -> 616456.25 | H27: =(G27-E27)/E27 -> 0.0050766904
A28: IDEA | B28: 66275 | C28: 12.99 | D28: 66275 | E28: =B28*C28 -> 860912.25 | F28: =IFERROR(__xludf.DUMMYFUNCTION("GOOGLEFINANCE(CONCAT(""NSE:"",A28))"),14.27) -> 14.27 | G28: =D28*F28 -> 945744.25 | H28: =(G28-E28)/E28 -> 0.098537336
A29: J&KBANK | B29: 3805 | C29: 158.75 | D29: 3805 | E29: =B29*C29 -> 604043.75 | F29: =IFERROR(__xludf.DUMMYFUNCTION("GOOGLEFINANCE(CONCAT(""NSE:"",A29))"),148.92) -> 148.92 | G29: =D29*F29 -> 566640.6 | H29: =(G29-E29)/E29 -> -0.06192126
A30: PFOCUS | B30: 2770 | C30: 304.81 | D30: 2770 | E30: =B30*C30 -> 844323.7 | F30: =IFERROR(__xludf.DUMMYFUNCTION("GOOGLEFINANCE(CONCAT(""NSE:"",A30))"),338.9) -> 338.9 | G30: =D30*F30 -> 938753 | H30: =(G30-E30)/E30 -> 0.11184016
A31: RRKABEL | B31: 318 | C31: 2744.5 | D31: 318 | E31: =B31*C31 -> 872751 | F31: =IFERROR(__xludf.DUMMYFUNCTION("GOOGLEFINANCE(CONCAT(""NSE:"",A31))"),2422.4) -> 2422.4 | G31: =D31*F31 -> 770323.2 | H31: =(G31-E31)/E31 -> -0.117362
A32: SHRIRAMFIN | B32: 647 | C32: 1096.3 | D32: 647 | E32: =B32*C32 -> 709306.1 | F32: =IFERROR(__xludf.DUMMYFUNCTION("GOOGLEFINANCE(CONCAT(""NSE:"",A32))"),989.1) -> 989.1 | G32: =D32*F32 -> 639947.7 | H32: =(G32-E32)/E32 -> -0.097783453
A33: SONACOMS | B33: 852 | C33: 796.97 | D33: 852 | E33: =B33*C33 -> 679018.44 | F33: =IFERROR(__xludf.DUMMYFUNCTION("GOOGLEFINANCE(CONCAT(""NSE:"",A33))"),786.05) -> 786.05 | G33: =D33*F33 -> 669714.6 | H33: =(G33-E33)/E33 -> -0.013701896
A35: 46146 | B35: qty | C35: Buying Rate | D35: Changed Qty | E35: Amount at entry | F35: Actual Price | G35: Amount by M2M | H35: P&L
A36: ABCAPITAL | B36: 1639 | C36: 357.33 | D36: =B36 -> 1639 | E36: =B36*C36 -> 585663.87 | F36: =IFERROR(__xludf.DUMMYFUNCTION("GOOGLEFINANCE(CONCAT(""NSE:"",A36))"),386.35) -> 386.35 | G36: =D36*F36 -> 633227.65 | H36: =(G36-E36)/E36 -> 0.081213444 | I36: HPC39_7 | J36: AMOL | K36: ABCA01 | L36: ABCAPITAL | M36: INE674K01013 | N36: 1639 | O36: 424.35 | P36: 695509.7
A37: ANANDRATHI | B37: 203 | C37: 3615 | D37: =B37 -> 203 | E37: =B37*C37 -> 733845 | F37: =IFERROR(__xludf.DUMMYFUNCTION("GOOGLEFINANCE(CONCAT(""NSE:"",A37))"),2211.9) -> 2211.9 | G37: =D37*F37 -> 449015.7 | H37: =(G37-E37)/E37 -> -0.38813278 | I37: HPC39_7 | J37: AMOL | K37: ABDL01 | L37: ABDL | N37: 1167 | O37: 619.55 | P37: 723014.9
A38: BSE | B38: 171 | C38: 3703 | D38: =B38 -> 171 | E38: =B38*C38 -> 633213 | F38: =IFERROR(__xludf.DUMMYFUNCTION("GOOGLEFINANCE(CONCAT(""NSE:"",A38))"),3271.6) -> 3271.6 | G38: =D38*F38 -> 559443.6 | H38: =(G38-E38)/E38 -> -0.11650014 | I38: HPC39_7 | J38: AMOL | K38: ADAN01 | L38: ADANIPOWER | M38: INE814H01029 | N38: 3368 | O38: 213.65 | P38: 719573.2
A39: CHENNPETRO | B39: 613 | C39: 1112.2 | D39: =B39 -> 613 | E39: =B39*C39 -> 681778.6 | F39: =IFERROR(__xludf.DUMMYFUNCTION("GOOGLEFINANCE(CONCAT(""NSE:"",A39))"),1417.5) -> 1417.5 | G39: =D39*F39 -> 868927.5 | H39: =(G39-E39)/E39 -> 0.27450099 | I39: HPC39_7 | J39: AMOL | K39: ANAN02 | L39: ANANDRATHI | M39: INE463V01026 | N39: 203 | O39: 2058.7 | P39: 417916.1
A40: FORCEMOT | B40: 46 | C40: 19235.19 | D40: =B40 -> 46 | E40: =B40*C40 -> 884818.74 | F40: =IFERROR(__xludf.DUMMYFUNCTION("GOOGLEFINANCE(CONCAT(""NSE:"",A40))"),17516.0) -> 17516 | G40: =D40*F40 -> 805736 | H40: =(G40-E40)/E40 -> -0.089377334 | I40: HPC39_7 | J40: AMOL | K40: APAR01 | L40: APARINDS | M40: INE372A01015 | N40: 72 | O40: 14746 | P40: 1061712
A41: GMDCLTD | B41: 1413 | C41: 737.6 | D41: =B41 -> 1413 | E41: =B41*C41 -> 1042228.8 | F41: =IFERROR(__xludf.DUMMYFUNCTION("GOOGLEFINANCE(CONCAT(""NSE:"",A41))"),549.9) -> 549.9 | G41: =D41*F41 -> 777008.7 | H41: =(G41-E41)/E41 -> -0.25447397 | I41: HPC39_7 | J41: AMOL | K41: BSE001 | L41: BSE | M41: INE118H01025 | N41: 171 | O41: 3575 | P41: 611325
A42: GRSE | B42: 217 | C42: 2797 | D42: =B42 -> 217 | E42: =B42*C42 -> 606949 | F42: =IFERROR(__xludf.DUMMYFUNCTION("GOOGLEFINANCE(CONCAT(""NSE:"",A42))"),2337.0) -> 2337 | G42: =D42*F42 -> 507129 | H42: =(G42-E42)/E42 -> -0.16446192 | I42: HPC39_7 | J42: AMOL | K42: CCL001 | L42: CCL | M42: INE421D01022 | N42: 621 | O42: 1152.4 | P42: 715640.4
A43: GVT&D | B43: 236 | C43: 4565 | D43: =B43 -> 236 | E43: =B43*C43 -> 1077340 | F43: =IFERROR(__xludf.DUMMYFUNCTION("GOOGLEFINANCE(CONCAT(""NSE:"",A43))"),4297.0) -> 4297 | G43: =D43*F43 -> 1014092 | H43: =(G43-E43)/E43 -> -0.058707558 | I43: HPC39_7 | J43: AMOL | K43: CHEN01 | L43: CHENNPETRO | M43: INE178A01016 | N43: 613 | O43: 1325.5 | P43: 812531.5
A44: HINDCOPPER | B44: 1921 | C44: 533.55 | D44: =B44 -> 1921 | E44: =B44*C44 -> 1024949.6 | F44: =IFERROR(__xludf.DUMMYFUNCTION("GOOGLEFINANCE(CONCAT(""NSE:"",A44))"),484.55) -> 484.55 | G44: =D44*F44 -> 930820.55 | H44: =(G44-E44)/E44 -> -0.091837691 | I44: HPC39_7 | J44: AMOL | K44: CUMM01 | L44: CUMMINSIND | M44: INE298A01020 | N44: 117 | O44: 5550 | P44: 649350
A45: LAURUSLABS | B45: 506 | C45: 1169.5 | D45: =B45 -> 506 | E45: =B45*C45 -> 591767 | F45: =IFERROR(__xludf.DUMMYFUNCTION("GOOGLEFINANCE(CONCAT(""NSE:"",A45))"),1944.7) -> 1944.7 | G45: =D45*F45 -> 984018.2 | H45: =(G45-E45)/E45 -> 0.66284737 | I45: HPC39_7 | J45: AMOL | K45: DATA02 | L45: DATAPATTNS | M45: INE0IX101010 | N45: 179 | O45: 4428.8 | P45: 792755.2
A46: MCX | B46: 327 | C46: 2903.52 | D46: =B46 -> 327 | E46: =B46*C46 -> 949451.04 | F46: =IFERROR(__xludf.DUMMYFUNCTION("GOOGLEFINANCE(CONCAT(""NSE:"",A46))"),3290.8) -> 3290.8 | G46: =D46*F46 -> 1076091.6 | H46: =(G46-E46)/E46 -> 0.13338293 | I46: HPC39_7 | J46: AMOL | K46: FORC01 | L46: FORCEMOT | M46: INE451A01017 | N46: 46 | O46: 18494 | P46: 850724
A47: NETWEB | B47: 271 | C47: 4071.3 | D47: =B47 -> 271 | E47: =B47*C47 -> 1103322.3 | F47: =IFERROR(__xludf.DUMMYFUNCTION("GOOGLEFINANCE(CONCAT(""NSE:"",A47))"),4576.0) -> 4576 | G47: =D47*F47 -> 1240096 | H47: =(G47-E47)/E47 -> 0.12396532 | I47: HPC39_7 | J47: AMOL | K47: GABR01 | L47: GABRIEL | M47: INE524A01029 | N47: 793 | O47: 1527.4 | P47: 1211228
A48: POWERINDIA | B48: 28 | C48: 34025 | D48: =B48 -> 28 | E48: =B48*C48 -> 952700 | F48: =IFERROR(__xludf.DUMMYFUNCTION("GOOGLEFINANCE(CONCAT(""NSE:"",A48))"),30810.0) -> 30810 | G48: =D48*F48 -> 862680 | H48: =(G48-E48)/E48 -> -0.094489346 | I48: HPC39_7 | J48: AMOL | K48: GALL01 | L48: GALLANTT | N48: 884 | O48: 627.6 | P48: 554798.4
A49: ABDL | B49: 1167 | C49: 540.23 | D49: =B49 -> 1167 | E49: =B49*C49 -> 630448.41 | F49: =IFERROR(__xludf.DUMMYFUNCTION("GOOGLEFINANCE(CONCAT(""NSE:"",A49))"),647.1) -> 647.1 | G49: =D49*F49 -> 755165.7 | H49: =(G49-E49)/E49 -> 0.19782315 | I49: HPC39_7 | J49: AMOL | K49: GESH01 | L49: GESHIP | M49: INE017A01032 | N49: 372 | O49: 1398.4 | P49: 520204.8
A50: ADANIPOWER | B50: 3368 | C50: 233 | D50: =B50 -> 3368 | E50: =B50*C50 -> 784744 | F50: =IFERROR(__xludf.DUMMYFUNCTION("GOOGLEFINANCE(CONCAT(""NSE:"",A50))"),203.99) -> 203.99 | G50: =D50*F50 -> 687038.32 | H50: =(G50-E50)/E50 -> -0.12450644 | I50: HPC39_7 | J50: AMOL | K50: GMDC01 | L50: GMDCLTD | M50: INE131A01031 | N50: 1413 | O50: 561 | P50: 792693
A51: APARINDS | B51: 72 | C51: 12685 | D51: =B51 -> 72 | E51: =B51*C51 -> 913320 | F51: =IFERROR(__xludf.DUMMYFUNCTION("GOOGLEFINANCE(CONCAT(""NSE:"",A51))"),17308.0) -> 17308 | G51: =D51*F51 -> 1246176 | H51: =(G51-E51)/E51 -> 0.3644462 | I51: HPC39_7 | J51: AMOL | K51: GPIL01 | L51: GPIL | M51: INE177H01039 | N51: 1909 | O51: 244.37 | P51: 466502.3
A52: CCL | B52: 621 | C52: 1167.4 | D52: =B52 -> 621 | E52: =B52*C52 -> 724955.4 | F52: =IFERROR(__xludf.DUMMYFUNCTION("GOOGLEFINANCE(CONCAT(""NSE:"",A52))"),1065.3) -> 1065.3 | G52: =D52*F52 -> 661551.3 | H52: =(G52-E52)/E52 -> -0.087459311 | I52: HPC39_7 | J52: AMOL | K52: GRSE01 | L52: GRSE | M52: INE382Z01011 | N52: 217 | O52: 2582.7 | P52: 560445.9
A53: CUMMINSIND | B53: 117 | C53: 5252.48 | D53: =B53 -> 117 | E53: =B53*C53 -> 614540.16 | F53: =IFERROR(__xludf.DUMMYFUNCTION("GOOGLEFINANCE(CONCAT(""NSE:"",A53))"),5003.0) -> 5003 | G53: =D53*F53 -> 585351 | H53: =(G53-E53)/E53 -> -0.047497563 | I53: HPC39_7 | J53: AMOL | K53: GVT&01 | L53: GVT&D | M53: INE200A01026 | N53: 236 | O53: 4370 | P53: 1031320
A54: DATAPATTNS | B54: 179 | C54: 4131.13 | D54: =B54 -> 179 | E54: =B54*C54 -> 739472.27 | F54: =IFERROR(__xludf.DUMMYFUNCTION("GOOGLEFINANCE(CONCAT(""NSE:"",A54))"),4397.0) -> 4397 | G54: =D54*F54 -> 787063 | H54: =(G54-E54)/E54 -> 0.064357694 | I54: HPC39_7 | J54: AMOL | K54: HBLE01 | L54: HBLENGINE | M54: INE292B01021 | N54: 786 | O54: 739.2 | P54: 581011.2
A55: GABRIEL | B55: 793 | C55: 1045.4 | D55: =B55 -> 793 | E55: =B55*C55 -> 829002.2 | F55: =IFERROR(__xludf.DUMMYFUNCTION("GOOGLEFINANCE(CONCAT(""NSE:"",A55))"),1287.7) -> 1287.7 | G55: =D55*F55 -> 1021146.1 | H55: =(G55-E55)/E55 -> 0.23177731 | I55: HPC39_7 | J55: AMOL | K55: HIND06 | L55: HINDCOPPER | M55: INE531E01026 | N55: 1921 | O55: 495.05 | P55: 950991.1
A56: GALLANTT | B56: 884 | C56: 879.54 | D56: =B56 -> 884 | E56: =B56*C56 -> 777513.36 | F56: =IFERROR(__xludf.DUMMYFUNCTION("GOOGLEFINANCE(CONCAT(""NSE:"",A56))"),534.15) -> 534.15 | G56: =D56*F56 -> 472188.6 | H56: =(G56-E56)/E56 -> -0.39269391 | I56: HPC39_7 | J56: AMOL | K56: KIRL01 | L56: KIRLOSENG | M56: INE146L01010 | N56: 526 | O56: 2225.2 | P56: 1170455
A57: GESHIP | B57: 372 | C57: 1526.7 | D57: =B57 -> 372 | E57: =B57*C57 -> 567932.4 | F57: =IFERROR(__xludf.DUMMYFUNCTION("GOOGLEFINANCE(CONCAT(""NSE:"",A57))"),1405.4) -> 1405.4 | G57: =D57*F57 -> 522808.8 | H57: =(G57-E57)/E57 -> -0.079452414 | I57: HPC39_7 | J57: AMOL | K57: LAUR01 | L57: LAURUSLABS | M57: INE947Q01028 | N57: 506 | O57: 1811.4 | P57: 916568.4
A58: GPIL | B58: 1909 | C58: 302.55 | D58: =B58 -> 1909 | E58: =B58*C58 -> 577567.95 | F58: =IFERROR(__xludf.DUMMYFUNCTION("GOOGLEFINANCE(CONCAT(""NSE:"",A58))"),238.04) -> 238.04 | G58: =D58*F58 -> 454418.36 | H58: =(G58-E58)/E58 -> -0.21322096 | I58: HPC39_7 | J58: AMOL | K58: MCX001 | L58: MCX | M58: INE745G01043 | N58: 327 | O58: 2642.1 | P58: 863966.7
A59: HBLENGINE | B59: 786 | C59: 798 | D59: =B59 -> 786 | E59: =B59*C59 -> 627228 | F59: =IFERROR(__xludf.DUMMYFUNCTION("GOOGLEFINANCE(CONCAT(""NSE:"",A59))"),749.35) -> 749.35 | G59: =D59*F59 -> 588989.1 | H59: =(G59-E59)/E59 -> -0.060964912 | I59: HPC39_7 | J59: AMOL | K59: NATI01 | L59: NATIONALUM | M59: INE139A01034 | N59: 2278 | O59: 369 | P59: 840582
A60: KIRLOSENG | B60: 526 | C60: 1736.57 | D60: =B60 -> 526 | E60: =B60*C60 -> 913435.82 | F60: =IFERROR(__xludf.DUMMYFUNCTION("GOOGLEFINANCE(CONCAT(""NSE:"",A60))"),2125.3) -> 2125.3 | G60: =D60*F60 -> 1117907.8 | H60: =(G60-E60)/E60 -> 0.22384931 | I60: HPC39_7 | J60: AMOL | K60: NETW02 | L60: NETWEB | M60: INE0NT901020 | N60: 271 | O60: 4586 | P60: 1242806
A61: NATIONALUM | B61: 2278 | C61: 407.65 | D61: =B61 -> 2278 | E61: =B61*C61 -> 928626.7 | F61: =IFERROR(__xludf.DUMMYFUNCTION("GOOGLEFINANCE(CONCAT(""NSE:"",A61))"),356.3) -> 356.3 | G61: =D61*F61 -> 811651.4 | H61: =(G61-E61)/E61 -> -0.1259659 | I61: HPC39_7 | J61: AMOL | K61: POWE03 | L61: POWERINDIA | M61: INE07Y701011 | N61: 28 | O61: 32000 | P61: 896000
A62: SCHNEIDER | B62: 647 | C62: 1347.9 | D62: =B62 -> 647 | E62: =B62*C62 -> 872091.3 | F62: =IFERROR(__xludf.DUMMYFUNCTION("GOOGLEFINANCE(CONCAT(""NSE:"",A62))"),1193.0) -> 1193 | G62: =D62*F62 -> 771871 | H62: =(G62-E62)/E62 -> -0.1149195 | I62: HPC39_7 | J62: AMOL | K62: SCHN01 | L62: SCHNEIDER | M62: INE839M01018 | N62: 647 | O62: 1346.1 | P62: 870926.7
A63: SCI | B63: 2321 | C63: 326.5 | D63: =B63 -> 2321 | E63: =B63*C63 -> 757806.5 | F63: =IFERROR(__xludf.DUMMYFUNCTION("GOOGLEFINANCE(CONCAT(""NSE:"",A63))"),268.05) -> 268.05 | G63: =D63*F63 -> 622144.05 | H63: =(G63-E63)/E63 -> -0.17901991 | I63: HPC39_7 | J63: AMOL | K63: SCI001 | L63: SCI | M63: INE109A01011 | N63: 2321 | O63: 292.65 | P63: 679240.7
A64: SYRMA | B64: 863 | C64: 1037.85 | D64: =B64 -> 863 | E64: =B64*C64 -> 895664.55 | F64: =IFERROR(__xludf.DUMMYFUNCTION("GOOGLEFINANCE(CONCAT(""NSE:"",A64))"),1642.0) -> 1642 | G64: =D64*F64 -> 1417046 | H64: =(G64-E64)/E64 -> 0.58211688 | I64: HPC39_7 | J64: AMOL | K64: SYRM01 | L64: SYRMA | M64: INE0DYJ01015 | N64: 863 | O64: 1360.6 | P64: 1174198
A65: WELCORP | B65: 463 | C65: 1240.4 | D65: =B65 -> 463 | E65: =B65*C65 -> 574305.2 | F65: =IFERROR(__xludf.DUMMYFUNCTION("GOOGLEFINANCE(CONCAT(""NSE:"",A65))"),2491.5) -> 2491.5 | G65: =D65*F65 -> 1153564.5 | H65: =(G65-E65)/E65 -> 1.0086263 | I65: HPC39_7 | J65: AMOL | K65: WELC01 | L65: WELCORP | M65: INE191B01025 | N65: 463 | O65: 1715.3 | P65: 794183.9
A67: 46057 | B67: qty | C67: Buying Rate | D67: Changed Qty | E67: Amount at entry | F67: Actual Price | G67: Amount by M2M | H67: P&L
A68: ANANDRATHI | B68: 204 | C68: 2946.7 | D68: =B68 -> 204 | E68: =B68*C68 -> 601126.8 | F68: =IFERROR(__xludf.DUMMYFUNCTION("GOOGLEFINANCE(CONCAT(""NSE:"",A68))"),2211.9) -> 2211.9 | G68: =D68*F68 -> 451227.6 | H68: =(G68-E68)/E68 -> -0.24936369 | J68: ABCAPITAL | K68: INE674K01013 | L68: 2115 | M68: 348.45
A69: BSE | B69: 193 | C69: 2852.4 | D69: =B69 -> 193 | E69: =B69*C69 -> 550513.2 | F69: =IFERROR(__xludf.DUMMYFUNCTION("GOOGLEFINANCE(CONCAT(""NSE:"",A69))"),3271.6) -> 3271.6 | G69: =D69*F69 -> 631418.8 | H69: =(G69-E69)/E69 -> 0.14696396 | J69: ANANDRATHI | K69: INE463V01026 | L69: 204 | M69: 3586.5
A70: ECLERX | B70: 115 | C70: 4461.92 | D70: =B70 -> 115 | E70: =B70*C70 -> 513120.8 | F70: =IFERROR(__xludf.DUMMYFUNCTION("GOOGLEFINANCE(CONCAT(""NSE:"",A70))"),1993.1) -> 1993.1 | G70: =D70*F70 -> 229206.5 | H70: =(G70-E70)/E70 -> -0.55330889 | J70: ASAHIINDIA | K70: INE439A01020 | L70: 584 | M70: 850.6
A71: GRSE | B71: 322 | C71: 2440.3 | D71: =B71 -> 322 | E71: =B71*C71 -> 785776.6 | F71: =IFERROR(__xludf.DUMMYFUNCTION("GOOGLEFINANCE(CONCAT(""NSE:"",A71))"),2337.0) -> 2337 | G71: =D71*F71 -> 752514 | H71: =(G71-E71)/E71 -> -0.042330861 | J71: ASHOKLEY | K71: INE208A01029 | L71: 4011 | M71: 165.73
A72: GVT&D | B72: 253 | C72: 3521.2 | D72: =B72 -> 253 | E72: =B72*C72 -> 890863.6 | F72: =IFERROR(__xludf.DUMMYFUNCTION("GOOGLEFINANCE(CONCAT(""NSE:"",A72))"),4297.0) -> 4297 | G72: =D72*F72 -> 1087141 | H72: =(G72-E72)/E72 -> 0.22032262 | J72: AUBANK | K72: INE949L01017 | L72: 594 | M72: 1017.65
A73: LAURUSLABS | B73: 581 | C73: 961.95 | D73: =B73 -> 581 | E73: =B73*C73 -> 558892.95 | F73: =IFERROR(__xludf.DUMMYFUNCTION("GOOGLEFINANCE(CONCAT(""NSE:"",A73))"),1944.7) -> 1944.7 | G73: =D73*F73 -> 1129870.7 | H73: =(G73-E73)/E73 -> 1.0216227 | J73: BEL | K73: INE263A01024 | L73: 1228 | M73: 437.55
A74: LTF | B74: 2408 | C74: 279.4 | D74: =B74 -> 2408 | E74: =B74*C74 -> 672795.2 | F74: =IFERROR(__xludf.DUMMYFUNCTION("GOOGLEFINANCE(CONCAT(""NSE:"",A74))"),298.85) -> 298.85 | G74: =D74*F74 -> 719630.8 | H74: =(G74-E74)/E74 -> 0.069613457 | J74: BSE | K74: INE118H01025 | L74: 193 | M74: 3635.7
A75: MUTHOOTFIN | B75: 163 | C75: 3583.61 | D75: =B75 -> 163 | E75: =B75*C75 -> 584128.43 | F75: =IFERROR(__xludf.DUMMYFUNCTION("GOOGLEFINANCE(CONCAT(""NSE:"",A75))"),2752.2) -> 2752.2 | G75: =D75*F75 -> 448608.6 | H75: =(G75-E75)/E75 -> -0.23200348 | J75: CANBK | K75: INE476A01022 | L75: 3741 | M75: 137.06
A76: RBLBANK | B76: 2350 | C76: 304.05 | D76: =B76 -> 2350 | E76: =B76*C76 -> 714517.5 | F76: =IFERROR(__xludf.DUMMYFUNCTION("GOOGLEFINANCE(CONCAT(""NSE:"",A76))"),406.85) -> 406.85 | G76: =D76*F76 -> 956097.5 | H76: =(G76-E76)/E76 -> 0.33810229 | J76: CCL | K76: INE421D01022 | L76: 604 | M76: 1125.1
A77: FORCEMOT | B77: 77 | C77: 0 | D77: =B77 -> 77 | E77: =B77*C77 -> 0 | F77: =IFERROR(__xludf.DUMMYFUNCTION("GOOGLEFINANCE(CONCAT(""NSE:"",A77))"),17516.0) -> 17516 | G77: =D77*F77 -> 1348732 | H77: =(G77-E77)/E77 -> #DIV/0! | J77: CHENNPETRO | K77: INE178A01016 | L77: 863 | M77: 1139.5
A78: POWERINDIA | B78: 37 | C78: 0 | D78: =B78 -> 37 | E78: =B78*C78 -> 0 | F78: =IFERROR(__xludf.DUMMYFUNCTION("GOOGLEFINANCE(CONCAT(""NSE:"",A78))"),30810.0) -> 30810 | G78: =D78*F78 -> 1139970 | H78: =(G78-E78)/E78 -> #DIV/0! | J78: CRAFTSMAN | K78: INE00LO01017 | L78: 94 | M78: 7750.5
A79: ABCAPITAL | B79: 2115 | C79: 341.35 | D79: =B79 -> 2115 | E79: =B79*C79 -> 721955.25 | F79: =IFERROR(__xludf.DUMMYFUNCTION("GOOGLEFINANCE(CONCAT(""NSE:"",A79))"),386.35) -> 386.35 | G79: =D79*F79 -> 817130.25 | H79: =(G79-E79)/E79 -> 0.1318295 | J79: CUB | K79: INE491A01021 | L79: 2007 | M79: 277.37
A80: ASAHIINDIA | B80: 584 | C80: 948.19 | D80: =B80 -> 584 | E80: =B80*C80 -> 553742.96 | F80: =IFERROR(__xludf.DUMMYFUNCTION("GOOGLEFINANCE(CONCAT(""NSE:"",A80))"),951.65) -> 951.65 | G80: =D80*F80 -> 555763.6 | H80: =(G80-E80)/E80 -> 0.0036490577 | J80: ECLERX | K80: INE738I01010 | L80: 230 | M80: 1416.2
A81: ASHOKLEY | B81: 4011 | C81: 199.98 | D81: =B81 -> 4011 | E81: =B81*C81 -> 802119.78 | F81: =IFERROR(__xludf.DUMMYFUNCTION("GOOGLEFINANCE(CONCAT(""NSE:"",A81))"),157.53) -> 157.53 | G81: =D81*F81 -> 631852.83 | H81: =(G81-E81)/E81 -> -0.21227123 | J81: FORCEMOT | K81: INE451A01017 | L81: 77 | M81: 20985
A82: AUBANK | B82: 594 | C82: 981.73 | D82: =B82 -> 594 | E82: =B82*C82 -> 583147.62 | F82: =IFERROR(__xludf.DUMMYFUNCTION("GOOGLEFINANCE(CONCAT(""NSE:"",A82))"),1036.2) -> 1036.2 | G82: =D82*F82 -> 615502.8 | H82: =(G82-E82)/E82 -> 0.055483687 | J82: GMDCLTD | K82: INE131A01031 | L82: 1440 | M82: 740.05
A83: BEL | B83: 1228 | C83: 428.05 | D83: =B83 -> 1228 | E83: =B83*C83 -> 525645.4 | F83: =IFERROR(__xludf.DUMMYFUNCTION("GOOGLEFINANCE(CONCAT(""NSE:"",A83))"),392.8) -> 392.8 | G83: =D83*F83 -> 482358.4 | H83: =(G83-E83)/E83 -> -0.082350193 | J83: GRSE | K83: INE382Z01011 | L83: 322 | M83: 3072.7
A84: CANBK | B84: 3741 | C84: 147.23 | D84: =B84 -> 3741 | E84: =B84*C84 -> 550787.43 | F84: =IFERROR(__xludf.DUMMYFUNCTION("GOOGLEFINANCE(CONCAT(""NSE:"",A84))"),122.6) -> 122.6 | G84: =D84*F84 -> 458646.6 | H84: =(G84-E84)/E84 -> -0.16728928 | J84: GVT&D | K84: INE200A01026 | L84: 253 | M84: 4479.4
A85: CCL | B85: 604 | C85: 981.45 | D85: =B85 -> 604 | E85: =B85*C85 -> 592795.8 | F85: =IFERROR(__xludf.DUMMYFUNCTION("GOOGLEFINANCE(CONCAT(""NSE:"",A85))"),1065.3) -> 1065.3 | G85: =D85*F85 -> 643441.2 | H85: =(G85-E85)/E85 -> 0.085434816 | J85: HINDCOPPER | K85: INE531E01026 | L85: 1979 | M85: 555.25
A86: CHENNPETRO | B86: 863 | C86: 901.9 | D86: =B86 -> 863 | E86: =B86*C86 -> 778339.7 | F86: =IFERROR(__xludf.DUMMYFUNCTION("GOOGLEFINANCE(CONCAT(""NSE:"",A86))"),1417.5) -> 1417.5 | G86: =D86*F86 -> 1223302.5 | H86: =(G86-E86)/E86 -> 0.571682 | J86: INDIACEM | K86: INE383A01012 | L86: 1530 | M86: 401.85
A87: CRAFTSMAN | B87: 94 | C87: 7794.5 | D87: =B87 -> 94 | E87: =B87*C87 -> 732683 | F87: =IFERROR(__xludf.DUMMYFUNCTION("GOOGLEFINANCE(CONCAT(""NSE:"",A87))"),10943.0) -> 10943 | G87: =D87*F87 -> 1028642 | H87: =(G87-E87)/E87 -> 0.40393867 | J87: JKTYRE | K87: INE573A01042 | L87: 1210 | M87: 406.95
A88: CUB | B88: 2007 | C88: 293.46 | D88: =B88 -> 2007 | E88: =B88*C88 -> 588974.22 | F88: =IFERROR(__xludf.DUMMYFUNCTION("GOOGLEFINANCE(CONCAT(""NSE:"",A88))"),232.4) -> 232.4 | G88: =D88*F88 -> 466426.8 | H88: =(G88-E88)/E88 -> -0.20806924 | J88: LAURUSLABS | K88: INE947Q01028 | L88: 581 | M88: 1106.1
A89: GMDCLTD | B89: 1440 | C89: 608.74 | D89: =B89 -> 1440 | E89: =B89*C89 -> 876585.6 | F89: =IFERROR(__xludf.DUMMYFUNCTION("GOOGLEFINANCE(CONCAT(""NSE:"",A89))"),549.9) -> 549.9 | G89: =D89*F89 -> 791856 | H89: =(G89-E89)/E89 -> -0.096658672 | J89: LTF | K89: INE498L01015 | L89: 2408 | M89: 285.42
A90: HINDCOPPER | B90: 1979 | C90: 584.85 | D90: =B90 -> 1979 | E90: =B90*C90 -> 1157418.1 | F90: =IFERROR(__xludf.DUMMYFUNCTION("GOOGLEFINANCE(CONCAT(""NSE:"",A90))"),484.55) -> 484.55 | G90: =D90*F90 -> 958924.45 | H90: =(G90-E90)/E90 -> -0.17149697 | J90: MCX | K90: INE745G01043 | L90: 372 | M90: 2968.3
A91: INDIACEM | B91: 1530 | C91: 448.88 | D91: =B91 -> 1530 | E91: =B91*C91 -> 686786.4 | F91: =IFERROR(__xludf.DUMMYFUNCTION("GOOGLEFINANCE(CONCAT(""NSE:"",A91))"),349.75) -> 349.75 | G91: =D91*F91 -> 535117.5 | H91: =(G91-E91)/E91 -> -0.22083853 | J91: MUTHOOTFIN | K91: INE414G01012 | L91: 163 | M91: 3461.1
A92: JKTYRE | B92: 1210 | C92: 526.47 | D92: =B92 -> 1210 | E92: =B92*C92 -> 637028.7 | F92: =IFERROR(__xludf.DUMMYFUNCTION("GOOGLEFINANCE(CONCAT(""NSE:"",A92))"),346.1) -> 346.1 | G92: =D92*F92 -> 418781 | H92: =(G92-E92)/E92 -> -0.34260262 | J92: NATIONALUM | K92: INE139A01034 | L92: 2172 | M92: 433.3
A93: MCX | B93: 372 | C93: 2354 | D93: =B93 -> 372 | E93: =B93*C93 -> 875688 | F93: =IFERROR(__xludf.DUMMYFUNCTION("GOOGLEFINANCE(CONCAT(""NSE:"",A93))"),3290.8) -> 3290.8 | G93: =D93*F93 -> 1224177.6 | H93: =(G93-E93)/E93 -> 0.39796092 | J93: NETWEB | K93: INE0NT901020 | L93: 292 | M93: 4031
A94: NATIONALUM | B94: 2172 | C94: 353.6 | D94: =B94 -> 2172 | E94: =B94*C94 -> 768019.2 | F94: =IFERROR(__xludf.DUMMYFUNCTION("GOOGLEFINANCE(CONCAT(""NSE:"",A94))"),356.3) -> 356.3 | G94: =D94*F94 -> 773883.6 | H94: =(G94-E94)/E94 -> 0.0076357466 | J94: POWERINDIA | K94: INE07Y701011 | L94: 37 | M94: 32885
A95: NETWEB | B95: 292 | C95: 3057.7 | D95: =B95 -> 292 | E95: =B95*C95 -> 892848.4 | F95: =IFERROR(__xludf.DUMMYFUNCTION("GOOGLEFINANCE(CONCAT(""NSE:"",A95))"),4576.0) -> 4576 | G95: =D95*F95 -> 1336192 | H95: =(G95-E95)/E95 -> 0.49654969 | J95: RBLBANK | K95: INE976G01028 | L95: 2350 | M95: 341.2
A96: SHRIRAMFIN | B96: 660 | C96: 990.1 | D96: =B96 -> 660 | E96: =B96*C96 -> 653466 | F96: =IFERROR(__xludf.DUMMYFUNCTION("GOOGLEFINANCE(CONCAT(""NSE:"",A96))"),989.1) -> 989.1 | G96: =D96*F96 -> 652806 | H96: =(G96-E96)/E96 -> -0.001009999 | J96: SHRIRAMFIN | K96: INE721A01047 | L96: 660 | M96: 956.85
A97: UNIONBANK | B97: 3104 | C97: 177.14 | D97: =B97 -> 3104 | E97: =B97*C97 -> 549842.56 | F97: =IFERROR(__xludf.DUMMYFUNCTION("GOOGLEFINANCE(CONCAT(""NSE:"",A97))"),177.15) -> 177.15 | G97: =D97*F97 -> 549873.6 | H97: =(G97-E97)/E97 -> 5.6452523e-05 | J97: UNIONBANK | K97: INE692A01016 | L97: 3104 | M97: 167.31
A100: 45962 | B100: qty | C100: Buying Rate | D100: Changed Qty | E100: Amount at entry | F100: Actual Price | G100: Amount by M2M | H100: P&L
A101: ASTERDM | B101: 1041 | C101: 691.92 | D101: =B101 -> 1041 | E101: =B101*C101 -> 720288.72 | F101: =IFERROR(__xludf.DUMMYFUNCTION("GOOGLEFINANCE(CONCAT(""NSE:"",A101))"),758.0) -> 758 | G101: =F101*D101 -> 789078 | H101: =(G101-E101)/E101 -> 0.09550237
A102: BSE | B102: 325 | C102: 2508.3 | D102: =B102 -> 325 | E102: =B102*C102 -> 815197.5 | F102: =IFERROR(__xludf.DUMMYFUNCTION("GOOGLEFINANCE(CONCAT(""NSE:"",A102))"),3271.6) -> 3271.6 | G102: =F102*D102 -> 1063270 | H102: =(G102-E102)/E102 -> 0.30430969
A103: FORTIS | B103: 721 | C103: 1030.8 | D103: =B103 -> 721 | E103: =B103*C103 -> 743206.8 | F103: =IFERROR(__xludf.DUMMYFUNCTION("GOOGLEFINANCE(CONCAT(""NSE:"",A103))"),888.05) -> 888.05 | G103: =F103*D103 -> 640284.05 | H103: =(G103-E103)/E103 -> -0.13848467
A104: PAYTM | B104: 715 | C104: 1298.6 | D104: =B104 -> 715 | E104: =B104*C104 -> 928499 | F104: =IFERROR(__xludf.DUMMYFUNCTION("GOOGLEFINANCE(CONCAT(""NSE:"",A104))"),1761.4) -> 1761.4 | G104: =F104*D104 -> 1259401 | H104: =(G104-E104)/E104 -> 0.3563838
...

Sheet hpc39_10
A1: Total cash to be allocated | B1: 9907715 | C1: Rebalance Date | D1: 46268
A2: Target rebalance date | B2: 46296
A3: 46268 | B3: Qty | C3: Buying Rate | D3: Changed Qty | E3: Amount at entry | F3: Actual Price | G3: Amount by M2M | H3: P&L
A4: CYIENT | B4: 427 | C4: 1138 | D4: =B4 -> 427 | E4: =C4*D4 -> 485926 | F4: =IFERROR(__xludf.DUMMYFUNCTION("GOOGLEFINANCE(CONCAT(""NSE:"",A4))"),1080.2) -> 1080.2 | G4: =D4*F4 -> 461245.4 | H4: =(G4-E4)/E4 -> -0.050790861
A5: JINDALSAW | B5: 1577 | C5: 305.5 | D5: =B5 -> 1577 | E5: =C5*D5 -> 481773.5 | F5: =IFERROR(__xludf.DUMMYFUNCTION("GOOGLEFINANCE(CONCAT(""NSE:"",A5))"),289.4) -> 289.4 | G5: =D5*F5 -> 456383.8 | H5: =(G5-E5)/E5 -> -0.052700491
A6: JINDALSTEL | B6: 424 | C6: 1146 | D6: =B6 -> 424 | E6: =C6*D6 -> 485904 | F6: =IFERROR(__xludf.DUMMYFUNCTION("GOOGLEFINANCE(CONCAT(""NSE:"",A6))"),1124.4) -> 1124.4 | G6: =D6*F6 -> 476745.6 | H6: =(G6-E6)/E6 -> -0.018848168
A7: PVRINOX | B7: 403 | C7: 1220.7 | D7: =B7 -> 403 | E7: =C7*D7 -> 491942.1 | F7: =IFERROR(__xludf.DUMMYFUNCTION("GOOGLEFINANCE(CONCAT(""NSE:"",A7))"),1258.3) -> 1258.3 | G7: =D7*F7 -> 507094.9 | H7: =(G7-E7)/E7 -> 0.030801999
A8: IDFCFIRSTB | B8: 5828 | C8: 84.25 | D8: =B8 -> 5828 | E8: =C8*D8 -> 491009 | F8: =IFERROR(__xludf.DUMMYFUNCTION("GOOGLEFINANCE(CONCAT(""NSE:"",A8))"),85.19) -> 85.19 | G8: =D8*F8 -> 496487.32 | H8: =(G8-E8)/E8 -> 0.01115727
A9: BANDHANBNK | B9: 3021 | C9: 159.94 | D9: =B9 -> 3021 | E9: =C9*D9 -> 483178.74 | F9: =IFERROR(__xludf.DUMMYFUNCTION("GOOGLEFINANCE(CONCAT(""NSE:"",A9))"),172.69) -> 172.69 | G9: =D9*F9 -> 521696.49 | H9: =(G9-E9)/E9 -> 0.079717394
A10: CREDITACC | B10: 361 | C10: 1386.9 | D10: =B10 -> 361 | E10: =C10*D10 -> 500670.9 | F10: =IFERROR(__xludf.DUMMYFUNCTION("GOOGLEFINANCE(CONCAT(""NSE:"",A10))"),1386.6) -> 1386.6 | G10: =D10*F10 -> 500562.6 | H10: =(G10-E10)/E10 -> -0.00021630976
A11: DEEPAKFERT | B11: 346 | C11: 1423 | D11: =B11 -> 346 | E11: =C11*D11 -> 492358 | F11: =IFERROR(__xludf.DUMMYFUNCTION("GOOGLEFINANCE(CONCAT(""NSE:"",A11))"),1330.2) -> 1330.2 | G11: =D11*F11 -> 460249.2 | H11: =(G11-E11)/E11 -> -0.065214336
A12: ELECON | B12: 1188 | C12: 410.1 | D12: =B12 -> 1188 | E12: =C12*D12 -> 487198.8 | F12: =IFERROR(__xludf.DUMMYFUNCTION("GOOGLEFINANCE(CONCAT(""NSE:"",A12))"),410.15) -> 410.15 | G12: =D12*F12 -> 487258.2 | H12: =(G12-E12)/E12 -> 0.00012192148
A13: GODREJPROP | B13: 250 | C13: 1927.5 | D13: =B13 -> 250 | E13: =C13*D13 -> 481875 | F13: =IFERROR(__xludf.DUMMYFUNCTION("GOOGLEFINANCE(CONCAT(""NSE:"",A13))"),1673.8) -> 1673.8 | G13: =D13*F13 -> 418450 | H13: =(G13-E13)/E13 -> -0.13162127
A14: GPIL | B14: 2056 | C14: 241.65 | D14: =B14 -> 2056 | E14: =C14*D14 -> 496832.4 | F14: =IFERROR(__xludf.DUMMYFUNCTION("GOOGLEFINANCE(CONCAT(""NSE:"",A14))"),238.04) -> 238.04 | G14: =D14*F14 -> 489410.24 | H14: =(G14-E14)/E14 -> -0.014938961
A15: JMFINANCIL | B15: 3825 | C15: 127.08 | D15: =B15 -> 3825 | E15: =C15*D15 -> 486081 | F15: =IFERROR(__xludf.DUMMYFUNCTION("GOOGLEFINANCE(CONCAT(""NSE:"",A15))"),121.52) -> 121.52 | G15: =D15*F15 -> 464814 | H15: =(G15-E15)/E15 -> -0.043751967
A16: LLOYDSME | B16: 275 | C16: 1785.9 | D16: =B16 -> 275 | E16: =C16*D16 -> 491122.5 | F16: =IFERROR(__xludf.DUMMYFUNCTION("GOOGLEFINANCE(CONCAT(""NSE:"",A16))"),1824.9) -> 1824.9 | G16: =D16*F16 -> 501847.5 | H16: =(G16-E16)/E16 -> 0.021837729
A17: LTFOODS | B17: 1123 | C17: 435.6 | D17: =B17 -> 1123 | E17: =C17*D17 -> 489178.8 | F17: =IFERROR(__xludf.DUMMYFUNCTION("GOOGLEFINANCE(CONCAT(""NSE:"",A17))"),420.5) -> 420.5 | G17: =D17*F17 -> 472221.5 | H17: =(G17-E17)/E17 -> -0.03466483
A18: MANAPPURAM | B18: 1453 | C18: 334.05 | D18: =B18 -> 1453 | E18: =C18*D18 -> 485374.65 | F18: =IFERROR(__xludf.DUMMYFUNCTION("GOOGLEFINANCE(CONCAT(""NSE:"",A18))"),317.0) -> 317 | G18: =D18*F18 -> 460601 | H18: =(G18-E18)/E18 -> -0.051040263
A19: NIACL | B19: 2618 | C19: 186.95 | D19: =B19 -> 2618 | E19: =C19*D19 -> 489435.1 | F19: =IFERROR(__xludf.DUMMYFUNCTION("GOOGLEFINANCE(CONCAT(""NSE:"",A19))"),190.02) -> 190.02 | G19: =D19*F19 -> 497472.36 | H19: =(G19-E19)/E19 -> 0.016421503
A20: ONGC | B20: 2107 | C20: 238.29 | D20: =B20 -> 2107 | E20: =C20*D20 -> 502077.03 | F20: =IFERROR(__xludf.DUMMYFUNCTION("GOOGLEFINANCE(CONCAT(""NSE:"",A20))"),232.81) -> 232.81 | G20: =D20*F20 -> 490530.67 | H20: =(G20-E20)/E20 -> -0.022997188
A21: PCBL | B21: 1547 | C21: 314.1 | D21: =B21 -> 1547 | E21: =C21*D21 -> 485912.7 | F21: =IFERROR(__xludf.DUMMYFUNCTION("GOOGLEFINANCE(CONCAT(""NSE:"",A21))"),323.85) -> 323.85 | G21: =D21*F21 -> 500995.95 | H21: =(G21-E21)/E21 -> 0.03104107
A22: TATASTEEL | B22: 2661 | C22: 182.27 | D22: =B22 -> 2661 | E22: =C22*D22 -> 485020.47 | F22: =IFERROR(__xludf.DUMMYFUNCTION("GOOGLEFINANCE(CONCAT(""NSE:"",A22))"),184.29) -> 184.29 | G22: =D22*F22 -> 490395.69 | H22: =(G22-E22)/E22 -> 0.01108246
A23: YESBANK | B23: 22315 | C23: 21.9 | D23: =B23 -> 22315 | E23: =C23*D23 -> 488698.5 | F23: =IFERROR(__xludf.DUMMYFUNCTION("GOOGLEFINANCE(CONCAT(""NSE:"",A23))"),22.98) -> 22.98 | G23: =D23*F23 -> 512798.7 | H23: =(G23-E23)/E23 -> 0.049315068
A25: Total cash to be allocated | B25: 9770443 | C25: Rebalance Date | D25: 46237
A26: Target rebalance date | B26: 46266
A27: 46237 | B27: Qty | C27: Buying Rate | D27: Changed Qty | E27: Amount at entry | F27: Actual Price | G27: Amount by M2M | H27: P&L
A28: HINDALCO | B28: 493 | C28: 1001.3 | D28: =B28 -> 493 | E28: =B28*C28 -> 493640.9 | F28: =IFERROR(__xludf.DUMMYFUNCTION("GOOGLEFINANCE(CONCAT(""NSE:"",A28))"),983.7) -> 983.7 | G28: =D28*F28 -> 484964.1 | H28: =(G28-E28)/E28 -> -0.01757715
A29: IDFCFIRSTB | B29: 5766 | C29: 85.2 | D29: =B29 -> 5766 | E29: =B29*C29 -> 491263.2 | F29: =IFERROR(__xludf.DUMMYFUNCTION("GOOGLEFINANCE(CONCAT(""NSE:"",A29))"),85.19) -> 85.19 | G29: =D29*F29 -> 491205.54 | H29: =(G29-E29)/E29 -> -0.00011737089
A30: JINDALSTEL | B30: 439 | C30: 1113.8 | D30: =B30 -> 439 | E30: =B30*C30 -> 488958.2 | F30: =IFERROR(__xludf.DUMMYFUNCTION("GOOGLEFINANCE(CONCAT(""NSE:"",A30))"),1124.4) -> 1124.4 | G30: =D30*F30 -> 493611.6 | H30: =(G30-E30)/E30 -> 0.0095169689
A31: LLOYDSME | B31: 238 | C31: 2053.7 | D31: =B31 -> 238 | E31: =B31*C31 -> 488780.6 | F31: =IFERROR(__xludf.DUMMYFUNCTION("GOOGLEFINANCE(CONCAT(""NSE:"",A31))"),1824.9) -> 1824.9 | G31: =D31*F31 -> 434326.2 | H31: =(G31-E31)/E31 -> -0.11140868
A32: MANAPPURAM | B32: 1342 | C32: 362.8 | D32: =B32 -> 1342 | E32: =B32*C32 -> 486877.6 | F32: =IFERROR(__xludf.DUMMYFUNCTION("GOOGLEFINANCE(CONCAT(""NSE:"",A32))"),317.0) -> 317 | G32: =D32*F32 -> 425414 | H32: =(G32-E32)/E32 -> -0.12624035
A33: NATIONALUM | B33: 1338 | C33: 373.85 | D33: =B33 -> 1338 | E33: =B33*C33 -> 500211.3 | F33: =IFERROR(__xludf.DUMMYFUNCTION("GOOGLEFINANCE(CONCAT(""NSE:"",A33))"),356.3) -> 356.3 | G33: =D33*F33 -> 476729.4 | H33: =(G33-E33)/E33 -> -0.046943961
A34: OIL | B34: 1083 | C34: 450.15 | D34: =B34 -> 1083 | E34: =B34*C34 -> 487512.45 | F34: =IFERROR(__xludf.DUMMYFUNCTION("GOOGLEFINANCE(CONCAT(""NSE:"",A34))"),478.75) -> 478.75 | G34: =D34*F34 -> 518486.25 | H34: =(G34-E34)/E34 -> 0.063534377
A35: TATASTEEL | B35: 2585 | C35: 190.72 | D35: =B35 -> 2585 | E35: =B35*C35 -> 493011.2 | F35: =IFERROR(__xludf.DUMMYFUNCTION("GOOGLEFINANCE(CONCAT(""NSE:"",A35))"),184.29) -> 184.29 | G35: =D35*F35 -> 476389.65 | H35: =(G35-E35)/E35 -> -0.033714346
A36: UPL | B36: 786 | C36: 600.75 | D36: =B36 -> 786 | E36: =B36*C36 -> 472189.5 | F36: =IFERROR(__xludf.DUMMYFUNCTION("GOOGLEFINANCE(CONCAT(""NSE:"",A36))"),550.2) -> 550.2 | G36: =D36*F36 -> 432457.2 | H36: =(G36-E36)/E36 -> -0.084144819
A37: CREDITACC | B37: 313 | C37: 1564.2 | D37: =B37 -> 313 | E37: =B37*C37 -> 489594.6 | F37: =IFERROR(__xludf.DUMMYFUNCTION("GOOGLEFINANCE(CONCAT(""NSE:"",A37))"),1386.6) -> 1386.6 | G37: =D37*F37 -> 434005.8 | H37: =(G37-E37)/E37 -> -0.11354047
A38: CYIENT | B38: 569 | C38: 868 | D38: =B38 -> 569 | E38: =B38*C38 -> 493892 | F38: =IFERROR(__xludf.DUMMYFUNCTION("GOOGLEFINANCE(CONCAT(""NSE:"",A38))"),1080.2) -> 1080.2 | G38: =D38*F38 -> 614633.8 | H38: =(G38-E38)/E38 -> 0.24447005
A39: DEEPAKFERT | B39: 309 | C39: 1667.1 | D39: =B39 -> 309 | E39: =B39*C39 -> 515133.9 | F39: =IFERROR(__xludf.DUMMYFUNCTION("GOOGLEFINANCE(CONCAT(""NSE:"",A39))"),1330.2) -> 1330.2 | G39: =D39*F39 -> 411031.8 | H39: =(G39-E39)/E39 -> -0.20208746
A40: GESHIP | B40: 348 | C40: 1472.4 | D40: =B40 -> 348 | E40: =B40*C40 -> 512395.2 | F40: =IFERROR(__xludf.DUMMYFUNCTION("GOOGLEFINANCE(CONCAT(""NSE:"",A40))"),1405.4) -> 1405.4 | G40: =D40*F40 -> 489079.2 | H40: =(G40-E40)/E40 -> -0.045503939
A41: GPIL | B41: 2018 | C41: 246.74 | D41: =B41 -> 2018 | E41: =B41*C41 -> 497921.32 | F41: =IFERROR(__xludf.DUMMYFUNCTION("GOOGLEFINANCE(CONCAT(""NSE:"",A41))"),238.04) -> 238.04 | G41: =D41*F41 -> 480364.72 | H41: =(G41-E41)/E41 -> -0.035259788
A42: JINDALSAW | B42: 1886 | C42: 262.85 | D42: =B42 -> 1886 | E42: =B42*C42 -> 495735.1 | F42: =IFERROR(__xludf.DUMMYFUNCTION("GOOGLEFINANCE(CONCAT(""NSE:"",A42))"),289.4) -> 289.4 | G42: =D42*F42 -> 545808.4 | H42: =(G42-E42)/E42 -> 0.10100818
A43: KEC | B43: 1020 | C43: 480.6 | D43: =B43 -> 1020 | E43: =B43*C43 -> 490212 | F43: =IFERROR(__xludf.DUMMYFUNCTION("GOOGLEFINANCE(CONCAT(""NSE:"",A43))"),401.6) -> 401.6 | G43: =D43*F43 -> 409632 | H43: =(G43-E43)/E43 -> -0.16437786
A44: ONGC | B44: 2029 | C44: 242.43 | D44: =B44 -> 2029 | E44: =B44*C44 -> 491890.47 | F44: =IFERROR(__xludf.DUMMYFUNCTION("GOOGLEFINANCE(CONCAT(""NSE:"",A44))"),232.81) -> 232.81 | G44: =D44*F44 -> 472371.49 | H44: =(G44-E44)/E44 -> -0.039681558
A45: PCBL | B45: 1499 | C45: 325.8 | D45: =B45 -> 1499 | E45: =B45*C45 -> 488374.2 | F45: =IFERROR(__xludf.DUMMYFUNCTION("GOOGLEFINANCE(CONCAT(""NSE:"",A45))"),323.85) -> 323.85 | G45: =D45*F45 -> 485451.15 | H45: =(G45-E45)/E45 -> -0.005985267
A46: PVRINOX | B46: 432 | C46: 1135.97 | D46: =B46 -> 432 | E46: =B46*C46 -> 490739.04 | F46: =IFERROR(__xludf.DUMMYFUNCTION("GOOGLEFINANCE(CONCAT(""NSE:"",A46))"),1258.3) -> 1258.3 | G46: =D46*F46 -> 543585.6 | H46: =(G46-E46)/E46 -> 0.1076877
A47: ZEEL | B47: 4990 | C47: 100.15 | D47: =B47 -> 4990 | E47: =B47*C47 -> 499748.5 | F47: =IFERROR(__xludf.DUMMYFUNCTION("GOOGLEFINANCE(CONCAT(""NSE:"",A47))"),78.3) -> 78.3 | G47: =D47*F47 -> 390717 | H47: =(G47-E47)/E47 -> -0.21817274
A49: Total cash to be allocated | B49: 9632892 | C49: Rebalance Date | D49: 46204
A50: Target rebalance date | B50: 46237
A51: 46204 | B51: Qty | C51: Buying Rate | D51: Changed Qty | E51: Amount at entry | F51: Actual Price | G51: Amount by M2M | H51: P&L
A52: BANDHANBNK | B52: 2347 | C52: 201.12 | D52: =B52 -> 2347 | E52: =B52*C52 -> 472028.64 | F52: =IFERROR(__xludf.DUMMYFUNCTION("GOOGLEFINANCE(CONCAT(""NSE:"",A52))"),172.69) -> 172.69 | G52: =D52*F52 -> 405303.43 | H52: =(G52-E52)/E52 -> -0.14135839 | J52: HPC39_10 | K52: KAPIL SIR | L52: BHAN01 | M52: BANDHANBNK | N52: INE545U01014 | O52: 2347 | P52: 174.13 | Q52: 408683.1
A53: CREDITACC | B53: 311 | C53: 1558.9 | D53: =B53 -> 311 | E53: =B53*C53 -> 484817.9 | F53: =IFERROR(__xludf.DUMMYFUNCTION("GOOGLEFINANCE(CONCAT(""NSE:"",A53))"),1386.6) -> 1386.6 | G53: =D53*F53 -> 431232.6 | H53: =(G53-E53)/E53 -> -0.11052665 | J53: HPC39_10 | K53: KAPIL SIR | L53: CRED01 | M53: CREDITACC | N53: INE741K01010 | O53: 311 | P53: 1592.8 | Q53: 495360.8
A54: DEEPAKFERT | B54: 298 | C54: 1639.2 | D54: =B54 -> 298 | E54: =B54*C54 -> 488481.6 | F54: =IFERROR(__xludf.DUMMYFUNCTION("GOOGLEFINANCE(CONCAT(""NSE:"",A54))"),1330.2) -> 1330.2 | G54: =D54*F54 -> 396399.6 | H54: =(G54-E54)/E54 -> -0.18850659 | J54: HPC39_10 | K54: KAPIL SIR | L54: DEEP02 | M54: DEEPAKFERT | N54: INE501A01019 | O54: 298 | P54: 1552.8 | Q54: 462734.4
A55: GESHIP | B55: 336 | C55: 1431.7 | D55: =B55 -> 336 | E55: =B55*C55 -> 481051.2 | F55: =IFERROR(__xludf.DUMMYFUNCTION("GOOGLEFINANCE(CONCAT(""NSE:"",A55))"),1405.4) -> 1405.4 | G55: =D55*F55 -> 472214.4 | H55: =(G55-E55)/E55 -> -0.01836977 | J55: HPC39_10 | K55: KAPIL SIR | L55: GESH01 | M55: GESHIP | N55: INE017A01032 | O55: 336 | P55: 1350.4 | Q55: 453734.4
A56: IDFCFIRSTB | B56: 6116 | C56: 79.52 | D56: =B56 -> 6116 | E56: =B56*C56 -> 486344.32 | F56: =IFERROR(__xludf.DUMMYFUNCTION("GOOGLEFINANCE(CONCAT(""NSE:"",A56))"),85.19) -> 85.19 | G56: =D56*F56 -> 521022.04 | H56: =(G56-E56)/E56 -> 0.071302817 | J56: HPC39_10 | K56: KAPIL SIR | L56: GPIL01 | M56: GPIL | N56: INE177H01039 | O56: 1880 | P56: 242.4 | Q56: 455712
A57: IRB | B57: 22412 | C57: 21.36 | D57: =B57 -> 22412 | E57: =B57*C57 -> 478720.32 | F57: =IFERROR(__xludf.DUMMYFUNCTION("GOOGLEFINANCE(CONCAT(""NSE:"",A57))"),18.96) -> 18.96 | G57: =D57*F57 -> 424931.52 | H57: =(G57-E57)/E57 -> -0.11235955 | J57: HPC39_10 | K57: KAPIL SIR | L57: HIND01 | M57: HINDALCO | N57: INE038A01020 | O57: 507 | P57: 974.45 | Q57: 494046.2
A58: LLOYDSME | B58: 265 | C58: 1787.1 | D58: =B58 -> 265 | E58: =B58*C58 -> 473581.5 | F58: =IFERROR(__xludf.DUMMYFUNCTION("GOOGLEFINANCE(CONCAT(""NSE:"",A58))"),1824.9) -> 1824.9 | G58: =D58*F58 -> 483598.5 | H58: =(G58-E58)/E58 -> 0.021151586 | J58: HPC39_10 | K58: KAPIL SIR | L58: IDFC05 | M58: IDFCFIRSTB | N58: INE092T01019 | O58: 6116 | P58: 84.68 | Q58: 517902.9
A59: MANAPPURAM | B59: 1500 | C59: 329.85 | D59: =B59 -> 1500 | E59: =B59*C59 -> 494775 | F59: =IFERROR(__xludf.DUMMYFUNCTION("GOOGLEFINANCE(CONCAT(""NSE:"",A59))"),317.0) -> 317 | G59: =D59*F59 -> 475500 | H59: =(G59-E59)/E59 -> -0.038957102 | J59: HPC39_10 | K59: KAPIL SIR | L59: IRB001 | M59: IRB | N59: INE821I01022 | O59: 22412 | P59: 20 | Q59: 448240
A60: MOTILALOFS | B60: 498 | C60: 959.85 | D60: =B60 -> 498 | E60: =B60*C60 -> 478005.3 | F60: =IFERROR(__xludf.DUMMYFUNCTION("GOOGLEFINANCE(CONCAT(""NSE:"",A60))"),993.4) -> 993.4 | G60: =D60*F60 -> 494713.2 | H60: =(G60-E60)/E60 -> 0.034953378 | J60: HPC39_10 | K60: KAPIL SIR | L60: JIND01 | M60: JINDALSTEL | N60: INE749A01030 | O60: 465 | P60: 1102.4 | Q60: 512616
A61: OIL | B61: 1148 | C61: 420.95 | D61: =B61 -> 1148 | E61: =B61*C61 -> 483250.6 | F61: =IFERROR(__xludf.DUMMYFUNCTION("GOOGLEFINANCE(CONCAT(""NSE:"",A61))"),478.75) -> 478.75 | G61: =D61*F61 -> 549605 | H61: =(G61-E61)/E61 -> 0.13730847 | J61: HPC39_10 | K61: KAPIL SIR | L61: LLOY02 | M61: LLOYDSME | N61: INE281B01032 | O61: 265 | P61: 2047 | Q61: 542455
A62: PNB | B62: 4500 | C62: 105.66 | D62: =B62 -> 4500 | E62: =B62*C62 -> 475470 | F62: =IFERROR(__xludf.DUMMYFUNCTION("GOOGLEFINANCE(CONCAT(""NSE:"",A62))"),117.38) -> 117.38 | G62: =D62*F62 -> 528210 | H62: =(G62-E62)/E62 -> 0.11092182 | J62: HPC39_10 | K62: KAPIL SIR | L62: MANA02 | M62: MANAPPURAM | N62: INE522D01027 | O62: 1500 | P62: 371.85 | Q62: 557775
A63: REDINGTON | B63: 1738 | C63: 275.95 | D63: =B63 -> 1738 | E63: =B63*C63 -> 479601.1 | F63: =IFERROR(__xludf.DUMMYFUNCTION("GOOGLEFINANCE(CONCAT(""NSE:"",A63))"),397.05) -> 397.05 | G63: =D63*F63 -> 690072.9 | H63: =(G63-E63)/E63 -> 0.43884762 | J63: HPC39_10 | K63: KAPIL SIR | L63: MOTI01 | M63: MOTILALOFS | N63: INE338I01027 | O63: 498 | P63: 851.95 | Q63: 424271.1
A64: UPL | B64: 828 | C64: 611.4 | D64: =B64 -> 828 | E64: =B64*C64 -> 506239.2 | F64: =IFERROR(__xludf.DUMMYFUNCTION("GOOGLEFINANCE(CONCAT(""NSE:"",A64))"),550.2) -> 550.2 | G64: =D64*F64 -> 455565.6 | H64: =(G64-E64)/E64 -> -0.10009814 | J64: HPC39_10 | K64: KAPIL SIR | L64: NATI01 | M64: NATIONALUM | N64: INE139A01034 | O64: 1436 | P64: 350.05 | Q64: 502671.8
A65: GPIL | B65: 1880 | C65: 254.95 | D65: =B65 -> 1880 | E65: =B65*C65 -> 479306 | F65: =IFERROR(__xludf.DUMMYFUNCTION("GOOGLEFINANCE(CONCAT(""NSE:"",A65))"),238.04) -> 238.04 | G65: =D65*F65 -> 447515.2 | H65: =(G65-E65)/E65 -> -0.066326731 | J65: HPC39_10 | K65: KAPIL SIR | L65: NIAC01 | M65: NIACL | N65: INE470Y01017 | O65: 2583 | P65: 173.62 | Q65: 448460.5
A66: HINDALCO | B66: 507 | C66: 961 | D66: =B66 -> 507 | E66: =B66*C66 -> 487227 | F66: =IFERROR(__xludf.DUMMYFUNCTION("GOOGLEFINANCE(CONCAT(""NSE:"",A66))"),983.7) -> 983.7 | G66: =D66*F66 -> 498735.9 | H66: =(G66-E66)/E66 -> 0.023621228 | J66: HPC39_10 | K66: KAPIL SIR | L66: OIL001 | M66: OIL | N66: INE274J01014 | O66: 1148 | P66: 458.6 | Q66: 526472.8
A67: JINDALSTEL | B67: 465 | C67: 1056.2 | D67: =B67 -> 465 | E67: =B67*C67 -> 491133 | F67: =IFERROR(__xludf.DUMMYFUNCTION("GOOGLEFINANCE(CONCAT(""NSE:"",A67))"),1124.4) -> 1124.4 | G67: =D67*F67 -> 522846 | H67: =(G67-E67)/E67 -> 0.064571104 | J67: HPC39_10 | K67: KAPIL SIR | L67: PNB001 | M67: PNB | N67: INE160A01022 | O67: 4500 | P67: 112.71 | Q67: 507195
A68: NATIONALUM | B68: 1436 | C68: 345.75 | D68: =B68 -> 1436 | E68: =B68*C68 -> 496497 | F68: =IFERROR(__xludf.DUMMYFUNCTION("GOOGLEFINANCE(CONCAT(""NSE:"",A68))"),356.3) -> 356.3 | G68: =D68*F68 -> 511646.8 | H68: =(G68-E68)/E68 -> 0.030513377 | J68: HPC39_10 | K68: KAPIL SIR | L68: REDI01 | M68: REDINGTON | N68: INE891D01026 | O68: 1738 | P68: 321.65 | Q68: 559027.7
A69: NIACL | B69: 2583 | C69: 184.75 | D69: =B69 -> 2583 | E69: =B69*C69 -> 477209.25 | F69: =IFERROR(__xludf.DUMMYFUNCTION("GOOGLEFINANCE(CONCAT(""NSE:"",A69))"),190.02) -> 190.02 | G69: =D69*F69 -> 490821.66 | H69: =(G69-E69)/E69 -> 0.028525034 | J69: HPC39_10 | K69: KAPIL SIR | L69: TATA01 | M69: TATASTEEL | N69: INE081A01020 | O69: 2600 | P69: 189.69 | Q69: 493194
A70: TATASTEEL | B70: 2600 | C70: 190.82 | D70: =B70 -> 2600 | E70: =B70*C70 -> 496132 | F70: =IFERROR(__xludf.DUMMYFUNCTION("GOOGLEFINANCE(CONCAT(""NSE:"",A70))"),184.29) -> 184.29 | G70: =D70*F70 -> 479154 | H70: =(G70-E70)/E70 -> -0.034220732 | J70: HPC39_10 | K70: KAPIL SIR | L70: UPL001 | M70: UPL | N70: INE628A01036 | O70: 828 | P70: 604.3 | Q70: 500360.4
A71: VEDL | B71: 1739 | C71: 279.8 | D71: =B71 -> 1739 | E71: =B71*C71 -> 486572.2 | F71: =IFERROR(__xludf.DUMMYFUNCTION("GOOGLEFINANCE(CONCAT(""NSE:"",A71))"),256.3) -> 256.3 | G71: =D71*F71 -> 445705.7 | H71: =(G71-E71)/E71 -> -0.083988563 | J71: HPC39_10 | K71: KAPIL SIR | L71: VEDL01 | M71: VEDL | N71: INE205A01025 | O71: 1739 | P71: 264.25 | Q71: 459530.8
A73: Total cash to be allocated | B73: 10000000 | C73: Rebalance Date | D73: 46197
A74: Target rebalance date | B74: 46204
A75: 46197 | B75: Qty | C75: Buying Rate | D75: Changed Qty | E75: Amount at entry | F75: Actual Price | G75: Amount by M2M | H75: P&L | J75: Client Code | K75: Name | L75: Scrip Code | M75: Scrip Name | N75: ISIN Code | O75: Stock | P75: Close Rate | Q75: Stk.Value Credit
A76: BANDHANBNK | B76: 2416 | C76: 207.98 | D76: =B76 -> 2416 | E76: =B76*C76 -> 502479.68 | F76: =IFERROR(__xludf.DUMMYFUNCTION("GOOGLEFINANCE(CONCAT(""NSE:"",A76))"),172.69) -> 172.69 | G76: =D76*F76 -> 417219.04 | H76: =(G76-E76)/E76 -> -0.16967978 | J76: HPC39_10 | K76: KAPIL SIR | L76: BHAN01 | M76: BANDHANBNK | N76: INE545U01014 | O76: 2416 | P76: 205.04 | Q76: 495376.6
A77: CREDITACC | B77: 355 | C77: 1394.8 | D77: =B77 -> 355 | E77: =B77*C77 -> 495154 | F77: =IFERROR(__xludf.DUMMYFUNCTION("GOOGLEFINANCE(CONCAT(""NSE:"",A77))"),1386.6) -> 1386.6 | G77: =D77*F77 -> 492243 | H77: =(G77-E77)/E77 -> -0.0058789791 | J77: HPC39_10 | K77: KAPIL SIR | L77: CRED01 | M77: CREDITACC | N77: INE741K01010 | O77: 355 | P77: 1502.3 | Q77: 533316.5
A78: DEEPAKFERT | B78: 314 | C78: 1600 | D78: =B78 -> 314 | E78: =B78*C78 -> 502400 | F78: =IFERROR(__xludf.DUMMYFUNCTION("GOOGLEFINANCE(CONCAT(""NSE:"",A78))"),1330.2) -> 1330.2 | G78: =D78*F78 -> 417682.8 | H78: =(G78-E78)/E78 -> -0.168625 | J78: HPC39_10 | K78: KAPIL SIR | L78: DEEP02 | M78: DEEPAKFERT | N78: INE501A01019 | O78: 314 | P78: 1604.6 | Q78: 503844.4
A79: GESHIP | B79: 339 | C79: 1500 | D79: =B79 -> 339 | E79: =B79*C79 -> 508500 | F79: =IFERROR(__xludf.DUMMYFUNCTION("GOOGLEFINANCE(CONCAT(""NSE:"",A79))"),1405.4) -> 1405.4 | G79: =D79*F79 -> 476430.6 | H79: =(G79-E79)/E79 -> -0.063066667 | J79: HPC39_10 | K79: KAPIL SIR | L79: GESH01 | M79: GESHIP | N79: INE017A01032 | O79: 339 | P79: 1421 | Q79: 481719
A80: GPIL | B80: 1813 | C80: 274.85 | D80: =B80 -> 1813 | E80: =B80*C80 -> 498303.05 | F80: =IFERROR(__xludf.DUMMYFUNCTION("GOOGLEFINANCE(CONCAT(""NSE:"",A80))"),238.04) -> 238.04 | G80: =D80*F80 -> 431566.52 | H80: =(G80-E80)/E80 -> -0.1339276 | J80: HPC39_10 | K80: KAPIL SIR | L80: GPIL01 | M80: GPIL | N80: INE177H01039 | O80: 1813 | P80: 254.6 | Q80: 461589.8
A81: HINDALCO | B81: 492 | C81: 991.75 | D81: =B81 -> 492 | E81: =B81*C81 -> 487941 | F81: =IFERROR(__xludf.DUMMYFUNCTION("GOOGLEFINANCE(CONCAT(""NSE:"",A81))"),983.7) -> 983.7 | G81: =D81*F81 -> 483980.4 | H81: =(G81-E81)/E81 -> -0.008116965 | J81: HPC39_10 | K81: KAPIL SIR | L81: HIND01 | M81: HINDALCO | N81: INE038A01020 | O81: 492 | P81: 939.7 | Q81: 462332.4
A82: IDFCFIRSTB | B82: 6207 | C82: 79.41 | D82: =B82 -> 6207 | E82: =B82*C82 -> 492897.87 | F82: =IFERROR(__xludf.DUMMYFUNCTION("GOOGLEFINANCE(CONCAT(""NSE:"",A82))"),85.19) -> 85.19 | G82: =D82*F82 -> 528774.33 | H82: =(G82-E82)/E82 -> 0.072786803 | J82: HPC39_10 | K82: KAPIL SIR | L82: IDFC05 | M82: IDFCFIRSTB | N82: INE092T01019 | O82: 6207 | P82: 78.93 | Q82: 489918.5
A83: IRB | B83: 23041 | C83: 21.55 | D83: =B83 -> 23041 | E83: =B83*C83 -> 496533.55 | F83: =IFERROR(__xludf.DUMMYFUNCTION("GOOGLEFINANCE(CONCAT(""NSE:"",A83))"),18.96) -> 18.96 | G83: =D83*F83 -> 436857.36 | H83: =(G83-E83)/E83 -> -0.12018561 | J83: HPC39_10 | K83: KAPIL SIR | L83: IRB001 | M83: IRB | N83: INE821I01022 | O83: 23041 | P83: 21.3 | Q83: 490773.3
A84: JINDALSTEL | B84: 441 | C84: 1106.9 | D84: =B84 -> 441 | E84: =B84*C84 -> 488142.9 | F84: =IFERROR(__xludf.DUMMYFUNCTION("GOOGLEFINANCE(CONCAT(""NSE:"",A84))"),1124.4) -> 1124.4 | G84: =D84*F84 -> 495860.4 | H84: =(G84-E84)/E84 -> 0.01580992 | J84: HPC39_10 | K84: KAPIL SIR | L84: JIND01 | M84: JINDALSTEL | N84: INE749A01030 | O84: 441 | P84: 1028.8 | Q84: 453700.8
A85: LLOYDSME | B85: 280 | C85: 1783.6 | D85: =B85 -> 280 | E85: =B85*C85 -> 499408 | F85: =IFERROR(__xludf.DUMMYFUNCTION("GOOGLEFINANCE(CONCAT(""NSE:"",A85))"),1824.9) -> 1824.9 | G85: =D85*F85 -> 510972 | H85: =(G85-E85)/E85 -> 0.023155416 | J85: HPC39_10 | K85: KAPIL SIR | L85: LLOY02 | M85: LLOYDSME | N85: INE281B01032 | O85: 280 | P85: 1805.9 | Q85: 505652
A86: MANAPPURAM | B86: 1523 | C86: 323 | D86: =B86 -> 1523 | E86: =B86*C86 -> 491929 | F86: =IFERROR(__xludf.DUMMYFUNCTION("GOOGLEFINANCE(CONCAT(""NSE:"",A86))"),317.0) -> 317 | G86: =D86*F86 -> 482791 | H86: =(G86-E86)/E86 -> -0.018575851 | J86: HPC39_10 | K86: KAPIL SIR | L86: MANA02 | M86: MANAPPURAM | N86: INE522D01027 | O86: 1523 | P86: 316.65 | Q86: 482258
A87: MOTILALOFS | B87: 527 | C87: 945.92 | D87: =B87 -> 527 | E87: =B87*C87 -> 498499.84 | F87: =IFERROR(__xludf.DUMMYFUNCTION("GOOGLEFINANCE(CONCAT(""NSE:"",A87))"),993.4) -> 993.4 | G87: =D87*F87 -> 523521.8 | H87: =(G87-E87)/E87 -> 0.05019452 | J87: HPC39_10 | K87: KAPIL SIR | L87: MOTI01 | M87: MOTILALOFS | N87: INE338I01027 | O87: 527 | P87: 955.95 | Q87: 503785.7
A88: NIACL | B88: 2353 | C88: 200.96 | D88: =B88 -> 2353 | E88: =B88*C88 -> 472858.88 | F88: =IFERROR(__xludf.DUMMYFUNCTION("GOOGLEFINANCE(CONCAT(""NSE:"",A88))"),190.02) -> 190.02 | G88: =D88*F88 -> 447117.06 | H88: =(G88-E88)/E88 -> -0.054438694 | J88: HPC39_10 | K88: KAPIL SIR | L88: NIAC01 | M88: NIACL | N88: INE470Y01017 | O88: 2353 | P88: 183.11 | Q88: 430857.8
A89: OIL | B89: 1183 | C89: 418.15 | D89: =B89 -> 1183 | E89: =B89*C89 -> 494671.45 | F89: =IFERROR(__xludf.DUMMYFUNCTION("GOOGLEFINANCE(CONCAT(""NSE:"",A89))"),478.75) -> 478.75 | G89: =D89*F89 -> 566361.25 | H89: =(G89-E89)/E89 -> 0.14492407 | J89: HPC39_10 | K89: KAPIL SIR | L89: OIL001 | M89: OIL | N89: INE274J01014 | O89: 1183 | P89: 419.8 | Q89: 496623.4
A90: ONGC | B90: 2036 | C90: 245.25 | D90: =B90 -> 2036 | E90: =B90*C90 -> 499329 | F90: =IFERROR(__xludf.DUMMYFUNCTION("GOOGLEFINANCE(CONCAT(""NSE:"",A90))"),232.81) -> 232.81 | G90: =D90*F90 -> 474001.16 | H90: =(G90-E90)/E90 -> -0.050723751 | J90: HPC39_10 | K90: KAPIL SIR | L90: ONGC01 | M90: ONGC | N90: INE213A01029 | O90: 2036 | P90: 234.99 | Q90: 478439.6
A91: PNB | B91: 4558 | C91: 108.04 | D91: =B91 -> 4558 | E91: =B91*C91 -> 492446.32 | F91: =IFERROR(__xludf.DUMMYFUNCTION("GOOGLEFINANCE(CONCAT(""NSE:"",A91))"),117.38) -> 117.38 | G91: =D91*F91 -> 535018.04 | H91: =(G91-E91)/E91 -> 0.086449463 | J91: HPC39_10 | K91: KAPIL SIR | L91: PNB001 | M91: PNB | N91: INE160A01022 | O91: 4558 | P91: 107.54 | Q91: 490167.3
A92: REDINGTON | B92: 1786 | C92: 279.9 | D92: =B92 -> 1786 | E92: =B92*C92 -> 499901.4 | F92: =IFERROR(__xludf.DUMMYFUNCTION("GOOGLEFINANCE(CONCAT(""NSE:"",A92))"),397.05) -> 397.05 | G92: =D92*F92 -> 709131.3 | H92: =(G92-E92)/E92 -> 0.41854234 | J92: HPC39_10 | K92: KAPIL SIR | L92: REDI01 | M92: REDINGTON | N92: INE891D01026 | O92: 1786 | P92: 273.65 | Q92: 488738.9
A93: TATASTEEL | B93: 2515 | C93: 196.46 | D93: =B93 -> 2515 | E93: =B93*C93 -> 494096.9 | F93: =IFERROR(__xludf.DUMMYFUNCTION("GOOGLEFINANCE(CONCAT(""NSE:"",A93))"),184.29) -> 184.29 | G93: =D93*F93 -> 463489.35 | H93: =(G93-E93)/E93 -> -0.061946452 | J93: HPC39_10 | K93: KAPIL SIR | L93: TATA01 | M93: TATASTEEL | N93: INE081A01020 | O93: 2515 | P93: 185.17 | Q93: 465702.6
A94: UPL | B94: 827 | C94: 604.38 | D94: =B94 -> 827 | E94: =B94*C94 -> 499822.26 | F94: =IFERROR(__xludf.DUMMYFUNCTION("GOOGLEFINANCE(CONCAT(""NSE:"",A94))"),550.2) -> 550.2 | G94: =D94*F94 -> 455015.4 | H94: =(G94-E94)/E94 -> -0.089645587 | J94: HPC39_10 | K94: KAPIL SIR | L94: UPL001 | M94: UPL | N94: INE628A01036 | O94: 827 | P94: 565.05 | Q94: 467296.4
A95: VEDL | B95: 1636 | C95: 282.9 | D95: =B95 -> 1636 | E95: =B95*C95 -> 462824.4 | F95: =IFERROR(__xludf.DUMMYFUNCTION("GOOGLEFINANCE(CONCAT(""NSE:"",A95))"),256.3) -> 256.3 | G95: =D95*F95 -> 419306.8 | H95: =(G95-E95)/E95 -> -0.094026158 | J95: HPC39_10 | K95: KAPIL SIR | L95: VEDL01 | M95: VEDL | N95: INE205A01025 | O95: 1636 | P95: 275.55 | Q95: 450799.8

Sheet hpc39_8
A1: Total cash to be allocated | B1: 20000000 | C1: Rebalance Date | D1: 46205
A2: Target rebalance date | B2: 46296
A3: 46204 | B3: Qty | C3: Buying Rate | D3: Changed Qty | E3: Amount at entry | F3: Actual Price | G3: Amount by M2M | H3: P&L
A4: ABCAPITAL | B4: 1507 | C4: 390.45 | D4: =B4 -> 1507 | E4: =B4*C4 -> 588408.15 | F4: =IFERROR(__xludf.DUMMYFUNCTION("GOOGLEFINANCE(CONCAT(""NSE:"",A4))"),386.35) -> 386.35 | G4: =D4*F4 -> 582229.45 | H4: =(G4-E4)/E4 -> -0.010500704
A5: ASHOKLEY | B5: 3721 | C5: 165.2 | D5: =B5 -> 3721 | E5: =B5*C5 -> 614709.2 | F5: =IFERROR(__xludf.DUMMYFUNCTION("GOOGLEFINANCE(CONCAT(""NSE:"",A5))"),157.53) -> 157.53 | G5: =D5*F5 -> 586169.13 | H5: =(G5-E5)/E5 -> -0.046428571
A6: BSE | B6: 177 | C6: 3938.7 | D6: =B6 -> 177 | E6: =B6*C6 -> 697149.9 | F6: =IFERROR(__xludf.DUMMYFUNCTION("GOOGLEFINANCE(CONCAT(""NSE:"",A6))"),3271.6) -> 3271.6 | G6: =D6*F6 -> 579073.2 | H6: =(G6-E6)/E6 -> -0.1693706
A7: FORCEMOT | B7: 36 | C7: 18841 | D7: =B7 -> 36 | E7: =B7*C7 -> 678276 | F7: =IFERROR(__xludf.DUMMYFUNCTION("GOOGLEFINANCE(CONCAT(""NSE:"",A7))"),17516.0) -> 17516 | G7: =D7*F7 -> 630576 | H7: =(G7-E7)/E7 -> -0.070325354
A8: KEI | B8: 109 | C8: 5273 | D8: =B8 -> 109 | E8: =B8*C8 -> 574757 | F8: =IFERROR(__xludf.DUMMYFUNCTION("GOOGLEFINANCE(CONCAT(""NSE:"",A8))"),4512.5) -> 4512.5 | G8: =D8*F8 -> 491862.5 | H8: =(G8-E8)/E8 -> -0.1442253
A9: LAURUSLABS | B9: 647 | C9: 1509.9 | D9: =B9 -> 647 | E9: =B9*C9 -> 976905.3 | F9: =IFERROR(__xludf.DUMMYFUNCTION("GOOGLEFINANCE(CONCAT(""NSE:"",A9))"),1944.7) -> 1944.7 | G9: =D9*F9 -> 1258220.9 | H9: =(G9-E9)/E9 -> 0.28796609
A10: LTF | B10: 2208 | C10: 313.45 | D10: =B10 -> 2208 | E10: =B10*C10 -> 692097.6 | F10: =IFERROR(__xludf.DUMMYFUNCTION("GOOGLEFINANCE(CONCAT(""NSE:"",A10))"),298.85) -> 298.85 | G10: =D10*F10 -> 659860.8 | H10: =(G10-E10)/E10 -> -0.046578402
A11: MCX | B11: 280 | C11: 3011 | D11: =B11 -> 280 | E11: =B11*C11 -> 843080 | F11: =IFERROR(__xludf.DUMMYFUNCTION("GOOGLEFINANCE(CONCAT(""NSE:"",A11))"),3290.8) -> 3290.8 | G11: =D11*F11 -> 921424 | H11: =(G11-E11)/E11 -> 0.092925938
A12: NAM-INDIA | B12: 652 | C12: 1220.5 | D12: =B12 -> 652 | E12: =B12*C12 -> 795766 | F12: =IFERROR(__xludf.DUMMYFUNCTION("GOOGLEFINANCE(CONCAT(""NSE:"",A12))"),1113.3) -> 1113.3 | G12: =D12*F12 -> 725871.6 | H12: =(G12-E12)/E12 -> -0.087832855
A13: NATIONALUM | B13: 2446 | C13: 334.95 | D13: =B13 -> 2446 | E13: =B13*C13 -> 819287.7 | F13: =IFERROR(__xludf.DUMMYFUNCTION("GOOGLEFINANCE(CONCAT(""NSE:"",A13))"),356.3) -> 356.3 | G13: =D13*F13 -> 871509.8 | H13: =(G13-E13)/E13 -> 0.063740857
A14: POWERINDIA | B14: 28 | C14: 34085 | D14: =B14 -> 28 | E14: =B14*C14 -> 954380 | F14: =IFERROR(__xludf.DUMMYFUNCTION("GOOGLEFINANCE(CONCAT(""NSE:"",A14))"),30810.0) -> 30810 | G14: =D14*F14 -> 862680 | H14: =(G14-E14)/E14 -> -0.096083321
A15: RBLBANK | B15: 1519 | C15: 356.55 | D15: =B15 -> 1519 | E15: =B15*C15 -> 541599.45 | F15: =IFERROR(__xludf.DUMMYFUNCTION("GOOGLEFINANCE(CONCAT(""NSE:"",A15))"),406.85) -> 406.85 | G15: =D15*F15 -> 618005.15 | H15: =(G15-E15)/E15 -> 0.14107418
A16: ADANIENSOL | B16: 617 | C16: 1551.9 | D16: =B16 -> 617 | E16: =B16*C16 -> 957522.3 | F16: =IFERROR(__xludf.DUMMYFUNCTION("GOOGLEFINANCE(CONCAT(""NSE:"",A16))"),1356.1) -> 1356.1 | G16: =D16*F16 -> 836713.7 | H16: =(G16-E16)/E16 -> -0.12616792
A17: ADANIENT | B17: 150 | C17: 3149.9 | D17: =B17 -> 150 | E17: =B17*C17 -> 472485 | F17: =IFERROR(__xludf.DUMMYFUNCTION("GOOGLEFINANCE(CONCAT(""NSE:"",A17))"),2921.0) -> 2921 | G17: =D17*F17 -> 438150 | H17: =(G17-E17)/E17 -> -0.072668974
A18: ADANIGREEN | B18: 537 | C18: 1543.4 | D18: =B18 -> 537 | E18: =B18*C18 -> 828805.8 | F18: =IFERROR(__xludf.DUMMYFUNCTION("GOOGLEFINANCE(CONCAT(""NSE:"",A18))"),1269.6) -> 1269.6 | G18: =D18*F18 -> 681775.2 | H18: =(G18-E18)/E18 -> -0.17740054
A19: ADANIPOWER | B19: 4574 | C19: 226.61 | D19: =B19 -> 4574 | E19: =B19*C19 -> 1036514.1 | F19: =IFERROR(__xludf.DUMMYFUNCTION("GOOGLEFINANCE(CONCAT(""NSE:"",A19))"),203.99) -> 203.99 | G19: =D19*F19 -> 933050.26 | H19: =(G19-E19)/E19 -> -0.099819072
A20: BHARATFORG | B20: 363 | C20: 2129 | D20: =B20 -> 363 | E20: =B20*C20 -> 772827 | F20: =IFERROR(__xludf.DUMMYFUNCTION("GOOGLEFINANCE(CONCAT(""NSE:"",A20))"),1915.6) -> 1915.6 | G20: =D20*F20 -> 695362.8 | H20: =(G20-E20)/E20 -> -0.10023485
A21: BHEL | B21: 1760 | C21: 403.13 | D21: =B21 -> 1760 | E21: =B21*C21 -> 709508.8 | F21: =IFERROR(__xludf.DUMMYFUNCTION("GOOGLEFINANCE(CONCAT(""NSE:"",A21))"),420.35) -> 420.35 | G21: =D21*F21 -> 739816 | H21: =(G21-E21)/E21 -> 0.042715749
A22: CGPOWER | B22: 631 | C22: 965.23 | D22: =B22 -> 631 | E22: =B22*C22 -> 609060.13 | F22: =IFERROR(__xludf.DUMMYFUNCTION("GOOGLEFINANCE(CONCAT(""NSE:"",A22))"),868.85) -> 868.85 | G22: =D22*F22 -> 548244.35 | H22: =(G22-E22)/E22 -> -0.099851849
A23: CUMMINSIND | B23: 143 | C23: 5591 | D23: =B23 -> 143 | E23: =B23*C23 -> 799513 | F23: =IFERROR(__xludf.DUMMYFUNCTION("GOOGLEFINANCE(CONCAT(""NSE:"",A23))"),5003.0) -> 5003 | G23: =D23*F23 -> 715429 | H23: =(G23-E23)/E23 -> -0.10516902
A24: FEDERALBNK | B24: 1893 | C24: 330.05 | D24: =B24 -> 1893 | E24: =B24*C24 -> 624784.65 | F24: =IFERROR(__xludf.DUMMYFUNCTION("GOOGLEFINANCE(CONCAT(""NSE:"",A24))"),339.5) -> 339.5 | G24: =D24*F24 -> 642673.5 | H24: =(G24-E24)/E24 -> 0.028632025
A25: GMRAIRPORT | B25: 4737 | C25: 111.48 | D25: =B25 -> 4737 | E25: =B25*C25 -> 528080.76 | F25: =IFERROR(__xludf.DUMMYFUNCTION("GOOGLEFINANCE(CONCAT(""NSE:"",A25))"),94.38) -> 94.38 | G25: =D25*F25 -> 447078.06 | H25: =(G25-E25)/E25 -> -0.15339074
A26: GVT&D | B26: 227 | C26: 4848.98 | D26: =B26 -> 227 | E26: =B26*C26 -> 1100718.5 | F26: =IFERROR(__xludf.DUMMYFUNCTION("GOOGLEFINANCE(CONCAT(""NSE:"",A26))"),4297.0) -> 4297 | G26: =D26*F26 -> 975419 | H26: =(G26-E26)/E26 -> -0.11383425
A27: MOTHERSON | B27: 4873 | C27: 147.09 | D27: =B27 -> 4873 | E27: =B27*C27 -> 716769.57 | F27: =IFERROR(__xludf.DUMMYFUNCTION("GOOGLEFINANCE(CONCAT(""NSE:"",A27))"),161.34) -> 161.34 | G27: =D27*F27 -> 786209.82 | H27: =(G27-E27)/E27 -> 0.096879462
A28: NYKAA | B28: 2037 | C28: 311.4 | D28: =B28 -> 2037 | E28: =B28*C28 -> 634321.8 | F28: =IFERROR(__xludf.DUMMYFUNCTION("GOOGLEFINANCE(CONCAT(""NSE:"",A28))"),324.9) -> 324.9 | G28: =D28*F28 -> 661821.3 | H28: =(G28-E28)/E28 -> 0.043352601
A29: PAYTM | B29: 461 | C29: 1214.75 | D29: =B29 -> 461 | E29: =B29*C29 -> 559999.75 | F29: =IFERROR(__xludf.DUMMYFUNCTION("GOOGLEFINANCE(CONCAT(""NSE:"",A29))"),1761.4) -> 1761.4 | G29: =D29*F29 -> 812005.4 | H29: =(G29-E29)/E29 -> 0.45001029
A30: POLYCAB | B30: 66 | C30: 9606 | D30: =B30 -> 66 | E30: =B30*C30 -> 633996 | F30: =IFERROR(__xludf.DUMMYFUNCTION("GOOGLEFINANCE(CONCAT(""NSE:"",A30))"),8163.5) -> 8163.5 | G30: =D30*F30 -> 538791 | H30: =(G30-E30)/E30 -> -0.15016656
A31: RADICO | B31: 163 | C31: 3953 | D31: =B31 -> 163 | E31: =B31*C31 -> 644339 | F31: =IFERROR(__xludf.DUMMYFUNCTION("GOOGLEFINANCE(CONCAT(""NSE:"",A31))"),4424.0) -> 4424 | G31: =D31*F31 -> 721112 | H31: =(G31-E31)/E31 -> 0.11915001
A32: SHRIRAMFIN | B32: 744 | C32: 1067.3 | D32: =B32 -> 744 | E32: =B32*C32 -> 794071.2 | F32: =IFERROR(__xludf.DUMMYFUNCTION("GOOGLEFINANCE(CONCAT(""NSE:"",A32))"),989.1) -> 989.1 | G32: =D32*F32 -> 735890.4 | H32: =(G32-E32)/E32 -> -0.073268997
A33: SONACOMS | B33: 760 | C33: 652 | D33: =B33 -> 760 | E33: =B33*C33 -> 495520 | F33: =IFERROR(__xludf.DUMMYFUNCTION("GOOGLEFINANCE(CONCAT(""NSE:"",A33))"),786.05) -> 786.05 | G33: =D33*F33 -> 597398 | H33: =(G33-E33)/E33 -> 0.20559816
A35: 46118 | B35: Qty | C35: Buying Rate | D35: Changed Qty | E35: Amount at entry | F35: Actual Price | G35: Amount by M2M | H35: P&L
A36: ABCAPITAL | B36: 2041 | C36: 295.75 | D36: =B36 -> 2041 | E36: =B36*C36 -> 603625.75 | F36: =IFERROR(__xludf.DUMMYFUNCTION("GOOGLEFINANCE(concat(""NSE:"",A36))"),386.35) -> 386.35 | G36: =D36*F36 -> 788540.35 | H36: =(G36-E36)/E36 -> 0.30633981
A37: ASHOKLEY | B37: 3792 | C37: 145.37 | D37: =B37 -> 3792 | E37: =B37*C37 -> 551243.04 | F37: =IFERROR(__xludf.DUMMYFUNCTION("GOOGLEFINANCE(concat(""NSE:"",A37))"),157.53) -> 157.53 | G37: =D37*F37 -> 597353.76 | H37: =(G37-E37)/E37 -> 0.083648621
A38: AUBANK | B38: 736 | C38: 858.7 | D38: =B38 -> 736 | E38: =B38*C38 -> 632003.2 | F38: =IFERROR(__xludf.DUMMYFUNCTION("GOOGLEFINANCE(concat(""NSE:"",A38))"),1036.2) -> 1036.2 | G38: =D38*F38 -> 762643.2 | H38: =(G38-E38)/E38 -> 0.20670781
A39: BEL | B39: 974 | C39: 421.45 | D39: =B39 -> 974 | E39: =B39*C39 -> 410492.3 | F39: =IFERROR(__xludf.DUMMYFUNCTION("GOOGLEFINANCE(concat(""NSE:"",A39))"),392.8) -> 392.8 | G39: =D39*F39 -> 382587.2 | H39: =(G39-E39)/E39 -> -0.067979594
A40: BSE | B40: 225 | C40: 2826.5 | D40: =B40 -> 225 | E40: =B40*C40 -> 635962.5 | F40: =IFERROR(__xludf.DUMMYFUNCTION("GOOGLEFINANCE(concat(""NSE:"",A40))"),3271.6) -> 3271.6 | G40: =D40*F40 -> 736110 | H40: =(G40-E40)/E40 -> 0.15747391
A41: CANBK | B41: 3466 | C41: 125.56 | D41: =B41 -> 3466 | E41: =B41*C41 -> 435190.96 | F41: =IFERROR(__xludf.DUMMYFUNCTION("GOOGLEFINANCE(concat(""NSE:"",A41))"),122.6) -> 122.6 | G41: =D41*F41 -> 424931.6 | H41: =(G41-E41)/E41 -> -0.023574387
A42: INDIANB | B42: 693 | C42: 873.25 | D42: =B42 -> 693 | E42: =B42*C42 -> 605162.25 | F42: =IFERROR(__xludf.DUMMYFUNCTION("GOOGLEFINANCE(concat(""NSE:"",A42))"),842.9) -> 842.9 | G42: =D42*F42 -> 584129.7 | H42: =(G42-E42)/E42 -> -0.034755225
A43: LAURUSLABS | B43: 650 | C43: 1019 | D43: =B43 -> 650 | E43: =B43*C43 -> 662350 | F43: =IFERROR(__xludf.DUMMYFUNCTION("GOOGLEFINANCE(concat(""NSE:"",A43))"),1944.7) -> 1944.7 | G43: =D43*F43 -> 1264055 | H43: =(G43-E43)/E43 -> 0.90843965
A44: LTF | B44: 2568 | C44: 243.9 | D44: =B44 -> 2568 | E44: =B44*C44 -> 626335.2 | F44: =IFERROR(__xludf.DUMMYFUNCTION("GOOGLEFINANCE(concat(""NSE:"",A44))"),298.85) -> 298.85 | G44: =D44*F44 -> 767446.8 | H44: =(G44-E44)/E44 -> 0.22529725
A45: MCX | B45: 466 | C45: 2447.93 | D45: =B45 -> 466 | E45: =B45*C45 -> 1140735.4 | F45: =IFERROR(__xludf.DUMMYFUNCTION("GOOGLEFINANCE(concat(""NSE:"",A45))"),3290.8) -> 3290.8 | G45: =D45*F45 -> 1533512.8 | H45: =(G45-E45)/E45 -> 0.34431949
A46: MUTHOOTFIN | B46: 135 | C46: 3189.54 | D46: =B46 -> 135 | E46: =B46*C46 -> 430587.9 | F46: =IFERROR(__xludf.DUMMYFUNCTION("GOOGLEFINANCE(concat(""NSE:"",A46))"),2752.2) -> 2752.2 | G46: =D46*F46 -> 371547 | H46: =(G46-E46)/E46 -> -0.13711695
A47: RBLBANK | B47: 2228 | C47: 308.2 | D47: =B47 -> 2228 | E47: =B47*C47 -> 686669.6 | F47: =IFERROR(__xludf.DUMMYFUNCTION("GOOGLEFINANCE(concat(""NSE:"",A47))"),406.85) -> 406.85 | G47: =D47*F47 -> 906461.8 | H47: =(G47-E47)/E47 -> 0.32008436
A48: SHRIRAMFIN | B48: 592 | C48: 893 | D48: =B48 -> 592 | E48: =B48*C48 -> 528656 | F48: =IFERROR(__xludf.DUMMYFUNCTION("GOOGLEFINANCE(concat(""NSE:"",A48))"),989.1) -> 989.1 | G48: =D48*F48 -> 585547.2 | H48: =(G48-E48)/E48 -> 0.10761478
A49: UNIONBANK | B49: 2580 | C49: 171.92 | D49: =B49 -> 2580 | E49: =B49*C49 -> 443553.6 | F49: =IFERROR(__xludf.DUMMYFUNCTION("GOOGLEFINANCE(concat(""NSE:"",A49))"),177.15) -> 177.15 | G49: =D49*F49 -> 457047 | H49: =(G49-E49)/E49 -> 0.030421126
A50: TVSMOTOR | B50: 132 | C50: 0 | D50: =B50 -> 132 | E50: =B50*C50 -> 0 | F50: =IFERROR(__xludf.DUMMYFUNCTION("GOOGLEFINANCE(concat(""NSE:"",A50))"),4116.7) -> 4116.7 | G50: =D50*F50 -> 543404.4 | H50: =(G50-E50)/E50 -> #DIV/0!
A51: ADANIPOWER | B51: 3996 | C51: 163.95 | D51: =B51 -> 3996 | E51: =B51*C51 -> 655144.2 | F51: =IFERROR(__xludf.DUMMYFUNCTION("GOOGLEFINANCE(concat(""NSE:"",A51))"),203.99) -> 203.99 | G51: =D51*F51 -> 815144.04 | H51: =(G51-E51)/E51 -> 0.2442208
A52: BHARATFORG | B52: 318 | C52: 1636.9 | D52: =B52 -> 318 | E52: =B52*C52 -> 520534.2 | F52: =IFERROR(__xludf.DUMMYFUNCTION("GOOGLEFINANCE(concat(""NSE:"",A52))"),1915.6) -> 1915.6 | G52: =D52*F52 -> 609160.8 | H52: =(G52-E52)/E52 -> 0.17026086
A53: CUMMINSIND | B53: 125 | C53: 4684.6 | D53: =B53 -> 125 | E53: =B53*C53 -> 585575 | F53: =IFERROR(__xludf.DUMMYFUNCTION("GOOGLEFINANCE(concat(""NSE:"",A53))"),5003.0) -> 5003 | G53: =D53*F53 -> 625375 | H53: =(G53-E53)/E53 -> 0.067967382
A54: DELHIVERY | B54: 1412 | C54: 422.85 | D54: =B54 -> 1412 | E54: =B54*C54 -> 597064.2 | F54: =IFERROR(__xludf.DUMMYFUNCTION("GOOGLEFINANCE(concat(""NSE:"",A54))"),422.4) -> 422.4 | G54: =D54*F54 -> 596428.8 | H54: =(G54-E54)/E54 -> -0.0010642072
A55: FORCEMOT | B55: 60 | C55: 21420 | D55: =B55 -> 60 | E55: =B55*C55 -> 1285200 | F55: =IFERROR(__xludf.DUMMYFUNCTION("GOOGLEFINANCE(concat(""NSE:"",A55))"),17516.0) -> 17516 | G55: =D55*F55 -> 1050960 | H55: =(G55-E55)/E55 -> -0.18225957
A56: GLENMARK | B56: 219 | C56: 2052.86 | D56: =B56 -> 219 | E56: =B56*C56 -> 449576.34 | F56: =IFERROR(__xludf.DUMMYFUNCTION("GOOGLEFINANCE(concat(""NSE:"",A56))"),2394.4) -> 2394.4 | G56: =D56*F56 -> 524373.6 | H56: =(G56-E56)/E56 -> 0.16637277
A57: HEROMOTOCO | B57: 86 | C57: 5030.5 | D57: =B57 -> 86 | E57: =B57*C57 -> 432623 | F57: =IFERROR(__xludf.DUMMYFUNCTION("GOOGLEFINANCE(concat(""NSE:"",A57))"),5311.0) -> 5311 | G57: =D57*F57 -> 456746 | H57: =(G57-E57)/E57 -> 0.055759865
A58: KEI | B58: 125 | C58: 4037.35 | D58: =B58 -> 125 | E58: =B58*C58 -> 504668.75 | F58: =IFERROR(__xludf.DUMMYFUNCTION("GOOGLEFINANCE(concat(""NSE:"",A58))"),4512.5) -> 4512.5 | G58: =D58*F58 -> 564062.5 | H58: =(G58-E58)/E58 -> 0.11768858
A59: NAM-INDIA | B59: 701 | C59: 826.54 | D59: =B59 -> 701 | E59: =B59*C59 -> 579404.54 | F59: =IFERROR(__xludf.DUMMYFUNCTION("GOOGLEFINANCE(concat(""NSE:"",A59))"),1113.3) -> 1113.3 | G59: =D59*F59 -> 780423.3 | H59: =(G59-E59)/E59 -> 0.34694026
A60: NATIONALUM | B60: 2557 | C60: 412.45 | D60: =B60 -> 2557 | E60: =B60*C60 -> 1054634.6 | F60: =IFERROR(__xludf.DUMMYFUNCTION("GOOGLEFINANCE(concat(""NSE:"",A60))"),356.3) -> 356.3 | G60: =D60*F60 -> 911059.1 | H60: =(G60-E60)/E60 -> -0.13613771
A61: POLYCAB | B61: 63 | C61: 6882 | D61: =B61 -> 63 | E61: =B61*C61 -> 433566 | F61: =IFERROR(__xludf.DUMMYFUNCTION("GOOGLEFINANCE(concat(""NSE:"",A61))"),8163.5) -> 8163.5 | G61: =D61*F61 -> 514300.5 | H61: =(G61-E61)/E61 -> 0.1862104
A62: POWERINDIA | B62: 40 | C62: 25418.33 | D62: =B62 -> 40 | E62: =B62*C62 -> 1016733.2 | F62: =IFERROR(__xludf.DUMMYFUNCTION("GOOGLEFINANCE(concat(""NSE:"",A62))"),30810.0) -> 30810 | G62: =D62*F62 -> 1232400 | H62: =(G62-E62)/E62 -> 0.2121174
A63: SAIL | B63: 2653 | C63: 153.15 | D63: =B63 -> 2653 | E63: =B63*C63 -> 406306.95 | F63: =IFERROR(__xludf.DUMMYFUNCTION("GOOGLEFINANCE(concat(""NSE:"",A63))"),173.29) -> 173.29 | G63: =D63*F63 -> 459738.37 | H63: =(G63-E63)/E63 -> 0.13150506
A64: VEDL | B64: 821 | C64: 707.4 | D64: =B64 -> 821 | E64: =B64*C64 -> 580775.4 | F64: =IFERROR(__xludf.DUMMYFUNCTION("GOOGLEFINANCE(concat(""NSE:"",A64))"),256.3) -> 256.3 | G64: =D64*F64 -> 210422.3 | H64: =(G64-E64)/E64 -> -0.63768731
A65: WAAREEENER | B65: 145 | C65: 3062 | D65: =B65 -> 145 | E65: =B65*C65 -> 443990 | F65: =IFERROR(__xludf.DUMMYFUNCTION("GOOGLEFINANCE(concat(""NSE:"",A65))"),2497.5) -> 2497.5 | G65: =D65*F65 -> 362137.5 | H65: =(G65-E65)/E65 -> -0.18435663
A68: 46030 | B68: Qty | C68: Buying Rate | D68: Changed Qty | E68: Amount at entry | F68: Actual Price | G68: Amount by M2M | H68: P&L
A69: BDL | B69: 304 | C69: 1536.2 | D69: =B69 -> 304 | E69: =B69*C69 -> 467004.8 | F69: =IFERROR(__xludf.DUMMYFUNCTION("GOOGLEFINANCE(CONCAT(""NSE:"",A69))"),1144.0) -> 1144 | G69: =D69*F69 -> 347776 | H69: =(G69-E69)/E69 -> -0.2553053
A70: BEL | B70: 1218 | C70: 413.6 | D70: =B70 -> 1218 | E70: =B70*C70 -> 503764.8 | F70: =IFERROR(__xludf.DUMMYFUNCTION("GOOGLEFINANCE(CONCAT(""NSE:"",A70))"),392.8) -> 392.8 | G70: =D70*F70 -> 478430.4 | H70: =(G70-E70)/E70 -> -0.050290135
A71: BSE | B71: 231 | C71: 2739.6 | D71: =B71 -> 231 | E71: =B71*C71 -> 632847.6 | F71: =IFERROR(__xludf.DUMMYFUNCTION("GOOGLEFINANCE(CONCAT(""NSE:"",A71))"),3271.6) -> 3271.6 | G71: =D71*F71 -> 755739.6 | H71: =(G71-E71)/E71 -> 0.19418893
A72: INDIANB | B72: 796 | C72: 854.1 | D72: =B72 -> 796 | E72: =B72*C72 -> 679863.6 | F72: =IFERROR(__xludf.DUMMYFUNCTION("GOOGLEFINANCE(CONCAT(""NSE:"",A72))"),842.9) -> 842.9 | G72: =D72*F72 -> 670948.4 | H72: =(G72-E72)/E72 -> -0.013113219
A73: LAURUSLABS | B73: 696 | C73: 1131.8 | D73: =B73 -> 696 | E73: =B73*C73 -> 787732.8 | F73: =IFERROR(__xludf.DUMMYFUNCTION("GOOGLEFINANCE(CONCAT(""NSE:"",A73))"),1944.7) -> 1944.7 | G73: =D73*F73 -> 1353511.2 | H73: =(G73-E73)/E73 -> 0.71823644
A74: MANAPPURAM | B74: 2275 | C74: 312.3 | D74: =B74 -> 2275 | E74: =B74*C74 -> 710482.5 | F74: =IFERROR(__xludf.DUMMYFUNCTION("GOOGLEFINANCE(CONCAT(""NSE:"",A74))"),317.0) -> 317 | G74: =D74*F74 -> 721175 | H74: =(G74-E74)/E74 -> 0.015049632
A75: MUTHOOTFIN | B75: 220 | C75: 3973.7 | D75: =B75 -> 220 | E75: =B75*C75 -> 874214 | F75: =IFERROR(__xludf.DUMMYFUNCTION("GOOGLEFINANCE(CONCAT(""NSE:"",A75))"),2752.2) -> 2752.2 | G75: =D75*F75 -> 605484 | H75: =(G75-E75)/E75 -> -0.30739613
A76: PAYTM | B76: 354 | C76: 1320.6 | D76: =B76 -> 354 | E76: =B76*C76 -> 467492.4 | F76: =IFERROR(__xludf.DUMMYFUNCTION("GOOGLEFINANCE(CONCAT(""NSE:"",A76))"),1761.4) -> 1761.4 | G76: =D76*F76 -> 623535.6 | H76: =(G76-E76)/E76 -> 0.33378767
A77: POWERINDIA | B77: 31 | C77: 19413 | D77: =B77 -> 31 | E77: =B77*C77 -> 601803 | F77: =IFERROR(__xludf.DUMMYFUNCTION("GOOGLEFINANCE(CONCAT(""NSE:"",A77))"),30810.0) -> 30810 | G77: =D77*F77 -> 955110 | H77: =(G77-E77)/E77 -> 0.58708082
A78: UNIONBANK | B78: 2755 | C78: 165.53 | D78: =B78 -> 2755 | E78: =B78*C78 -> 456035.15 | F78: =IFERROR(__xludf.DUMMYFUNCTION("GOOGLEFINANCE(CONCAT(""NSE:"",A78))"),177.15) -> 177.15 | G78: =D78*F78 -> 488048.25 | H78: =(G78-E78)/E78 -> 0.070198756
A79: ABCAPITAL | B79: 2563 | C79: 361.67 | D79: =B79 -> 2563 | E79: =B79*C79 -> 926960.21 | F79: =IFERROR(__xludf.DUMMYFUNCTION("GOOGLEFINANCE(CONCAT(""NSE:"",A79))"),386.35) -> 386.35 | G79: =D79*F79 -> 990215.05 | H79: =(G79-E79)/E79 -> 0.068239002
A80: ASHOKLEY | B80: 4022 | C80: 185.48 | D80: =B80 -> 4022 | E80: =B80*C80 -> 746000.56 | F80: =IFERROR(__xludf.DUMMYFUNCTION("GOOGLEFINANCE(CONCAT(""NSE:"",A80))"),157.53) -> 157.53 | G80: =D80*F80 -> 633585.66 | H80: =(G80-E80)/E80 -> -0.1506901
A81: AUBANK | B81: 854 | C81: 1002.63 | D81: =B81 -> 854 | E81: =B81*C81 -> 856246.02 | F81: =IFERROR(__xludf.DUMMYFUNCTION("GOOGLEFINANCE(CONCAT(""NSE:"",A81))"),1036.2) -> 1036.2 | G81: =D81*F81 -> 884914.8 | H81: =(G81-E81)/E81 -> 0.033481942
A82: BANKINDIA | B82: 3547 | C82: 151.54 | D82: =B82 -> 3547 | E82: =B82*C82 -> 537512.38 | F82: =IFERROR(__xludf.DUMMYFUNCTION("GOOGLEFINANCE(CONCAT(""NSE:"",A82))"),138.55) -> 138.55 | G82: =D82*F82 -> 491436.85 | H82: =(G82-E82)/E82 -> -0.085719942
A83: CANBK | B83: 3761 | C83: 155.19 | D83: =B83 -> 3761 | E83: =B83*C83 -> 583669.59 | F83: =IFERROR(__xludf.DUMMYFUNCTION("GOOGLEFINANCE(CONCAT(""NSE:"",A83))"),122.6) -> 122.6 | G83: =D83*F83 -> 461098.6 | H83: =(G83-E83)/E83 -> -0.21000064
A84: CUMMINSIND | B84: 104 | C84: 4149.17 | D84: =B84 -> 104 | E84: =B84*C84 -> 431513.68 | F84: =IFERROR(__xludf.DUMMYFUNCTION("GOOGLEFINANCE(CONCAT(""NSE:"",A84))"),5003.0) -> 5003 | G84: =D84*F84 -> 520312 | H84: =(G84-E84)/E84 -> 0.20578333
A85: HINDALCO | B85: 619 | C85: 943.05 | D85: =B85 -> 619 | E85: =B85*C85 -> 583747.95 | F85: =IFERROR(__xludf.DUMMYFUNCTION("GOOGLEFINANCE(CONCAT(""NSE:"",A85))"),983.7) -> 983.7 | G85: =D85*F85 -> 608910.3 | H85: =(G85-E85)/E85 -> 0.043104819
A86: IIFL | B86: 729 | C86: 654.5 | D86: =B86 -> 729 | E86: =B86*C86 -> 477130.5 | F86: =IFERROR(__xludf.DUMMYFUNCTION("GOOGLEFINANCE(CONCAT(""NSE:"",A86))"),597.1) -> 597.1 | G86: =D86*F86 -> 435285.9 | H86: =(G86-E86)/E86 -> -0.087700535
A87: LTF | B87: 3386 | C87: 314.05 | D87: =B87 -> 3386 | E87: =B87*C87 -> 1063373.3 | F87: =IFERROR(__xludf.DUMMYFUNCTION("GOOGLEFINANCE(CONCAT(""NSE:"",A87))"),298.85) -> 298.85 | G87: =D87*F87 -> 1011906.1 | H87: =(G87-E87)/E87 -> -0.048399936
A88: MARUTI | B88: 24 | C88: 17023 | D88: =B88 -> 24 | E88: =B88*C88 -> 408552 | F88: =IFERROR(__xludf.DUMMYFUNCTION("GOOGLEFINANCE(CONCAT(""NSE:"",A88))"),12324.0) -> 12324 | G88: =D88*F88 -> 295776 | H88: =(G88-E88)/E88 -> -0.2760383
A89: MCX | B89: 373 | C89: 2282 | D89: =B89 -> 373 | E89: =B89*C89 -> 851186 | F89: =IFERROR(__xludf.DUMMYFUNCTION("GOOGLEFINANCE(CONCAT(""NSE:"",A89))"),3290.8) -> 3290.8 | G89: =D89*F89 -> 1227468.4 | H89: =(G89-E89)/E89 -> 0.44206836
A90: MFSL | B90: 306 | C90: 1739.4 | D90: =B90 -> 306 | E90: =B90*C90 -> 532256.4 | F90: =IFERROR(__xludf.DUMMYFUNCTION("GOOGLEFINANCE(CONCAT(""NSE:"",A90))"),1531.1) -> 1531.1 | G90: =D90*F90 -> 468516.6 | H90: =(G90-E90)/E90 -> -0.11975394
A91: NATIONALUM | B91: 1814 | C91: 351.4 | D91: =B91 -> 1814 | E91: =B91*C91 -> 637439.6 | F91: =IFERROR(__xludf.DUMMYFUNCTION("GOOGLEFINANCE(CONCAT(""NSE:"",A91))"),356.3) -> 356.3 | G91: =D91*F91 -> 646328.2 | H91: =(G91-E91)/E91 -> 0.013944223
A92: NYKAA | B92: 1880 | C92: 268.8 | D92: =B92 -> 1880 | E92: =B92*C92 -> 505344 | F92: =IFERROR(__xludf.DUMMYFUNCTION("GOOGLEFINANCE(CONCAT(""NSE:"",A92))"),324.9) -> 324.9 | G92: =D92*F92 -> 610812 | H92: =(G92-E92)/E92 -> 0.20870536
A93: RBLBANK | B93: 2637 | C93: 319 | D93: =B93 -> 2637 | E93: =B93*C93 -> 841203 | F93: =IFERROR(__xludf.DUMMYFUNCTION("GOOGLEFINANCE(CONCAT(""NSE:"",A93))"),406.85) -> 406.85 | G93: =D93*F93 -> 1072863.4 | H93: =(G93-E93)/E93 -> 0.27539185
A94: SBILIFE | B94: 225 | C94: 2083.11 | D94: =B94 -> 225 | E94: =B94*C94 -> 468699.75 | F94: =IFERROR(__xludf.DUMMYFUNCTION("GOOGLEFINANCE(CONCAT(""NSE:"",A94))"),1734.0) -> 1734 | G94: =D94*F94 -> 390150 | H94: =(G94-E94)/E94 -> -0.16759077
A95: SHRIRAMFIN | B95: 676 | C95: 999 | D95: =B95 -> 676 | E95: =B95*C95 -> 675324 | F95: =IFERROR(__xludf.DUMMYFUNCTION("GOOGLEFINANCE(CONCAT(""NSE:"",A95))"),989.1) -> 989.1 | G95: =D95*F95 -> 668631.6 | H95: =(G95-E95)/E95 -> -0.0099099099
A96: SOLARINDS | B96: 32 | C96: 13109 | D96: =B96 -> 32 | E96: =B96*C96 -> 419488 | F96: =IFERROR(__xludf.DUMMYFUNCTION("GOOGLEFINANCE(CONCAT(""NSE:"",A96))"),18950.0) -> 18950 | G96: =D96*F96 -> 606400 | H96: =(G96-E96)/E96 -> 0.44557174
A97: TVSMOTOR | B97: 132 | C97: 3854.1 | D97: =B97 -> 132 | E97: =B97*C97 -> 508741.2 | F97: =IFERROR(__xludf.DUMMYFUNCTION("GOOGLEFINANCE(CONCAT(""NSE:"",A97))"),4116.7) -> 4116.7 | G97: =D97*F97 -> 543404.4 | H97: =(G97-E97)/E97 -> 0.068135233
A98: UPL | B98: 664 | C98: 801.25 | D98: =B98 -> 664 | E98: =B98*C98 -> 532030 | F98: =IFERROR(__xludf.DUMMYFUNCTION("GOOGLEFINANCE(CONCAT(""NSE:"",A98))"),550.2) -> 550.2 | G98: =D98*F98 -> 365332.8 | H98: =(G98-E98)/E98 -> -0.31332293
G99: =SUM(G69:G98) -> 19933107
A100: 45931 | B100: Qty | C100: Buying Rate | D100: Changed Qty | E100: Amount at entry | F100: Actual Price | G100: Amount by M2M | H100: P&L
A101: BSE | B101: 467 | C101: 2068.2 | D101: =B101 -> 467 | E101: =B101*C101 -> 965849.4 | F101: =IFERROR(__xludf.DUMMYFUNCTION("GOOGLEFINANCE(CONCAT(""NSE:"",A101))"),3271.6) -> 3271.6 | G101: =F101*D101 -> 1527837.2 | H101: =(G101-E101)/E101 -> 0.58185862 | U101: ABCA01 | V101: ABCAPITAL | W101: INE674K01013 | X101: 1400 | Y101: 363.3 | Z101: 508620
A102: FORTIS | B102: 704 | C102: 986.52 | D102: =B102 -> 704 | E102: =B102*C102 -> 694510.08 | F102: =IFERROR(__xludf.DUMMYFUNCTION("GOOGLEFINANCE(CONCAT(""NSE:"",A102))"),888.05) -> 888.05 | G102: =F102*D102 -> 625187.2 | H102: =(G102-E102)/E102 -> -0.099815513 | U102: AMBE01 | V102: AMBER | W102: INE371P01015 | X102: 126 | Y102: 6712 | Z102: 845712
A103: GLENMARK | B103: 174 | C103: 1965.5 | D103: =B103 -> 174 | E103: =B103*C103 -> 341997 | F103: =IFERROR(__xludf.DUMMYFUNCTION("GOOGLEFINANCE(CONCAT(""NSE:"",A103))"),2394.4) -> 2394.4 | G103: =F103*D103 -> 416625.6 | H103: =(G103-E103)/E103 -> 0.21821419 | U103: ASHO01 | V103: ASHOKLEY | W103: INE208A01029 | X103: 3474 | Y103: 187.76 | Z103: 652278.2
...

Sheet hpc39_5 cash ledger
E1: dr | F1: cr | G1: net | H1: holding | I1: p&l | L1: Nifty Performance | M1: Strategy performance
A2: 45360 | B2: Settlement Posting-NU4165 | C2: DLV1-0309-NU4165/HPC39_5 | D2: 45331 | E2: 1080618.2 | F2: 0 | G2: -1080618.2
A3: 45360 | B3: Settlement Posting-NG4165 | C3: DLV3-0309-NG4165/HPC39_5 | D3: 45331 | E3: 18951655 | F3: 0 | G3: -20032274 | K3: 25278.7 | L3: =K3/K3 -> 1
A4: 22-10-2024 | B4: Settlement Posting-NG4165 | C4: DLV3-0309-NG4165/HPC39_5 | D4: 21-10-2024 | F4: 0 | G4: -20032274 | H4: 19411044 | I4: =G4+H4 -> -621229.66 | K4: 24781.1 | L4: =K4/$K$3 -> 0.98031544 | M4: =-H4/$G$3 -> 0.96898856
A5: 23-10-2024 | B5: Settlement Posting-NG4165 | C5: DLV3-0309-NG4165/HPC39_5 | D5: 22-10-2024 | F5: 0 | G5: -20032274 | H5: 18628512 | I5: =G5+H5 -> -1403761.7 | K5: 24472.1 | L5: =K5/$K$3 -> 0.96809171 | M5: =-H5/$G$3 -> 0.929925
A6: 24-10-2024 | B6: Settlement Posting-NG4165 | C6: DLV3-0309-NG4165/HPC39_5 | D6: 23-10-2024 | F6: 0 | G6: -20032274 | H6: 18861927 | I6: =G6+H6 -> -1170346.7 | K6: 24435.5 | L6: =K6/$K$3 -> 0.96664385 | M6: =-H6/$G$3 -> 0.94157694
A7: 25-10-2024 | B7: Settlement Posting-NG4165 | C7: DLV3-0309-NG4165/HPC39_5 | D7: 24-10-2024 | F7: 0 | G7: -20032274 | H7: 18716869 | I7: =G7+H7 -> -1315404.7 | K7: 24399.4 | L7: =K7/$K$3 -> 0.96521577 | M7: =-H7/$G$3 -> 0.93433573
A8: 28-10-2024 | B8: Settlement Posting-NG4165 | C8: DLV3-0309-NG4165/HPC39_5 | D8: 25-10-2024 | F8: 0 | G8: -20032274 | H8: 18138954 | I8: =G8+H8 -> -1893319.7 | K8: 24180.8 | L8: =K8/$K$3 -> 0.95656818 | M8: =-H8/$G$3 -> 0.90548653
A9: 29-10-2024 | B9: Settlement Posting-NG4165 | C9: DLV3-0309-NG4165/HPC39_5 | D9: 28-10-2024 | F9: 0 | G9: -20032274 | H9: 18834889 | I9: =G9+H9 -> -1197384.7 | K9: 24339.15 | L9: =K9/$K$3 -> 0.96283235 | M9: =-H9/$G$3 -> 0.94022722
A10: 30-10-2024 | B10: Settlement Posting-NG4165 | C10: DLV3-0309-NG4165/HPC39_5 | D10: 29-10-2024 | F10: 0 | G10: -20032274 | H10: 19101220 | I10: =G10+H10 -> -931053.66 | K10: 24466.85 | L10: =K10/$K$3 -> 0.96788403 | M10: =-H10/$G$3 -> 0.95352232
A11: 31-10-2024 | B11: Settlement Posting-NG4165 | C11: DLV3-0309-NG4165/HPC39_5 | D11: 30-10-2024 | F11: 0 | G11: -20032274 | H11: 19101220 | I11: =G11+H11 -> -931053.66 | K11: 24340.85 | L11: =K11/$K$3 -> 0.9628996 | M11: =-H11/$G$3 -> 0.95352232
A12: 45302 | B12: Settlement Posting-NG4165 | C12: DLV3-0309-NG4165/HPC39_5 | D12: 31-10-2024 | F12: 0 | G12: -20032274 | H12: 19236397 | I12: =G12+H12 -> -795876.66 | K12: 24205.35 | L12: =K12/$K$3 -> 0.95753935 | M12: =-H12/$G$3 -> 0.96027028
A13: 45393 | B13: Settlement Posting-NG4165 | C13: DLV3-0309-NG4165/HPC39_5 | D13: 45302 | F13: 0 | G13: -20032274 | H13: 19378649 | I13: =G13+H13 -> -653624.66 | K13: 24304.35 | L13: =K13/$K$3 -> 0.96145569 | M13: =-H13/$G$3 -> 0.96737142
A14: 45423 | B14: Settlement Posting-NG4165 | C14: DLV3-0309-NG4165/HPC39_5 | D14: 45393 | F14: 0 | G14: -20032274 | H14: 19013361 | I14: =G14+H14 -> -1018912.7 | K14: 23995.35 | L14: =K14/$K$3 -> 0.94923196 | M14: =-H14/$G$3 -> 0.94913644
A15: 45454 | B15: Settlement Posting-NG4165 | C15: DLV3-0309-NG4165/HPC39_5 | D15: 45423 | F15: 0 | G15: -20032274 | H15: 19171102 | I15: =G15+H15 -> -861171.66 | K15: 24213.3 | L15: =K15/$K$3 -> 0.95785385 | M15: =-H15/$G$3 -> 0.95701079
A16: 45484 | B16: Settlement Posting-NG4165 | C16: DLV3-0309-NG4165/HPC39_5 | D16: 45454 | F16: 0 | G16: -20032274 | H16: 19718329 | I16: =G16+H16 -> -313944.66 | K16: 24484.05 | L16: =K16/$K$3 -> 0.96856444 | M16: =-H16/$G$3 -> 0.98432806
A17: 45515 | B17: Settlement Posting-NG4165 | C17: DLV3-0309-NG4165/HPC39_5 | D17: 45484 | F17: 0 | G17: -20032274 | H17: 19542817 | I17: =G17+H17 -> -489456.66 | K17: 24199.35 | L17: =K17/$K$3 -> 0.957302 | M17: =-H17/$G$3 -> 0.97556659
A18: 45607 | B18: Settlement Posting-NG4165 | C18: DLV3-0309-NG4165/HPC39_5 | D18: 45515 | F18: 0 | G18: -20032274 | H18: 18955853 | I18: =G18+H18 -> -1076420.7 | K18: 24148.2 | L18: =K18/$K$3 -> 0.95527855 | M18: =-H18/$G$3 -> 0.94626568
A19: 45637 | B19: Settlement Posting-NG4165 | C19: DLV3-0309-NG4165/HPC39_5 | D19: 45607 | F19: 0 | G19: -20032274 | H19: 18862394 | I19: =G19+H19 -> -1169879.7 | K19: 24141.3 | L19: =K19/$K$3 -> 0.9550056 | M19: =-H19/$G$3 -> 0.94160026
A20: 13-11-2024 | B20: Settlement Posting-NG4165 | C20: DLV3-0309-NG4165/HPC39_5 | D20: 45637 | F20: 0 | G20: -20032274 | H20: 18652204 | I20: =G20+H20 -> -1380069.7 | K20: 23883.45 | L20: =K20/$K$3 -> 0.94480531 | M20: =-H20/$G$3 -> 0.93110769
A21: 14-11-2024 | B21: Settlement Posting-NG4165 | C21: DLV3-0309-NG4165/HPC39_5 | D21: 13-11-2024 | F21: 0 | G21: -20032274 | H21: 17914121 | I21: =G21+H21 -> -2118152.7 | K21: 23559.05 | L21: =K21/$K$3 -> 0.93197237 | M21: =-H21/$G$3 -> 0.89426299
A22: 18-11-2024 | B22: Settlement Posting-NG4165 | C22: DLV3-0309-NG4165/HPC39_5 | D22: 14-11-2024 | F22: 0 | G22: -20032274 | H22: 17934330 | I22: =G22+H22 -> -2097943.7 | K22: 23532.7 | L22: =K22/$K$3 -> 0.93092999 | M22: =-H22/$G$3 -> 0.89527182
A23: 19-11-2024 | B23: Settlement Posting-NG4165 | C23: DLV3-0309-NG4165/HPC39_5 | D23: 18-11-2024 | F23: 0 | G23: -20032274 | H23: 17903741 | I23: =G23+H23 -> -2128532.7 | K23: 23453.8 | L23: =K23/$K$3 -> 0.92780879 | M23: =-H23/$G$3 -> 0.89374483
A24: 21-11-2024 | B24: Settlement Posting-NG4165 | C24: DLV3-0309-NG4165/HPC39_5 | D24: 19-11-2024 | F24: 0 | G24: -20032274 | H24: 18236937 | I24: =G24+H24 -> -1795336.7 | K24: 23518.5 | L24: =K24/$K$3 -> 0.93036825 | M24: =-H24/$G$3 -> 0.91037779
A25: 22-11-2024 | B25: Settlement Posting-NG4165 | C25: DLV3-0309-NG4165/HPC39_5 | D25: 21-11-2024 | F25: 0 | G25: -20032274 | H25: 18143354 | I25: =G25+H25 -> -1888919.7 | K25: 23349.9 | L25: =K25/$K$3 -> 0.92369861 | M25: =-H25/$G$3 -> 0.90570618
A26: 25-11-2024 | B26: Settlement Posting-NG4165 | C26: DLV3-0309-NG4165/HPC39_5 | D26: 22-11-2024 | F26: 0 | G26: -20032274 | H26: 18252373 | I26: =G26+H26 -> -1779900.7 | K26: 23907.25 | L26: =K26/$K$3 -> 0.94574681 | M26: =-H26/$G$3 -> 0.91114835
A27: 26-11-2024 | B27: Settlement Posting-NG4165 | C27: DLV3-0309-NG4165/HPC39_5 | D27: 25-11-2024 | F27: 0 | G27: -20032274 | H27: 18252373 | I27: =G27+H27 -> -1779900.7 | K27: 24221.9 | L27: =K27/$K$3 -> 0.95819405 | M27: =-H27/$G$3 -> 0.91114835
A28: 27-11-2024 | B28: Settlement Posting-NG4165 | C28: DLV3-0309-NG4165/HPC39_5 | D28: 26-11-2024 | F28: 0 | G28: -20032274 | H28: 18430398 | I28: =G28+H28 -> -1601875.7 | K28: 24194.5 | L28: =K28/$K$3 -> 0.95711014 | M28: =-H28/$G$3 -> 0.92003525
A29: 28-11-2024 | B29: Settlement Posting-NG4165 | C29: DLV3-0309-NG4165/HPC39_5 | D29: 27-11-2024 | F29: 0 | G29: -20032274 | H29: 18694188 | I29: =G29+H29 -> -1338085.7 | K29: 24274.9 | L29: =K29/$K$3 -> 0.96029068 | M29: =-H29/$G$3 -> 0.93320351
A30: 29-11-2024 | B30: Settlement Posting-NG4165 | C30: DLV3-0309-NG4165/HPC39_5 | D30: 28-11-2024 | F30: 0 | G30: -20032274 | H30: 18898033 | I30: =G30+H30 -> -1134240.7 | K30: 23914.15 | L30: =K30/$K$3 -> 0.94601977 | M30: =-H30/$G$3 -> 0.94337933
A31: 45334 | B31: Settlement Posting-NG4165 | C31: DLV3-0309-NG4165/HPC39_5 | D31: 29-11-2024 | F31: 0 | G31: -20032274 | H31: 18902497 | I31: =G31+H31 -> -1129776.7 | K31: 24131.1 | L31: =K31/$K$3 -> 0.9546021 | M31: =-H31/$G$3 -> 0.94360218
A32: 45363 | B32: Settlement Posting-NG4165 | C32: DLV3-0309-NG4165/HPC39_5 | D32: 45334 | F32: 0 | G32: -20032274 | H32: 19093250 | I32: =G32+H32 -> -939023.66 | K32: 24276.05 | L32: =K32/$K$3 -> 0.96033617 | M32: =-H32/$G$3 -> 0.95312446
A33: 45394 | B33: Settlement Posting-NG4165 | C33: DLV3-0309-NG4165/HPC39_5 | D33: 45363 | F33: 0 | G33: -20032274 | H33: 19255787 | I33: =G33+H33 -> -776486.66 | K33: 24457.15 | L33: =K33/$K$3 -> 0.96750031 | M33: =-H33/$G$3 -> 0.96123822
A34: 45424 | B34: Settlement Posting-NG4165 | C34: DLV3-0309-NG4165/HPC39_5 | D34: 45394 | F34: 0 | G34: -20032274 | H34: 19423700 | I34: =G34+H34 -> -608573.66 | K34: 24467.45 | L34: =K34/$K$3 -> 0.96790776 | M34: =-H34/$G$3 -> 0.96962034
A35: 45455 | B35: Settlement Posting-NG4165 | C35: DLV3-0309-NG4165/HPC39_5 | D35: 45424 | F35: 0 | G35: -20032274 | H35: 19776143 | I35: =G35+H35 -> -256130.66 | K35: 24708.4 | L35: =K35/$K$3 -> 0.9774395 | M35: =-H35/$G$3 -> 0.9872141
A36: 45547 | B36: Settlement Posting-NG4231 | C36: DLV1-0912-NG4231/HPC39_5 | D36: 45455 | E36: 0 | F36: 1040095.9 | G36: -18992180 | H36: 19997329 | I36: =G36+H36 -> 1005148.5 | K36: 24677.8 | L36: =K36/$K$3 -> 0.976229 | M36: =-H36/$G$3 -> 0.99825558
A37: 45547 | B37: Settlement Posting-NU4231 | C37: DLV1-0912-NU4231/HPC39_5 | D37: 45455 | E37: 1444239.7 | F37: 0 | G37: -20436420 | H37: 19997329 | I37: =G37+H37 -> -439091.14 | K37: 24619 | L37: =K37/$K$3 -> 0.97390293 | M37: =-H37/$G$3 -> 0.99825558
A38: 45577 | B38: Settlement Posting-NU4231 | C38: DLV1-0912-NU4231/HPC39_5 | D38: 45547 | F38: 0 | G38: -20436420 | H38: 20295915 | I38: =G38+H38 -> -140505.14 | K38: 24610.05 | L38: =K38/$K$3 -> 0.97354888 | M38: =-H38/$G$3 -> 1.0131608
A39: 45608 | B39: Settlement Posting-NU4231 | C39: DLV1-0912-NU4231/HPC39_5 | D39: 45577 | F39: 0 | G39: -20436420 | H39: 20232458 | I39: =G39+H39 -> -203962.14 | K39: 24641.8 | L39: =K39/$K$3 -> 0.97480488 | M39: =-H39/$G$3 -> 1.0099931
A40: 45638 | B40: Settlement Posting-NU4231 | C40: DLV1-0912-NU4231/HPC39_5 | D40: 45608 | F40: 0 | G40: -20436420 | H40: 20334090 | I40: =G40+H40 -> -102330.14 | K40: 24548.7 | L40: =K40/$K$3 -> 0.97112193 | M40: =-H40/$G$3 -> 1.0150665
A41: 13-12-2024 | B41: Settlement Posting-NU4231 | C41: DLV1-0912-NU4231/HPC39_5 | D41: 45638 | F41: 0 | G41: -20436420 | H41: 20197513 | I41: =G41+H41 -> -238907.14 | K41: 24768.3 | L41: =K41/$K$3 -> 0.97980909 | M41: =-H41/$G$3 -> 1.0082487
A42: 16-12-2024 | B42: Settlement Posting-NU4231 | C42: DLV1-0912-NU4231/HPC39_5 | D42: 13-12-2024 | F42: 0 | G42: -20436420 | H42: 20132383 | I42: =G42+H42 -> -304037.14 | K42: 24668.25 | L42: =K42/$K$3 -> 0.97585121 | M42: =-H42/$G$3 -> 1.0049974
A43: 17-12-2024 | B43: Settlement Posting-NU4231 | C43: DLV1-0912-NU4231/HPC39_5 | D43: 16-12-2024 | F43: 0 | G43: -20436420 | H43: 20438957 | I43: =G43+H43 -> 2536.86 | K43: 24336 | L43: =K43/$K$3 -> 0.96270773 | M43: =-H43/$G$3 -> 1.0203014
A44: 18-12-2024 | B44: Settlement Posting-NU4231 | C44: DLV1-0912-NU4231/HPC39_5 | D44: 17-12-2024 | F44: 0 | G44: -20436420 | H44: 20509210 | I44: =G44+H44 -> 72789.86 | K44: 24198.85 | L44: =K44/$K$3 -> 0.95728222 | M44: =-H44/$G$3 -> 1.0238084
A45: 19-12-2024 | B45: Settlement Posting-NU4231 | C45: DLV1-0912-NU4231/HPC39_5 | D45: 18-12-2024 | F45: 0 | G45: -20436420 | H45: 20219478 | I45: =G45+H45 -> -216942.14 | K45: 23951.7 | L45: =K45/$K$3 -> 0.94750521 | M45: =-H45/$G$3 -> 1.0093451
A46: 20-12-2024 | B46: Settlement Posting-NU4231 | C46: DLV1-0912-NU4231/HPC39_5 | D46: 19-12-2024 | F46: 0 | G46: -20436420 | H46: 20275255 | I46: =G46+H46 -> -161165.14 | K46: 23587.5 | L46: =K46/$K$3 -> 0.93309783 | M46: =-H46/$G$3 -> 1.0121295
A47: 45649 | B47: Settlement Posting-NU4231 | C47: DLV1-0912-NU4231/HPC39_5 | D47: 45646 | F47: 0 | G47: -20436420 | H47: 19895764 | I47: =G47+H47 -> -540656.14 | K47: 23753.45 | L47: =K47/$K$3 -> 0.93966264 | M47: =-H47/$G$3 -> 0.99318551
A48: 45650 | B48: Settlement Posting-NU4231 | C48: DLV1-0912-NU4231/HPC39_5 | D48: 45649 | F48: 0 | G48: -20436420 | H48: 19718128 | I48: =G48+H48 -> -718292.14 | K48: 23727.65 | L48: =K48/$K$3 -> 0.93864202 | M48: =-H48/$G$3 -> 0.98431802
A49: 45652 | B49: Settlement Posting-NU4231 | C49: DLV1-0912-NU4231/HPC39_5 | D49: 45650 | F49: 0 | G49: -20436420 | H49: 19681670 | I49: =G49+H49 -> -754750.14 | K49: 23750.2 | L49: =K49/$K$3 -> 0.93953407 | M49: =-H49/$G$3 -> 0.98249806
A50: 45653 | B50: Settlement Posting-NU4231 | C50: DLV1-0912-NU4231/HPC39_5 | D50: 45652 | F50: 0 | G50: -20436420 | H50: 19695386 | I50: =G50+H50 -> -741034.14 | K50: 23813.4 | L50: =K50/$K$3 -> 0.9420342 | M50: =-H50/$G$3 -> 0.98318275
A51: 45656 | B51: Settlement Posting-NU4231 | C51: DLV1-0912-NU4231/HPC39_5 | D51: 45653 | F51: 0 | G51: -20436420 | H51: 19711492 | I51: =G51+H51 -> -724928.14 | K51: 23644.9 | L51: =K51/$K$3 -> 0.93536851 | M51: =-H51/$G$3 -> 0.98398676
A52: 45657 | B52: Settlement Posting-NU4231 | C52: DLV1-0912-NU4231/HPC39_5 | D52: 45656 | F52: 0 | G52: -20436420 | H52: 19814514 | I52: =G52+H52 -> -621906.14 | K52: 23644.8 | L52: =K52/$K$3 -> 0.93536456 | M52: =-H52/$G$3 -> 0.98912956
A53: 45658 | B53: Settlement Posting-NU4231 | C53: DLV1-0912-NU4231/HPC39_5 | D53: 45657 | F53: 0 | G53: -20436420 | H53: 20002348 | I53: =G53+H53 -> -434072.14 | K53: 23742.9 | L53: =K53/$K$3 -> 0.93924529 | M53: =-H53/$G$3 -> 0.99850613
A54: 45659 | B54: Settlement Posting-NU4231 | C54: DLV1-0912-NU4231/HPC39_5 | D54: 45658 | F54: 0 | G54: -20436420 | H54: 20215397 | I54: =G54+H54 -> -221023.14 | K54: 24188.65 | L54: =K54/$K$3 -> 0.95687872 | M54: =-H54/$G$3 -> 1.0091414
A55: 45660 | B55: Settlement Posting-NU4231 | C55: DLV1-0912-NU4231/HPC39_5 | D55: 45659 | F55: 0 | G55: -20436420 | H55: 20388561 | I55: =G55+H55 -> -47859.14 | K55: 24004.75 | L55: =K55/$K$3 -> 0.94960382 | M55: =-H55/$G$3 -> 1.0177857
A56: 45663 | B56: Settlement Posting-NU4231 | C56: DLV1-0912-NU4231/HPC39_5 | D56: 45660 | F56: 0 | G56: -20436420 | H56: 20341983 | I56: =G56+H56 -> -94437.14 | K56: 23616.05 | L56: =K56/$K$3 -> 0.93422723 | M56: =-H56/$G$3 -> 1.0154605
A57: 45664 | B57: Settlement Posting-NU4231 | C57: DLV1-0912-NU4231/HPC39_5 | D57: 45663 | F57: 0 | G57: -20436420 | H57: 19522049 | I57: =G57+H57 -> -914371.14 | K57: 23707.9 | L57: =K57/$K$3 -> 0.93786073 | M57: =-H57/$G$3 -> 0.97452987
A58: 45665 | B58: Settlement Posting-NU4231 | C58: DLV1-0912-NU4231/HPC39_5 | D58: 45664 | F58: 0 | G58: -20436420 | H58: 19663037 | I58: =G58+H58 -> -773383.14 | K58: 23688.95 | L58: =K58/$K$3 -> 0.93711109 | M58: =-H58/$G$3 -> 0.98156791
... A99: 45722 | B99: Settlement Posting-NU4231 | C99: DLV1-0912-NU4231/HPC39_5 | D99: 45721 | F99: 0 | G99: -20436420 | H99: 14815700 | I99: =G99+H99 -> -5620720.1 | K99: 22544.7 | L99: =K99/$K$3 -> 0.8918457 | M99: =-H99/$G$3 -> 0.73959153
A100: 45723 | B100: Settlement Posting-NG5047 | C100: DLV2-0703-NG5047/HPC39_5 | D100: 45722 | E100: 0 | F100: 9468953.3 | G100: -10967467 | H100: 5541767 | I100: =G100+H100 -> -5425699.9 | K100: 22552.5 | L100: =K100/$K$3 -> 0.89215426 | M100: =-H100/$G$3 -> 0.27664194
A101: 45726 | B101: Settlement Posting-NG5047 | C101: DLV2-0703-NG5047/HPC39_5 | D101: 45723 | E101: 0 | F101: 850583.33 | G101: -10116884 | H101: 5541767 | I101: =G101+H101 -> -4575116.8 | K101: 22460.3 | L101: =K101/$K$3 -> 0.88850692 | M101: =-H101/$G$3 -> 0.27664194
A102: 45727 | B102: Settlement Posting-NG5049 | C102: DLV1-1103-NG5049/HPC39_5 | D102: 45726 | E102: 9856893.5 | F102: 0 | G102: -19973777 | H102: 14244817 | I102: =G102+H102 -> -5728960 | K102: 22497.9 | L102: =K102/$K$3 -> 0.88999434 | M102: =-H102/$G$3 -> 0.71109337
A103: 45728 | B103: Settlement Posting-NG5049 | C103: DLV1-1103-NG5049/HPC39_5 | D103: 45727 | F103: 0 | G103: -19973777 | H103: 14157971 | I103: =G103+H103 -> -5815806 | K103: 22470.5 | L103: =K103/$K$3 -> 0.88891043 | M103: =-H103/$G$3 -> 0.70675807
A104: 45729 | B104: Settlement Posting-NG5049 | C104: DLV1-1103-NG5049/HPC39_5 | D104: 45728 | F104: 0 | G104: -19973777 | H104: 14132624 | I104: =G104+H104 -> -5841153 | K104: 22397.2 | L104: =K104/$K$3 -> 0.88601075 | M104: =-H104/$G$3 -> 0.70549276
A105: 45733 | B105: Settlement Posting-NG5049 | C105: DLV1-1103-NG5049/HPC39_5 | D105: 45729 | F105: 0 | G105: -19973777 | H105: 14119796 | I105: =G105+H105 -> -5853981 | K105: 22508.75 | L105: =K105/$K$3 -> 0.89042356 | M105: =-H105/$G$3 -> 0.70485239
A106: 45734 | B106: Settlement Posting-NG5049 | C106: DLV1-1103-NG5049/HPC39_5 | D106: 45733 | F106: 0 | G106: -19973777 | H106: 14234484 | I106: =G106+H106 -> -5739293 | K106: 22834.3 | L106: =K106/$K$3 -> 0.90330199 | M106: =-H106/$G$3 -> 0.71057755
A107: 45735 | B107: Settlement Posting-NG5049 | C107: DLV1-1103-NG5049/HPC39_5 | D107: 45734 | F107: 0 | G107: -19973777 | H107: 14581989 | I107: =G107+H107 -> -5391788 | K107: 22907.6 | L107: =K107/$K$3 -> 0.90620166 | M107: =-H107/$G$3 -> 0.72792481
A108: 45736 | B108: Settlement Posting-NG5049 | C108: DLV1-1103-NG5049/HPC39_5 | D108: 45735 | F108: 0 | G108: -19973777 | H108: 15089842 | I108: =G108+H108 -> -4883935 | K108: 23190.65 | L108: =K108/$K$3 -> 0.91739884 | M108: =-H108/$G$3 -> 0.75327655
A109: 45737 | B109: Settlement Posting-NG5049 | C109: DLV1-1103-NG5049/HPC39_5 | D109: 45736 | F109: 0 | G109: -19973777 | H109: 15242592 | I109: =G109+H109 -> -4731185 | K109: 23350.4 | L109: =K109/$K$3 -> 0.92371839 | M109: =-H109/$G$3 -> 0.76090175
A110: 45740 | B110: Settlement Posting-NG5049 | C110: DLV1-1103-NG5049/HPC39_5 | D110: 45737 | F110: 0 | G110: -19973777 | H110: 15490002 | I110: =G110+H110 -> -4483775 | K110: 23658.35 | L110: =K110/$K$3 -> 0.93590058 | M110: =-H110/$G$3 -> 0.77325232
A111: 45741 | B111: Settlement Posting-NG5049 | C111: DLV1-1103-NG5049/HPC39_5 | D111: 45740 | F111: 0 | G111: -19973777 | H111: 15643593 | I111: =G111+H111 -> -4330184 | K111: 23668.65 | L111: =K111/$K$3 -> 0.93630804 | M111: =-H111/$G$3 -> 0.78091949
A112: 45742 | B112: Settlement Posting-NG5049 | C112: DLV1-1103-NG5049/HPC39_5 | D112: 45741 | F112: 0 | G112: -19973777 | H112: 15496029 | I112: =G112+H112 -> -4477748 | K112: 23486.85 | L112: =K112/$K$3 -> 0.92911621 | M112: =-H112/$G$3 -> 0.77355318
A113: 45743 | B113: Settlement Posting-NG5049 | C113: DLV1-1103-NG5049/HPC39_5 | D113: 45742 | F113: 0 | G113: -19973777 | H113: 15296878 | I113: =G113+H113 -> -4676899 | K113: 23591.95 | L113: =K113/$K$3 -> 0.93327386 | M113: =-H113/$G$3 -> 0.76361167
A114: 45744 | B114: Settlement Posting-NG5049 | C114: DLV1-1103-NG5049/HPC39_5 | D114: 45743 | F114: 0 | G114: -19973777 | H114: 15708534 | I114: =G114+H114 -> -4265243 | K114: 23519.35 | L114: =K114/$K$3 -> 0.93040188 | M114: =-H114/$G$3 -> 0.78416131
... A156: 45811 | B156: Settlement Posting-NG5049 | C156: DLV1-1103-NG5049/HPC39_5 | D156: 45810 | F156: 0 | G156: -19973777 | H156: 19353955 | I156: =G156+H156 -> -619822.05 | K156: 23328.55 | L156: =K156/$K$3 -> 0.92285402 | M156: =-H156/$G$3 -> 0.96613871
A157: 45812 | B157: Settlement Posting-NG5104 | C157: DLV4-0406-NG5104/HPC39_5 | D157: 45811 | E157: 0 | F157: 1126351.6 | G157: -18847426 | H157: 19611766 | I157: =G157+H157 -> 764340.11
A158: 45812 | B158: Settlement Posting-NU5104 | C158: DLV1-0406-NU5104/HPC39_5 | D158: 45811 | E158: 1133779.6 | F158: 0 | G158: -19981206 | H158: 19611766 | I158: =G158+H158 -> -369439.54
A159: 45813 | B159: Settlement Posting-NU5104 | C159: DLV1-0406-NU5104/HPC39_5 | D159: 45812 | F159: 0 | G159: -19981206 | H159: 19436799 | I159: =G159+H159 -> -544406.54
A160: 45814 | B160: Settlement Posting-NU5104 | C160: DLV1-0406-NU5104/HPC39_5 | D160: 45813 | F160: 0 | G160: -19981206 | H160: 19569757 | I160: =G160+H160 -> -411448.54
A161: 45817 | B161: Settlement Posting-NU5104 | C161: DLV1-0406-NU5104/HPC39_5 | D161: 45814 | F161: 0 | G161: -19981206 | H161: 19566898 | I161: =G161+H161 -> -414307.54
A162: 45818 | B162: Settlement Posting-NU5104 | C162: DLV1-0406-NU5104/HPC39_5 | D162: 45817 | F162: 0 | G162: -19981206 | H162: 20091866 | I162: =G162+H162 -> 110660.46
A163: 45819 | B163: Settlement Posting-NU5104 | C163: DLV1-0406-NU5104/HPC39_5 | D163: 45818 | F163: 0 | G163: -19981206 | H163: 20173490 | I163: =G163+H163 -> 192284.46
A164: 45820 | B164: Settlement Posting-NU5104 | C164: DLV1-0406-NU5104/HPC39_5 | D164: 45819 | F164: 0 | G164: -19981206 | H164: 20272556 | I164: =G164+H164 -> 291350.46
A165: 45821 | B165: Settlement Posting-NU5104 | C165: DLV1-0406-NU5104/HPC39_5 | D165: 45820 | F165: 0 | G165: -19981206 | H165: 19893139 | I165: =G165+H165 -> -88066.54
A166: 45824 | B166: Settlement Posting-NU5104 | C166: DLV1-0406-NU5104/HPC39_5 | D166: 45821 | F166: 0 | G166: -19981206 | H166: 19839722 | I166: =G166+H166 -> -141483.54
A167: 45825 | B167: Settlement Posting-NU5104 | C167: DLV1-0406-NU5104/HPC39_5 | D167: 45824 | F167: 0 | G167: -19981206 | H167: 19904229 | I167: =G167+H167 -> -76976.54
A168: 45826 | B168: Settlement Posting-NU5104 | C168: DLV1-0406-NU5104/HPC39_5 | D168: 45825 | F168: 0 | G168: -19981206 | H168: 19786751 | I168: =G168+H168 -> -194454.54
A169: 45827 | B169: Settlement Posting-NU5104 | C169: DLV1-0406-NU5104/HPC39_5 | D169: 45826 | F169: 0 | G169: -19981206 | H169: 19787684 | I169: =G169+H169 -> -193521.54
A170: 45828 | B170: Settlement Posting-NU5104 | C170: DLV1-0406-NU5104/HPC39_5 | D170: 45827 | F170: 0 | G170: -19981206 | H170: 19387303 | I170: =G170+H170 -> -593902.54
... A220: 45902 | B220: Settlement Posting-NU5104 | C220: DLV1-0406-NU5104/HPC39_5 | D220: 45901 | F220: 0 | G220: -19981206 | H220: 19193926 | I220: =G220+H220 -> -787279.54
A221: 45903 | B221: Settlement Posting-NG5167 | C221: DLV3-0309-NG5167/HPC39_5 | D221: 45902 | E221: 0 | F221: 7525912.1 | G221: -12455294 | H221: 11672701 | I221: =G221+H221 -> -782592.62
A222: 45904 | B222: Settlement Posting-NG5167 | C222: DLV3-0309-NG5167/HPC39_5 | D222: 45903 | E222: 0 | G222: -12455294 | H222: 11838513 | I222: =G222+H222 -> -616780.62
A223: 45909 | B223: Settlement Posting-NG5167 | C223: DLV3-0309-NG5167/HPC39_5 | D223: 45904 | E223: 0 | G223: -12455294 | H223: 11658685 | I223: =G223+H223 -> -796608.62
A224: 45909 | B224: Settlement Posting-NG5167 | C224: DLV3-0309-NG5167/HPC39_5 | D224: 45905 | E224: 0 | G224: -12455294 | H224: 11757924 | I224: =G224+H224 -> -697369.62
A225: 45910 | B225: Settlement Posting-NG5167 | C225: DLV3-0309-NG5167/HPC39_5 | D225: 45908 | E225: 0 | G225: -12455294 | H225: 11736002 | I225: =G225+H225 -> -719291.62
A226: 45910 | B226: Settlement Posting-NG5167 | C226: DLV3-0309-NG5167/HPC39_5 | D226: 45909 | E226: 0 | G226: -12455294 | H226: 11810733 | I226: =G226+H226 -> -644560.62
A227: 45911 | B227: Settlement Posting-NG5167 | C227: DLV3-0309-NG5167/HPC39_5 | D227: 45910 | E227: 0 | G227: -12455294 | H227: 11841898 | I227: =G227+H227 -> -613395.62
A228: 45912 | B228: Settlement Posting-NG5167 | C228: DLV3-0309-NG5167/HPC39_5 | D228: 45911 | E228: 0 | G228: -12455294 | H228: 11731466 | I228: =G228+H228 -> -723827.62
A229: 45915 | B229: Settlement Posting-NG5167 | C229: DLV3-0309-NG5167/HPC39_5 | D229: 45912 | E229: 0 | G229: -12455294 | H229: 11805077 | I229: =G229+H229 -> -650216.62
A230: 45916 | B230: Settlement Posting-NG5167 | C230: DLV3-0309-NG5167/HPC39_5 | D230: 45915 | E230: 0 | G230: -12455294 | H230: 11868271 | I230: =G230+H230 -> -587022.62
...

Sheet hpc39_7 cash ledger
E1: dr | F1: cr | G1: net | H1: holding | I1: p&l
A2: 18-11-2024 | B2: Settlement Posting-NG4217 | C2: DLV1-1811-NG4217/HPC39_7 | D2: 14-11-2024 | E2: 20068248 | F2: 0 | G2: -20068248 | H2: 19929592 | I2: =G2+H2 -> -138655.97
A3: 19-11-2024 | B3: Settlement Posting-NG4217 | C3: DLV1-1811-NG4217/HPC39_7 | D3: 18-11-2024 | F3: 0 | G3: -20068248 | H3: 19887263 | I3: =G3+H3 -> -180984.97
A4: 21-11-2024 | B4: Settlement Posting-NG4217 | C4: DLV1-1811-NG4217/HPC39_7 | D4: 19-11-2024 | F4: 0 | G4: -20068248 | H4: 19979067 | I4: =G4+H4 -> -89180.97
A5: 22-11-2024 | B5: Settlement Posting-NG4217 | C5: DLV1-1811-NG4217/HPC39_7 | D5: 21-11-2024 | F5: 0 | G5: -20068248 | H5: 19967609 | I5: =G5+H5 -> -100638.97
A6: 25-11-2024 | B6: Settlement Posting-NG4217 | C6: DLV1-1811-NG4217/HPC39_7 | D6: 22-11-2024 | F6: 0 | G6: -20068248 | H6: 20301562 | I6: =G6+H6 -> 233314.03
A7: 26-11-2024 | B7: Settlement Posting-NG4217 | C7: DLV1-1811-NG4217/HPC39_7 | D7: 25-11-2024 | F7: 0 | G7: -20068248 | H7: 20693123 | I7: =G7+H7 -> 624875.03
A8: 27-11-2024 | B8: Settlement Posting-NG4217 | C8: DLV1-1811-NG4217/HPC39_7 | D8: 26-11-2024 | F8: 0 | G8: -20068248 | H8: 20578829 | I8: =G8+H8 -> 510581.03
A9: 28-11-2024 | B9: Settlement Posting-NG4217 | C9: DLV1-1811-NG4217/HPC39_7 | D9: 27-11-2024 | F9: 0 | G9: -20068248 | H9: 20685180 | I9: =G9+H9 -> 616932.03
A10: 29-11-2024 | B10: Settlement Posting-NG4217 | C10: DLV1-1811-NG4217/HPC39_7 | D10: 28-11-2024 | F10: 0 | G10: -20068248 | H10: 20529503 | I10: =G10+H10 -> 461255.03
A11: 45334 | B11: Settlement Posting-NG4217 | C11: DLV1-1811-NG4217/HPC39_7 | D11: 29-11-2024 | F11: 0 | G11: -20068248 | H11: 20710214 | I11: =G11+H11 -> 641966.03
A12: 45363 | B12: Settlement Posting-NG4217 | C12: DLV1-1811-NG4217/HPC39_7 | D12: 45334 | F12: 0 | G12: -20068248 | H12: 21040888 | I12: =G12+H12 -> 972640.03
A13: 45394 | B13: Settlement Posting-NG4217 | C13: DLV1-1811-NG4217/HPC39_7 | D13: 45363 | F13: 0 | G13: -20068248 | H13: 21196013 | I13: =G13+H13 -> 1127765
A14: 45424 | B14: Settlement Posting-NG4217 | C14: DLV1-1811-NG4217/HPC39_7 | D14: 45394 | F14: 0 | G14: -20068248 | H14: 21236088 | I14: =G14+H14 -> 1167840
A15: 45455 | B15: Settlement Posting-NG4217 | C15: DLV1-1811-NG4217/HPC39_7 | D15: 45424 | F15: 0 | G15: -20068248 | H15: 21236088 | I15: =G15+H15 -> 1167840
A16: 45547 | B16: Settlement Posting-NG4217 | C16: DLV1-1811-NG4217/HPC39_7 | D16: 45455 | F16: 0 | G16: -20068248 | H16: 21619032 | I16: =G16+H16 -> 1550784
A17: 45636 | B17: Settlement Posting-NG4211 | C17: DLV2-0711-NG4211/HPC39_6 | D17: 45635 | F17: 0 | G17: -20068248 | H17: 21590420 | I17: =G17+H17 -> 1522172
A18: 45637 | B18: Settlement Posting-NG4211 | C18: DLV2-0711-NG4211/HPC39_6 | D18: 45636 | F18: 0 | G18: -20068248 | H18: 21589440 | I18: =G18+H18 -> 1521192
A19: 45638 | B19: Settlement Posting-NG4211 | C19: DLV2-0711-NG4211/HPC39_6 | D19: 45637 | F19: 0 | G19: -20068248 | H19: 21722500 | I19: =G19+H19 -> 1654252
